Workbook

Sheet Summary- FY 25-26
A1: CEO Of the Quarter | J1: Job Well Done
A3: Region / Quarters | B3: Q1-FY26 | C3: Q2-FY26 | D3: Q3-FY26 | E3: Q4-FY26 | F3: Total | J3: Region / Quarters | K3: Q1-FY26 | L3: Q2-FY26 | M3: Q3-FY26 | N3: Q4-FY26 | O3: Total
A4: Corporate | B4: =COUNTIFS('CEO of the Qtr'!$H:$H,'Summary- FY 25-26'!$A$4,'CEO of the Qtr'!$I:$I,'Summary- FY 25-26'!B3) -> 9 | C4: =COUNTIFS('CEO of the Qtr'!$H:$H,'Summary- FY 25-26'!$A$4,'CEO of the Qtr'!$I:$I,'Summary- FY 25-26'!C3) -> 0 | D4: =COUNTIFS('CEO of the Qtr'!$H:$H,'Summary- FY 25-26'!$A$4,'CEO of the Qtr'!$I:$I,'Summary- FY 25-26'!D3) -> 0 | E4: =COUNTIFS('CEO of the Qtr'!$H:$H,'Summary- FY 25-26'!$A$4,'CEO of the Qtr'!$I:$I,'Summary- FY 25-26'!E3) -> 0 | F4: =SUM(B4:E4) -> 9 | J4: Corporate | K4: =COUNTIFS('Job Well Done'!$F:$F,K3,'Job Well Done'!$J:$J,$J$4) -> 6 | L4: =COUNTIFS('Job Well Done'!$F:$F,L3,'Job Well Done'!$J:$J,$J$4) -> 0 | M4: =COUNTIFS('Job Well Done'!$F:$F,M3,'Job Well Done'!$J:$J,$J$4) -> 0 | N4: =COUNTIFS('Job Well Done'!$F:$F,N3,'Job Well Done'!$J:$J,$J$4) -> 0 | O4: =SUM(K4:N4) -> 6
A5: West | B5: =COUNTIFS('CEO of the Qtr'!$H:$H,'Summary- FY 25-26'!$A$5,'CEO of the Qtr'!$I:$I,'Summary- FY 25-26'!B3) -> 0 | C5: =COUNTIFS('CEO of the Qtr'!$H:$H,'Summary- FY 25-26'!$A$5,'CEO of the Qtr'!$I:$I,'Summary- FY 25-26'!C3) -> 0 | D5: =COUNTIFS('CEO of the Qtr'!$H:$H,'Summary- FY 25-26'!$A$5,'CEO of the Qtr'!$I:$I,'Summary- FY 25-26'!D3) -> 0 | E5: =COUNTIFS('CEO of the Qtr'!$H:$H,'Summary- FY 25-26'!$A$5,'CEO of the Qtr'!$I:$I,'Summary- FY 25-26'!E3) -> 0 | F5: =SUM(B5:E5) -> 0 | J5: West | K5: =COUNTIFS('Job Well Done'!$F:$F,K3,'Job Well Done'!$J:$J,$J$5) -> 5 | L5: =COUNTIFS('Job Well Done'!$F:$F,L3,'Job Well Done'!$J:$J,$J$5) -> 0 | M5: =COUNTIFS('Job Well Done'!$F:$F,M3,'Job Well Done'!$J:$J,$J$5) -> 0 | N5: =COUNTIFS('Job Well Done'!$F:$F,N3,'Job Well Done'!$J:$J,$J$5) -> 0 | O5: =SUM(K5:N5) -> 5
A6: East | B6: =COUNTIFS('CEO of the Qtr'!$H:$H,'Summary- FY 25-26'!$A$6,'CEO of the Qtr'!$I:$I,'Summary- FY 25-26'!B3) -> 0 | C6: =COUNTIFS('CEO of the Qtr'!$H:$H,'Summary- FY 25-26'!$A$6,'CEO of the Qtr'!$I:$I,'Summary- FY 25-26'!C3) -> 0 | D6: =COUNTIFS('CEO of the Qtr'!$H:$H,'Summary- FY 25-26'!$A$6,'CEO of the Qtr'!$I:$I,'Summary- FY 25-26'!D3) -> 0 | E6: =COUNTIFS('CEO of the Qtr'!$H:$H,'Summary- FY 25-26'!$A$6,'CEO of the Qtr'!$I:$I,'Summary- FY 25-26'!E3) -> 0 | F6: =SUM(B6:E6) -> 0 | J6: East | K6: =COUNTIFS('Job Well Done'!$F:$F,K3,'Job Well Done'!$J:$J,$J$6) -> 2 | L6: =COUNTIFS('Job Well Done'!$F:$F,L3,'Job Well Done'!$J:$J,$J$6) -> 0 | M6: =COUNTIFS('Job Well Done'!$F:$F,M3,'Job Well Done'!$J:$J,$J$6) -> 0 | N6: =COUNTIFS('Job Well Done'!$F:$F,N3,'Job Well Done'!$J:$J,$J$6) -> 0 | O6: =SUM(K6:N6) -> 2
A7: North | B7: =COUNTIFS('CEO of the Qtr'!$H:$H,'Summary- FY 25-26'!$A$7,'CEO of the Qtr'!$I:$I,'Summary- FY 25-26'!B3) -> 4 | C7: =COUNTIFS('CEO of the Qtr'!$H:$H,'Summary- FY 25-26'!$A$7,'CEO of the Qtr'!$I:$I,'Summary- FY 25-26'!C3) -> 0 | D7: =COUNTIFS('CEO of the Qtr'!$H:$H,'Summary- FY 25-26'!$A$7,'CEO of the Qtr'!$I:$I,'Summary- FY 25-26'!D3) -> 0 | E7: =COUNTIFS('CEO of the Qtr'!$H:$H,'Summary- FY 25-26'!$A$7,'CEO of the Qtr'!$I:$I,'Summary- FY 25-26'!E3) -> 0 | F7: =SUM(B7:E7) -> 4 | J7: North | K7: =COUNTIFS('Job Well Done'!$F:$F,K3,'Job Well Done'!$J:$J,$J$7) -> 3 | L7: =COUNTIFS('Job Well Done'!$F:$F,L3,'Job Well Done'!$J:$J,$J$7) -> 0 | M7: =COUNTIFS('Job Well Done'!$F:$F,M3,'Job Well Done'!$J:$J,$J$7) -> 0 | N7: =COUNTIFS('Job Well Done'!$F:$F,N3,'Job Well Done'!$J:$J,$J$7) -> 0 | O7: =SUM(K7:N7) -> 3
A8: South | B8: =COUNTIFS('CEO of the Qtr'!$H:$H,'Summary- FY 25-26'!$A$8,'CEO of the Qtr'!$I:$I,'Summary- FY 25-26'!B3) -> 14 | C8: =COUNTIFS('CEO of the Qtr'!$H:$H,'Summary- FY 25-26'!$A$8,'CEO of the Qtr'!$I:$I,'Summary- FY 25-26'!C3) -> 0 | D8: =COUNTIFS('CEO of the Qtr'!$H:$H,'Summary- FY 25-26'!$A$8,'CEO of the Qtr'!$I:$I,'Summary- FY 25-26'!D3) -> 0 | E8: =COUNTIFS('CEO of the Qtr'!$H:$H,'Summary- FY 25-26'!$A$8,'CEO of the Qtr'!$I:$I,'Summary- FY 25-26'!E3) -> 0 | F8: =SUM(B8:E8) -> 14 | J8: South | K8: =COUNTIFS('Job Well Done'!$F:$F,K3,'Job Well Done'!$J:$J,$J$8) -> 5 | L8: =COUNTIFS('Job Well Done'!$F:$F,L3,'Job Well Done'!$J:$J,$J$8) -> 0 | M8: =COUNTIFS('Job Well Done'!$F:$F,M3,'Job Well Done'!$J:$J,$J$8) -> 0 | N8: =COUNTIFS('Job Well Done'!$F:$F,N3,'Job Well Done'!$J:$J,$J$8) -> 0 | O8: =SUM(K8:N8) -> 5
A9: Total | B9: =SUM(B4:B8) -> 27 | C9: =SUM(C4:C8) -> 0 | D9: =SUM(D4:D8) -> 0 | E9: =SUM(E4:E8) -> 0 | F9: =SUM(B9:E9) -> 27 | J9: Total | K9: =SUM(K4:K8) -> 21 | L9: =SUM(L4:L8) -> 0 | M9: =SUM(M4:M8) -> 0 | N9: =SUM(N4:N8) -> 0 | O9: =SUM(K9:N9) -> 21
A11: SPOT and SPOT of the Month | J11: Intrafunctional
B13: FY25-26 | C13: FY25-26 | J13: Q1-FY26 | K13: Q2-FY26 | L13: Q3-FY26 | M13: Q4-FY26 | N13: Total
A14: Region / Quarters | B14: SPOT | C14: Spot of the Month | J14: 2 | K14: 0 | L14: 0 | M14: 0 | N14: =SUM(J14:M14) -> 2
A15: Corporate | B15: =COUNTIFS('Spot & Spot of the Month'!$I:$I,A15,'Spot & Spot of the Month'!$F:$F,$B$14,'Spot & Spot of the Month'!L:L,'Summary- FY 25-26'!$B$13) -> 26 | C15: =COUNTIFS('Spot & Spot of the Month'!$I:$I,A15,'Spot & Spot of the Month'!$F:$F,$C$14,'Spot & Spot of the Month'!L:L,'Summary- FY 25-26'!$C$13) -> 28
A16: West | B16: =COUNTIFS('Spot & Spot of the Month'!$I:$I,A16,'Spot & Spot of the Month'!$F:$F,$B$14,'Spot & Spot of the Month'!L:L,'Summary- FY 25-26'!$B$13) -> 3 | C16: =COUNTIFS('Spot & Spot of the Month'!$I:$I,A16,'Spot & Spot of the Month'!$F:$F,$C$14,'Spot & Spot of the Month'!L:L,'Summary- FY 25-26'!$C$13) -> 2
A17: East | B17: =COUNTIFS('Spot & Spot of the Month'!$I:$I,A17,'Spot & Spot of the Month'!$F:$F,$B$14,'Spot & Spot of the Month'!L:L,'Summary- FY 25-26'!$B$13) -> 5 | C17: =COUNTIFS('Spot & Spot of the Month'!$I:$I,A17,'Spot & Spot of the Month'!$F:$F,$C$14,'Spot & Spot of the Month'!L:L,'Summary- FY 25-26'!$C$13) -> 9
A18: North | B18: =COUNTIFS('Spot & Spot of the Month'!$I:$I,A18,'Spot & Spot of the Month'!$F:$F,$B$14,'Spot & Spot of the Month'!L:L,'Summary- FY 25-26'!$B$13) -> 11 | C18: =COUNTIFS('Spot & Spot of the Month'!$I:$I,A18,'Spot & Spot of the Month'!$F:$F,$C$14,'Spot & Spot of the Month'!L:L,'Summary- FY 25-26'!$C$13) -> 13
A19: South | B19: =COUNTIFS('Spot & Spot of the Month'!$I:$I,A19,'Spot & Spot of the Month'!$F:$F,$B$14,'Spot & Spot of the Month'!L:L,'Summary- FY 25-26'!$B$13) -> 41 | C19: =COUNTIFS('Spot & Spot of the Month'!$I:$I,A19,'Spot & Spot of the Month'!$F:$F,$C$14,'Spot & Spot of the Month'!L:L,'Summary- FY 25-26'!$C$13) -> 42
A21: Debutant of the Quarter | J21: Cross Functional
A22: Region / Quarters | B22: Q1-FY26 | C22: Q2-FY26 | D22: Q3-FY26 | E22: Q4-FY26 | F22: Total
A23: Corporate | B23: =COUNTIFS('Debutant of the Qtr'!$F:$F,B22,'Debutant of the Qtr'!$J:$J,'Summary- FY 25-26'!$A$23) -> 3 | C23: =COUNTIFS('Debutant of the Qtr'!$F:$F,C22,'Debutant of the Qtr'!$J:$J,'Summary- FY 25-26'!$A$23) -> 0 | D23: =COUNTIFS('Debutant of the Qtr'!$F:$F,D22,'Debutant of the Qtr'!$J:$J,'Summary- FY 25-26'!$A$23) -> 0 | E23: =COUNTIFS('Debutant of the Qtr'!$F:$F,E22,'Debutant of the Qtr'!$J:$J,'Summary- FY 25-26'!$A$23) -> 0 | F23: =COUNTIFS('Debutant of the Qtr'!$F:$F,F22,'Debutant of the Qtr'!$J:$J,'Summary- FY 25-26'!$A$23) -> 0 | J23: Q1-FY26 | K23: Q2-FY26 | L23: Q3-FY26 | M23: Q4-FY26 | N23: Total
A24: West | B24: =COUNTIFS('Debutant of the Qtr'!$F:$F,B22,'Debutant of the Qtr'!$J:$J,'Summary- FY 25-26'!$A$24) -> 0 | C24: =COUNTIFS('Debutant of the Qtr'!$F:$F,C22,'Debutant of the Qtr'!$J:$J,'Summary- FY 25-26'!$A$24) -> 0 | D24: =COUNTIFS('Debutant of the Qtr'!$F:$F,D22,'Debutant of the Qtr'!$J:$J,'Summary- FY 25-26'!$A$24) -> 0 | E24: =COUNTIFS('Debutant of the Qtr'!$F:$F,E22,'Debutant of the Qtr'!$J:$J,'Summary- FY 25-26'!$A$24) -> 0 | F24: =COUNTIFS('Debutant of the Qtr'!$F:$F,F22,'Debutant of the Qtr'!$J:$J,'Summary- FY 25-26'!$A$24) -> 0 | J24: 1 | K24: =COUNTIF(Sheet4!$G:$G,K23) -> 0 | L24: =COUNTIF(Sheet4!$G:$G,L23) -> 0 | M24: =COUNTIF(Sheet4!$G:$G,M23) -> 0 | N24: =SUM(J24:M24) -> 1
A25: East | B25: =COUNTIFS('Debutant of the Qtr'!$F:$F,B22,'Debutant of the Qtr'!$J:$J,'Summary- FY 25-26'!$A$25) -> 0 | C25: =COUNTIFS('Debutant of the Qtr'!$F:$F,C22,'Debutant of the Qtr'!$J:$J,'Summary- FY 25-26'!$A$25) -> 0 | D25: =COUNTIFS('Debutant of the Qtr'!$F:$F,D22,'Debutant of the Qtr'!$J:$J,'Summary- FY 25-26'!$A$25) -> 0 | E25: =COUNTIFS('Debutant of the Qtr'!$F:$F,E22,'Debutant of the Qtr'!$J:$J,'Summary- FY 25-26'!$A$25) -> 0 | F25: =COUNTIFS('Debutant of the Qtr'!$F:$F,F22,'Debutant of the Qtr'!$J:$J,'Summary- FY 25-26'!$A$25) -> 0
A26: North | B26: =COUNTIFS('Debutant of the Qtr'!$F:$F,B22,'Debutant of the Qtr'!$J:$J,'Summary- FY 25-26'!$A$26) -> 0 | C26: =COUNTIFS('Debutant of the Qtr'!$F:$F,C22,'Debutant of the Qtr'!$J:$J,'Summary- FY 25-26'!$A$26) -> 0 | D26: =COUNTIFS('Debutant of the Qtr'!$F:$F,D22,'Debutant of the Qtr'!$J:$J,'Summary- FY 25-26'!$A$26) -> 0 | E26: =COUNTIFS('Debutant of the Qtr'!$F:$F,E22,'Debutant of the Qtr'!$J:$J,'Summary- FY 25-26'!$A$26) -> 0 | F26: =COUNTIFS('Debutant of the Qtr'!$F:$F,F22,'Debutant of the Qtr'!$J:$J,'Summary- FY 25-26'!$A$26) -> 0
A27: South | B27: =COUNTIFS('Debutant of the Qtr'!$F:$F,B22,'Debutant of the Qtr'!$J:$J,'Summary- FY 25-26'!$A$27) -> 0 | C27: =COUNTIFS('Debutant of the Qtr'!$F:$F,C22,'Debutant of the Qtr'!$J:$J,'Summary- FY 25-26'!$A$27) -> 0 | D27: =COUNTIFS('Debutant of the Qtr'!$F:$F,D22,'Debutant of the Qtr'!$J:$J,'Summary- FY 25-26'!$A$27) -> 0 | E27: =COUNTIFS('Debutant of the Qtr'!$F:$F,E22,'Debutant of the Qtr'!$J:$J,'Summary- FY 25-26'!$A$27) -> 0 | F27: =COUNTIFS('Debutant of the Qtr'!$F:$F,F22,'Debutant of the Qtr'!$J:$J,'Summary- FY 25-26'!$A$27) -> 0
B30: People Champion | J30: Thank You
A31: Region / Quarters | C31: Total | J31: Region / Quarters | K31: Total
A32: Corporate | C32: =SUM(B32) -> 0 | J32: Corporate | K32: =COUNTIFS('Thank You'!$I:$I,'Summary- FY 25-26'!J32) -> 19
A33: South | C33: =SUM(B33) -> 0 | J33: West | K33: =COUNTIFS('Thank You'!$I:$I,'Summary- FY 25-26'!J33) -> 9
J34: East | K34: =COUNTIFS('Thank You'!$I:$I,'Summary- FY 25-26'!J34) -> 9
J35: North | K35: =COUNTIFS('Thank You'!$I:$I,'Summary- FY 25-26'!J35) -> 22
J36: South | K36: =COUNTIFS('Thank You'!$I:$I,'Summary- FY 25-26'!J36) -> 47

Sheet Summary- FY 24-25
A1: CEO Of the Quarter | J1: Job Well Done
A3: Region / Quarters | B3: Q3-FY24 | C3: Q4-FY24 | D3: Q1-FY25 | E3: Q2-FY 25 | F3: Q3-FY25 | G3: Q4-FY25 | H3: Total | J3: Region / Quarters | K3: Q3-FY24 | L3: Q4-FY24 | M3: Q1-FY25 | N3: Q2-FY25 | O3: Q3-FY25 | P3: Q4-FY25 | Q3: Total
A4: Corporate | B4: =COUNTIFS('CEO of the Qtr'!$H:$H,'Summary- FY 24-25'!$A$4,'CEO of the Qtr'!$I:$I,'Summary- FY 24-25'!B3) -> 8 | C4: =COUNTIFS('CEO of the Qtr'!$H:$H,'Summary- FY 24-25'!$A$4,'CEO of the Qtr'!$I:$I,'Summary- FY 24-25'!C3) -> 8 | D4: =COUNTIFS('CEO of the Qtr'!$H:$H,'Summary- FY 24-25'!$A$4,'CEO of the Qtr'!$I:$I,'Summary- FY 24-25'!D3) -> 7 | E4: =COUNTIFS('CEO of the Qtr'!$H:$H,'Summary- FY 24-25'!$A$4,'CEO of the Qtr'!$I:$I,'Summary- FY 24-25'!E3) -> 9 | F4: =COUNTIFS('CEO of the Qtr'!$H:$H,'Summary- FY 24-25'!$A$4,'CEO of the Qtr'!$I:$I,'Summary- FY 24-25'!F3) -> 7 | G4: =COUNTIFS('CEO of the Qtr'!$H:$H,'Summary- FY 24-25'!$A$4,'CEO of the Qtr'!$I:$I,'Summary- FY 24-25'!G3) -> 12 | H4: =SUM(B4:F4) -> 39 | J4: Corporate | K4: =COUNTIFS('Job Well Done'!$F:$F,K3,'Job Well Done'!$J:$J,$J$4) -> 3 | L4: =COUNTIFS('Job Well Done'!$F:$F,L3,'Job Well Done'!$J:$J,$J$4) -> 14 | M4: =COUNTIFS('Job Well Done'!$F:$F,M3,'Job Well Done'!$J:$J,$J$4) -> 5 | N4: =COUNTIFS('Job Well Done'!$F:$F,N3,'Job Well Done'!$J:$J,$J$4) -> 7 | O4: =COUNTIFS('Job Well Done'!$F:$F,O3,'Job Well Done'!$J:$J,$J$4) -> 5 | P4: =COUNTIFS('Job Well Done'!$F:$F,P3,'Job Well Done'!$J:$J,$J$4) -> 10 | Q4: =SUM(K4:O4) -> 34
A5: West | B5: =COUNTIFS('CEO of the Qtr'!$H:$H,'Summary- FY 24-25'!$A$5,'CEO of the Qtr'!$I:$I,'Summary- FY 24-25'!B3) -> 5 | C5: =COUNTIFS('CEO of the Qtr'!$H:$H,'Summary- FY 24-25'!$A$5,'CEO of the Qtr'!$I:$I,'Summary- FY 24-25'!C3) -> 3 | D5: =COUNTIFS('CEO of the Qtr'!$H:$H,'Summary- FY 24-25'!$A$5,'CEO of the Qtr'!$I:$I,'Summary- FY 24-25'!D3) -> 10 | E5: =COUNTIFS('CEO of the Qtr'!$H:$H,'Summary- FY 24-25'!$A$5,'CEO of the Qtr'!$I:$I,'Summary- FY 24-25'!E3) -> 5 | F5: =COUNTIFS('CEO of the Qtr'!$H:$H,'Summary- FY 24-25'!$A$5,'CEO of the Qtr'!$I:$I,'Summary- FY 24-25'!F3) -> 2 | G5: =COUNTIFS('CEO of the Qtr'!$H:$H,'Summary- FY 24-25'!$A$5,'CEO of the Qtr'!$I:$I,'Summary- FY 24-25'!G3) -> 4 | H5: =SUM(B5:F5) -> 25 | J5: West | K5: =COUNTIFS('Job Well Done'!$F:$F,K3,'Job Well Done'!$J:$J,$J$5) -> 8 | L5: =COUNTIFS('Job Well Done'!$F:$F,L3,'Job Well Done'!$J:$J,$J$5) -> 0 | M5: =COUNTIFS('Job Well Done'!$F:$F,M3,'Job Well Done'!$J:$J,$J$5) -> 1 | N5: =COUNTIFS('Job Well Done'!$F:$F,N3,'Job Well Done'!$J:$J,$J$5) -> 2 | O5: =COUNTIFS('Job Well Done'!$F:$F,O3,'Job Well Done'!$J:$J,$J$5) -> 3 | P5: =COUNTIFS('Job Well Done'!$F:$F,P3,'Job Well Done'!$J:$J,$J$5) -> 0 | Q5: =SUM(K5:O5) -> 14
A6: East | B6: =COUNTIFS('CEO of the Qtr'!$H:$H,'Summary- FY 24-25'!$A$6,'CEO of the Qtr'!$I:$I,'Summary- FY 24-25'!B3) -> 0 | C6: =COUNTIFS('CEO of the Qtr'!$H:$H,'Summary- FY 24-25'!$A$6,'CEO of the Qtr'!$I:$I,'Summary- FY 24-25'!C3) -> 0 | D6: =COUNTIFS('CEO of the Qtr'!$H:$H,'Summary- FY 24-25'!$A$6,'CEO of the Qtr'!$I:$I,'Summary- FY 24-25'!D3) -> 0 | E6: =COUNTIFS('CEO of the Qtr'!$H:$H,'Summary- FY 24-25'!$A$6,'CEO of the Qtr'!$I:$I,'Summary- FY 24-25'!E3) -> 2 | F6: =COUNTIFS('CEO of the Qtr'!$H:$H,'Summary- FY 24-25'!$A$6,'CEO of the Qtr'!$I:$I,'Summary- FY 24-25'!F3) -> 2 | G6: =COUNTIFS('CEO of the Qtr'!$H:$H,'Summary- FY 24-25'!$A$6,'CEO of the Qtr'!$I:$I,'Summary- FY 24-25'!G3) -> 1 | H6: =SUM(B6:F6) -> 4 | J6: East | K6: =COUNTIFS('Job Well Done'!$F:$F,K3,'Job Well Done'!$J:$J,$J$6) -> 1 | L6: =COUNTIFS('Job Well Done'!$F:$F,L3,'Job Well Done'!$J:$J,$J$6) -> 0 | M6: =COUNTIFS('Job Well Done'!$F:$F,M3,'Job Well Done'!$J:$J,$J$6) -> 0 | N6: =COUNTIFS('Job Well Done'!$F:$F,N3,'Job Well Done'!$J:$J,$J$6) -> 0 | O6: =COUNTIFS('Job Well Done'!$F:$F,O3,'Job Well Done'!$J:$J,$J$6) -> 0 | P6: =COUNTIFS('Job Well Done'!$F:$F,P3,'Job Well Done'!$J:$J,$J$6) -> 0 | Q6: =SUM(K6:O6) -> 1
A7: North | B7: =COUNTIFS('CEO of the Qtr'!$H:$H,'Summary- FY 24-25'!$A$7,'CEO of the Qtr'!$I:$I,'Summary- FY 24-25'!B3) -> 12 | C7: =COUNTIFS('CEO of the Qtr'!$H:$H,'Summary- FY 24-25'!$A$7,'CEO of the Qtr'!$I:$I,'Summary- FY 24-25'!C3) -> 8 | D7: =COUNTIFS('CEO of the Qtr'!$H:$H,'Summary- FY 24-25'!$A$7,'CEO of the Qtr'!$I:$I,'Summary- FY 24-25'!D3) -> 4 | E7: =COUNTIFS('CEO of the Qtr'!$H:$H,'Summary- FY 24-25'!$A$7,'CEO of the Qtr'!$I:$I,'Summary- FY 24-25'!E3) -> 7 | F7: =COUNTIFS('CEO of the Qtr'!$H:$H,'Summary- FY 24-25'!$A$7,'CEO of the Qtr'!$I:$I,'Summary- FY 24-25'!F3) -> 5 | G7: =COUNTIFS('CEO of the Qtr'!$H:$H,'Summary- FY 24-25'!$A$7,'CEO of the Qtr'!$I:$I,'Summary- FY 24-25'!G3) -> 9 | H7: =SUM(B7:F7) -> 36 | J7: North | K7: =COUNTIFS('Job Well Done'!$F:$F,K3,'Job Well Done'!$J:$J,$J$7) -> 3 | L7: =COUNTIFS('Job Well Done'!$F:$F,L3,'Job Well Done'!$J:$J,$J$7) -> 2 | M7: =COUNTIFS('Job Well Done'!$F:$F,M3,'Job Well Done'!$J:$J,$J$7) -> 10 | N7: =COUNTIFS('Job Well Done'!$F:$F,N3,'Job Well Done'!$J:$J,$J$7) -> 12 | O7: =COUNTIFS('Job Well Done'!$F:$F,O3,'Job Well Done'!$J:$J,$J$7) -> 6 | P7: =COUNTIFS('Job Well Done'!$F:$F,P3,'Job Well Done'!$J:$J,$J$7) -> 6 | Q7: =SUM(K7:O7) -> 33
A8: South | B8: =COUNTIFS('CEO of the Qtr'!$H:$H,'Summary- FY 24-25'!$A$8,'CEO of the Qtr'!$I:$I,'Summary- FY 24-25'!B3) -> 5 | C8: =COUNTIFS('CEO of the Qtr'!$H:$H,'Summary- FY 24-25'!$A$8,'CEO of the Qtr'!$I:$I,'Summary- FY 24-25'!C3) -> 9 | D8: =COUNTIFS('CEO of the Qtr'!$H:$H,'Summary- FY 24-25'!$A$8,'CEO of the Qtr'!$I:$I,'Summary- FY 24-25'!D3) -> 13 | E8: =COUNTIFS('CEO of the Qtr'!$H:$H,'Summary- FY 24-25'!$A$8,'CEO of the Qtr'!$I:$I,'Summary- FY 24-25'!E3) -> 9 | F8: =COUNTIFS('CEO of the Qtr'!$H:$H,'Summary- FY 24-25'!$A$8,'CEO of the Qtr'!$I:$I,'Summary- FY 24-25'!F3) -> 12 | G8: =COUNTIFS('CEO of the Qtr'!$H:$H,'Summary- FY 24-25'!$A$8,'CEO of the Qtr'!$I:$I,'Summary- FY 24-25'!G3) -> 8 | H8: =SUM(B8:F8) -> 48 | J8: South | K8: =COUNTIFS('Job Well Done'!$F:$F,K3,'Job Well Done'!$J:$J,$J$8) -> 4 | L8: =COUNTIFS('Job Well Done'!$F:$F,L3,'Job Well Done'!$J:$J,$J$8) -> 9 | M8: =COUNTIFS('Job Well Done'!$F:$F,M3,'Job Well Done'!$J:$J,$J$8) -> 6 | N8: =COUNTIFS('Job Well Done'!$F:$F,N3,'Job Well Done'!$J:$J,$J$8) -> 3 | O8: =COUNTIFS('Job Well Done'!$F:$F,O3,'Job Well Done'!$J:$J,$J$8) -> 9 | P8: =COUNTIFS('Job Well Done'!$F:$F,P3,'Job Well Done'!$J:$J,$J$8) -> 7 | Q8: =SUM(K8:O8) -> 31
A9: Total | B9: =SUM(B4:B8) -> 30 | C9: =SUM(C4:C8) -> 28 | D9: =SUM(D4:D8) -> 34 | E9: =SUM(E4:E8) -> 32 | F9: =SUM(F4:F8) -> 28 | G9: =SUM(G4:G8) -> 34 | H9: =SUM(H4:H8) -> 152 | J9: Total | K9: =SUM(K4:K8) -> 19 | L9: =SUM(L4:L8) -> 25 | M9: =SUM(M4:M8) -> 22 | N9: =SUM(N4:N8) -> 24 | O9: =SUM(O4:O8) -> 23 | P9: =SUM(P4:P8) -> 23 | Q9: =SUM(Q4:Q8) -> 113
A11: SPOT and SPOT of the Month | J11: Intrafunctional
A13: Region / Quarters | B13: Spot | C13: Spot of the Month | D13: Total | J13: Q3 FY24 | K13: Q4 FY24 | L13: Q1-FY25 | M13: Q2-FY 25 | N13: Q3 FY25 | O13: Q4-FY 25 | P13: Total
A14: Corporate | B14: =COUNTIFS('Spot & Spot of the Month'!$I:$I,'Summary- FY 24-25'!A14,'Spot & Spot of the Month'!$F:$F,$B$13) -> 119 | C14: =COUNTIFS('Spot & Spot of the Month'!$I:$I,'Summary- FY 24-25'!A14,'Spot & Spot of the Month'!$F:$F,$C$13) -> 120 | D14: =SUM(B14:C14) -> 239 | J14: =COUNTIF(Sheet4!$B:$B,'Summary- FY 24-25'!J13) -> 1 | K14: =COUNTIF(Sheet4!$B:$B,'Summary- FY 24-25'!K13) -> 9 | L14: =COUNTIF(Sheet4!$B:$B,'Summary- FY 24-25'!L13) -> 5 | M14: =COUNTIF(Sheet4!$B:$B,'Summary- FY 24-25'!M13) -> 3 | N14: =COUNTIF(Sheet4!$B:$B,'Summary- FY 24-25'!N13) -> 5 | O14: 2 | P14: =SUM(J14:O14) -> 25
A15: West | B15: =COUNTIFS('Spot & Spot of the Month'!$I:$I,'Summary- FY 24-25'!A15,'Spot & Spot of the Month'!$F:$F,$B$13) -> 69 | C15: =COUNTIFS('Spot & Spot of the Month'!$I:$I,'Summary- FY 24-25'!A15,'Spot & Spot of the Month'!$F:$F,$C$13) -> 88 | D15: =SUM(B15:C15) -> 157
A16: East | B16: =COUNTIFS('Spot & Spot of the Month'!$I:$I,'Summary- FY 24-25'!A16,'Spot & Spot of the Month'!$F:$F,$B$13) -> 46 | C16: =COUNTIFS('Spot & Spot of the Month'!$I:$I,'Summary- FY 24-25'!A16,'Spot & Spot of the Month'!$F:$F,$C$13) -> 35 | D16: =SUM(B16:C16) -> 81
A17: North | B17: =COUNTIFS('Spot & Spot of the Month'!$I:$I,'Summary- FY 24-25'!A17,'Spot & Spot of the Month'!$F:$F,$B$13) -> 150 | C17: =COUNTIFS('Spot & Spot of the Month'!$I:$I,'Summary- FY 24-25'!A17,'Spot & Spot of the Month'!$F:$F,$C$13) -> 141 | D17: =SUM(B17:C17) -> 291
A18: South | B18: =COUNTIFS('Spot & Spot of the Month'!$I:$I,'Summary- FY 24-25'!A18,'Spot & Spot of the Month'!$F:$F,$B$13) -> 212 | C18: =COUNTIFS('Spot & Spot of the Month'!$I:$I,'Summary- FY 24-25'!A18,'Spot & Spot of the Month'!$F:$F,$C$13) -> 199 | D18: =SUM(B18:C18) -> 411
B19: =SUM(B14:B18) -> 596 | C19: =SUM(C14:C18) -> 583
A21: Debutant of the Quarter | J21: Cross Functional
A22: Region / Quarters | B22: Q3-FY24 | C22: Q4-FY24 | D22: Q1-FY25 | E22: Q2-FY25 | F22: Q3-FY25 | G22: Q4-FY 25 | H22: Total
A23: Corporate | B23: =COUNTIFS('Debutant of the Qtr'!$F:$F,B22,'Debutant of the Qtr'!$J:$J,'Summary- FY 24-25'!$A$23) -> 0 | C23: =COUNTIFS('Debutant of the Qtr'!$F:$F,C22,'Debutant of the Qtr'!$J:$J,'Summary- FY 24-25'!$A$23) -> 4 | D23: =COUNTIFS('Debutant of the Qtr'!$F:$F,D22,'Debutant of the Qtr'!$J:$J,'Summary- FY 24-25'!$A$23) -> 4 | E23: =COUNTIFS('Debutant of the Qtr'!$F:$F,E22,'Debutant of the Qtr'!$J:$J,'Summary- FY 24-25'!$A$23) -> 5 | F23: =COUNTIFS('Debutant of the Qtr'!$F:$F,F22,'Debutant of the Qtr'!$J:$J,'Summary- FY 24-25'!$A$23) -> 1 | G23: =COUNTIFS('Debutant of the Qtr'!$F:$F,G22,'Debutant of the Qtr'!$J:$J,'Summary- FY 24-25'!$A$23) -> 3 | H23: =SUM(B23:F23) -> 14 | J23: Q3 FY24 | K23: Q4-FY 24 | L23: Q1-FY 25 | M23: Q2-FY 25 | N23: Q3-FY 25 | O23: Q4-FY 25 | P23: Total
A24: West | B24: =COUNTIFS('Debutant of the Qtr'!$F:$F,B22,'Debutant of the Qtr'!$J:$J,'Summary- FY 24-25'!$A$24) -> 0 | C24: =COUNTIFS('Debutant of the Qtr'!$F:$F,C22,'Debutant of the Qtr'!$J:$J,'Summary- FY 24-25'!$A$24) -> 0 | D24: =COUNTIFS('Debutant of the Qtr'!$F:$F,D22,'Debutant of the Qtr'!$J:$J,'Summary- FY 24-25'!$A$24) -> 2 | E24: =COUNTIFS('Debutant of the Qtr'!$F:$F,E22,'Debutant of the Qtr'!$J:$J,'Summary- FY 24-25'!$A$24) -> 0 | F24: =COUNTIFS('Debutant of the Qtr'!$F:$F,F22,'Debutant of the Qtr'!$J:$J,'Summary- FY 24-25'!$A$24) -> 1 | G24: =COUNTIFS('Debutant of the Qtr'!$F:$F,G22,'Debutant of the Qtr'!$J:$J,'Summary- FY 24-25'!$A$24) -> 0 | H24: =SUM(B24:F24) -> 3 | J24: =COUNTIF(Sheet4!$G:$G,J23) -> 0 | K24: =COUNTIF(Sheet4!$G:$G,K23) -> 3 | L24: =COUNTIF(Sheet4!$G:$G,L23) -> 4 | M24: =COUNTIF(Sheet4!$G:$G,M23) -> 1 | N24: =COUNTIF(Sheet4!$G:$G,N23) -> 1 | O24: 5 | P24: =SUM(J24:O24) -> 14
A25: East | B25: =COUNTIFS('Debutant of the Qtr'!$F:$F,B22,'Debutant of the Qtr'!$J:$J,'Summary- FY 24-25'!$A$25) -> 0 | C25: =COUNTIFS('Debutant of the Qtr'!$F:$F,C22,'Debutant of the Qtr'!$J:$J,'Summary- FY 24-25'!$A$25) -> 0 | D25: =COUNTIFS('Debutant of the Qtr'!$F:$F,D22,'Debutant of the Qtr'!$J:$J,'Summary- FY 24-25'!$A$25) -> 0 | E25: =COUNTIFS('Debutant of the Qtr'!$F:$F,E22,'Debutant of the Qtr'!$J:$J,'Summary- FY 24-25'!$A$25) -> 0 | F25: =COUNTIFS('Debutant of the Qtr'!$F:$F,F22,'Debutant of the Qtr'!$J:$J,'Summary- FY 24-25'!$A$25) -> 0 | G25: =COUNTIFS('Debutant of the Qtr'!$F:$F,G22,'Debutant of the Qtr'!$J:$J,'Summary- FY 24-25'!$A$25) -> 0 | H25: =SUM(B25:F25) -> 0
A26: North | B26: =COUNTIFS('Debutant of the Qtr'!$F:$F,B22,'Debutant of the Qtr'!$J:$J,'Summary- FY 24-25'!$A$26) -> 0 | C26: =COUNTIFS('Debutant of the Qtr'!$F:$F,C22,'Debutant of the Qtr'!$J:$J,'Summary- FY 24-25'!$A$26) -> 0 | D26: =COUNTIFS('Debutant of the Qtr'!$F:$F,D22,'Debutant of the Qtr'!$J:$J,'Summary- FY 24-25'!$A$26) -> 2 | E26: =COUNTIFS('Debutant of the Qtr'!$F:$F,E22,'Debutant of the Qtr'!$J:$J,'Summary- FY 24-25'!$A$26) -> 1 | F26: =COUNTIFS('Debutant of the Qtr'!$F:$F,F22,'Debutant of the Qtr'!$J:$J,'Summary- FY 24-25'!$A$26) -> 2 | G26: =COUNTIFS('Debutant of the Qtr'!$F:$F,G22,'Debutant of the Qtr'!$J:$J,'Summary- FY 24-25'!$A$26) -> 1 | H26: =SUM(B26:F26) -> 5
A27: South | B27: =COUNTIFS('Debutant of the Qtr'!$F:$F,B22,'Debutant of the Qtr'!$J:$J,'Summary- FY 24-25'!$A$27) -> 0 | C27: =COUNTIFS('Debutant of the Qtr'!$F:$F,C22,'Debutant of the Qtr'!$J:$J,'Summary- FY 24-25'!$A$27) -> 0 | D27: =COUNTIFS('Debutant of the Qtr'!$F:$F,D22,'Debutant of the Qtr'!$J:$J,'Summary- FY 24-25'!$A$27) -> 1 | E27: =COUNTIFS('Debutant of the Qtr'!$F:$F,E22,'Debutant of the Qtr'!$J:$J,'Summary- FY 24-25'!$A$27) -> 0 | F27: =COUNTIFS('Debutant of the Qtr'!$F:$F,F22,'Debutant of the Qtr'!$J:$J,'Summary- FY 24-25'!$A$27) -> 0 | G27: =COUNTIFS('Debutant of the Qtr'!$F:$F,G22,'Debutant of the Qtr'!$J:$J,'Summary- FY 24-25'!$A$27) -> 1 | H27: =SUM(B27:F27) -> 1
B30: People Champion | J30: Thank You
A31: Region / Quarters | B31: Q3-FY25 | C31: Total | J31: Region / Quarters | K31: Total
A32: Corporate | B32: 4 | C32: =SUM(B32) -> 4 | J32: Corporate | K32: =COUNTIFS('Thank You'!$I:$I,'Summary- FY 24-25'!J32) -> 19
A33: South | B33: 1 | C33: =SUM(B33) -> 1 | J33: West | K33: =COUNTIFS('Thank You'!$I:$I,'Summary- FY 24-25'!J33) -> 9
J34: East | K34: =COUNTIFS('Thank You'!$I:$I,'Summary- FY 24-25'!J34) -> 9
J35: North | K35: =COUNTIFS('Thank You'!$I:$I,'Summary- FY 24-25'!J35) -> 22
J36: South | K36: =COUNTIFS('Thank You'!$I:$I,'Summary- FY 24-25'!J36) -> 47

Sheet Process Document
A1: Ongoing
A2: Award | B2: Purpose | C2: Nominator ELigibility | D2: Eligibility | E2: Approval | F2: Vantage circle points
A3: Thank You | B3: Thank You badge is to express gratitude to colleagues who went beyond their call of duty to help their colleagues | C3: All | D3: All | E3: - | F3: -
A4: SPOT | B4: Employees can appreciate their colleagues for the demonstration of CEOs behaviours of Collaboration, Experimentation, Ownership and Speed and recognize them for their contribution, achievement and impact. | C4: All | D4: All | E4: - | F4: Eligibility for Spot of the Month
A5: Be Your Own CEOs
A6: Award | B6: Purpose | C6: Nominator ELigibility | D6: Eligibility | E6: Approval | F6: Vantage circle points
A7: Spot of the Month | B7: A monthly award for employees who have demonstrated CEOs behaviours and have had significant impact through achievement beyond day to day work. | C7: Via Spot | D7: 1. Via Spot | E7: M2 | F7: 500
C8: People Manager | D8: 2. Direct -> M3 to M5 employees
A9: CEOs of the Quarter | B9: A quarterly award to recognise employees who have demonstrated CEOs behaviours of Collaboration, Experimentation, Ownership and Speed and made an exemplary contribution through a pathbreaking idea or solution, to the function/organization, going beyond the call of duty. | C9: From the approved "SPOT of the month" of the past 3 months | D9: Spot of the Month | E9: M2 Jury | F9: Invitation to CEOs Forum
A10: Quarterly awards
A11: Award | B11: Purpose | C11: Nominator ELigibility | D11: Eligibility | E11: Approval | F11: Vantage circle points
A12: Job Well Done | B12: To recognise employees who have demonstrated Tata Play Anchor competencies in their work | C12: People Manager (within the same department) | D12: M3 to M5 employees | E12: M2 -> M1 | F12: 5000
A13: Debutant of the Quarter | B13: To recognise new joiners who blend with their peers and contribute through innovative thoughts and ideas | C13: People Manager (within the same department) | D13: M3 to M5 employees who have joined in a previous quarter | E13: M2 -> M1 | F13: -
A14: Intra Functional Team Awards | B14: To recognise intra functional teams who have displayed exceptional Anchor behaviours, collaborated on specific projects, and delivered positive results | C14: People Manager (within the same department) | D14: M3 to M5 employees who are part of same function | E14: M1 | F14: 10,000 divided equally to team members
A15: Cross Functional Team Awards | B15: To recognise cross functional teams who have displayed exceptional Anchor behaviours, collaborated on specific projects, and delivered positive results | C15: People Manager (across departments) | D15: M3 to M5 employees who are part of different functions | E15: M1 Jury | F15: 10,000 divided equally to team members
A16: Half-Yearly awards
A17: Award | B17: Purpose | C17: Nominator ELigibility | D17: Eligibility | E17: Approval | F17: Vantage circle points
A18: People Champion | B18: To recognise people managers for their efforts in creating a strong workplace which facilitates the employee to grow, engage and contribute to the fullest. | C18: People Manager (within the same department) | D18: People Manager | E18: M1 | F18: -
A19: Other awards
A20: Pathfinder Award
A21: Fundamental Award | B21: Basis activities conducted for respective regions

Sheet Sheet3
A2: CE
A3: Count of Sl No. | B3: Column Labels
A4: Row Labels | B4: Q1-FY25 | C4: Q2-FY 25 | D4: Q3-FY24 | E4: Q3-FY25 | F4: Q4-FY24 | G4: Grand Total
A5: Corporate | B5: 7 | C5: 9 | D5: 8 | E5: 7 | F5: 8 | G5: 39
A6: East | C6: 2 | E6: 2 | G6: 4
A7: North | B7: 4 | C7: 7 | D7: 12 | E7: 5 | F7: 8 | G7: 36
A8: South | B8: 13 | C8: 9 | D8: 5 | E8: 12 | F8: 9 | G8: 48
A9: West | B9: 10 | C9: 5 | D9: 5 | E9: 2 | F9: 3 | G9: 25
A10: Grand Total | B10: 34 | C10: 32 | D10: 30 | E10: 28 | F10: 28 | G10: 152

Sheet Sheet4
A1: Citation | B1: Quarter | F1: Citation | G1: Quarter
A2: Sony RIO was a very complex and a unique project which involved various teams within commercial function. The project helped rationalise subscribers content and also impact monthly charges. It was a complex project which involved making changes packaging and meeting regulatory compliances within timelines. Post execution the task was to roll it back as well with speed and efficiency as business objectives were achieved. This team worked very closely and their collective efforts demonstrated successful collaboration, ownership, speed and innovation with a focus on not just business KPIs but also on customer experience | B2: Q2-FY 25 | F2: Launch of Tata Play Superhit Serials At all levels, this was a project launched well and doing well despite very many challenges. It has been, at idea level, well thought out and well researched product after much debate between extension of classic TV vs standalone product. Example of good partner negotiation wherein for the first time, star agreed to create launch promos and create conceptual promos every month. Star also created special 1 hours edits of all shows despite the large cost. Overall, product idea, partner negotiations, new experiments in GTM, new formats of slate promos, appreciation by subscribers for bringing this product and great numbers makes this a superhit product of the year. All teams involved has put in wholehearted efforts to make this happen. | G2: Q2-FY 25
A3: Sunil is number one in overall Ranking in first six Month . Bhaskar is number 1 in Building Infra in his respective area across Circle | B3: Q2-FY 25 | F3: The project involved changing the existing Prime Video journey and implementing a new activation journey for Prime Video with all eligible Binge packs. This required altering all backend and Frontend statuses and stages for Amazon Prime Video.\n- end-to-end testing in UAT and Production environments.\n- 185 test cases prepared and executed in a single day in coordination with teams, identifying over 50+ issues.\n- Multiple teams coordinated on daily basis to resolve open issues, ensuring successful closing.\n- Prime Video rigorous testing with all eligible Binge packs as per business requirement and brought the integration successfully in live production.\n- Simultaneously performed regression testing for the Binge TV app and ad-hoc testing as well. | G3: Q1-FY 25
A4: TATA Play was migrating to a new SIEM tool, however, due to the TBXG Cyber Assessment, the DTH team started a little late. With just ~10 days remaining before the existing SOC contract expired, Ritesh and Swamy took charge of the situation and successfully onboarded all major log sources within the tight timelines by collaborating with multiple teams and putting in long hours to ensure a smooth transition. | B4: Q2-FY 25 | F4: In the month of May\u201924, we embarked on an ambitious initiative aimed at re-activating and ringfencing customers from the deep deactive bucket during the high opportunity T20 world cup season. We targeted 5 million subscribers from the D30 to D365 bucket with active days less than 240 in the past 12 months. By leveraging a multi-channel approach\u2014 which includes Outbound, Inbound, SMS, WhatsApp, OBD. \u2014we will have successfully retained and Winback more than 110K subs subscribers by the end of this activity. Cross functional teams were involved in planning, developing infrastructure, hiring and training of close to over 3000 resources, with a effective outcome of more than 110,000 conversions coming back with long term commitment (6month/12 month). The success of our Mega Winback Initiative underscores the importance of a multi-faceted approach, Speed and effective cross-functional collaboration. Push through Outbound, Inbound, WhatsApp, SMS, OBD led to a healthy conversion and returns. | G4: Q1-FY 25
A5: We launched a first of a kind partnership with Amazon Prime Video for Binge customers, offering Prime Lite as part of a 199(INR) best of 6 bundle. This strategic move aimed to launch a powerful & unique proposition for consumers to choose their favourite OTTs on a very aggressive price point. This ensured that we have a strong market pull for driving acquisition & thus aspire for 1 Mn Sub-base. It involved collaboration across teams to implement the proposition across multiple touchpoints, including both front-end and back-end product development creating customer experience & pack journeys. A robust marketing campaigns was launched with an ad-film along with tentpole Content (Mirzapur & Panchayat) across Digital & Ch 100. This created a high impact launch, achieving ~200K gross additions within the first couple of months which is the highest for Binge. | B5: Q1-FY25 | F5: Synamedia CY23 Bundle testing & download completion\nConsisting\u00A0of 9 different feature enhancements like 3 additional language in EPG, 1500 service capability in STB, subscriber channel indication and other marketing CRs for 18 field STB models. This required\u00A0arranging software deliveries, rigorous testing of multiple software releases in coordination with relevant configurations setup from the Headend team, getting issues fixed , conducting trial & target zip code based download for every STB model each day.\nResult achieved : successful software upgrade completion without major escalations from field.\n\u00A0 | G5: Q1-FY 25
A6: Team AI Evangelists:\nProject AI Literacy (PAL) has been taken up by a team, AI Evangelists comprising of Ishant, Dimple, Varun, Prabhat & Anantha. The project aims to ensure that by the end of 52-week period each of the Finance team member is familiar with the new age Tech tools and their impact on them both professionally & personally. \nAs part of this project already 10 modules have been published. Also the team has carried out multiple interactive sessions that have been well received. There is an overwhelming response and a change has set in. \nThe team sourced the course and extent of this project by referring to CBSE X syllabus of AI subject. They have referred to various materials across the internet sources, using GenAI tools to create the modules that are easy to read with pop culture references incl. Bollywood.\u00A0 | B6: Q1-FY25 | F6: Launch of targeted ads on Star channels Team collaborated to Launch an industry-first paid ad innovation Q1\u2013 Targeted ads on Star GEC and Sports contributing to the gross revenue of Rs. 1.6 Cr (Gross) activating brands like Apple, River soft, Amazon prime, Amazon Fresh, Gemini Edible oils, Rupay & Torrent pharmaceutical | G6: Q1-FY 25
A7: Recognizing the team with Intra Function Award for the below contributions towards 5Million Mega Winback Campaign.\n1. From day one, 5mn reports were expected by 9am and hence team had to login early shifts for churning the data and sharing the same on time.\n2. Few new campaigns under the same Mega WBK (Follow-up Phase 1, OB&WA Follow-up, Act/Deact Follow-up Phase 2 were introduced at regular intervals which increased the query run time & team worked together in optimizing the same using online techniques \n3. A new dashboard was introduced which is being sent to CEO on a daily basis by 9am, timeline was never missed & teams across functions worked on the same for seamless delivery. (Lenin to update dials & Conversions, Sujith to share FTE count, Srinidhi to share cost on a daily basis, Pavan Jagan's contribution towards CR's & Billing Closure), this report is sent on all days including Weekends and Holidays. \n4.Error free & timely delivery of reports helped in campaign success. | B7: Q1-FY25 | F7: The Delinking of Binge from DTH on the Binge+ STB was a complex project that brought together business, product and execution teams across platforms, to collaborate on a common goal and delivering under strict timelines. The objective was to empower customers with the flexibility to pay for Linear TV or OTT or both using Tata Play wallet. From a business perspective, this was an opportunity to bring back many of our lost customers who wanted to consume only Binge on their Binge+ box. A solution was needed to achieve these rules without impacting other adjacent DTH workflows, UX definition across the different customer touchpoints on different platforms like the Binge+ box and TPMA & finally in the testing & sign off of one of the most detailed set of use cases.The impact of this project post go-live has been a healthy \u2013 with 10% adoption of this feature by customers, with minimal revenue impact on DTH side, reflecting the customer value in these changing times.\u00A0 | G7: Q4-FY 24
A8: I would like to nominate Anand, Shoaib, and Vinod for the Intra-Functional Team Award for their exceptional performance in Q1. Their collaboration and dedication have led to outstanding results, significantly contributing to our overall success. Key Achievements: *Exceeded CESIP Target: The team achieved more than 125% of the CESIP appointment target, showcasing their dedication and strategic execution. *Strategic Partner Appointments: Their successful appointment of CESIP partners is crucial for our business, as TV installers play a vital role in convincing customers to choose Tata Play. *APD Business Growth: With the new CESIP partners onboard, they are now poised to initiate and ensure growth in the APD business. Their teamwork, strategic thinking, and commitment have been exemplary. I strongly recommend this team for the Intra-Functional Team Award to recognize their significant contributions and encourage their continued success. Congratulations to all. | B8: Q1-FY25 | F8: In Orissa Sales & team service team jointly executed big & complex projects(IFFCO) where more than 1200 connections being given with in time line with out any escalations.The smooth execution of big projects enable team motivations and given boost to market which fetches more similar project like this..This is showing a great example of collaborative approach team working with one single objectives of best of customer satisfaction and win over competition. | G8: Q4-FY 24
A9: First time since the time of inception of Tata Play, Customs Audit covering all the import and export transactions for the last 5 years i.e. from 2018 to 2023 happened this year. This was a premise-based audit which continued for the 2 months period through multiple meetings and engagements with Auditors, submission of series of relevant documents asked by auditors and ended with 2 full days visit by 3 authorities from customs audit department in our corporate office. Bhupendra Kumar and Harish Jathan have handled end to end documentation, liaising with cross functional stakeholders, solving of all the queries raised by auditors and finished the audit with clean report without any major observations. Being the audit happening for the first time, it was a difficult task to handle complicated queries and situations raised by Auditors. But Bhupendra and Harish have made best use of their knowledge and experience to handle these situations effectively and resolved all open queries timely. | B9: Q1-FY25 | F9: This recognition for the team that has worked together on putting up signages for Project Ravi and Versova across locations with agility. The cross functional team between Comms, Procurement and Trade Marketing worked as team to ensure newly opened outlets are given visibility support in quick time. The team set up a network of agencies and vendors with a monitoring system to ensure deliverables moved on time and were tracked. | G9: Q4-FY 24
A10: With a new satellite being commissioned the team was tasked to create impact and deliver ROI on the satellite cost. In the last 3 months of the fiscal, the team was persistent and demonstrated rigour in securing partnerships thus delivering the highest carriage collections seen across the last 5 years amounting to 60 Crs in revenue in 3 months. This contributed significantly to overall revenue for Tata Play. | B10: Q4 FY24 | F10: Launch of Tata Play Deiveegam<br/> The launch of Tata Play Deiveegam marked a significant milestone as our first regional devotional service after Aradhana. Recognizing the importance of the South Indian market, we chose Tamil for its enthusiasm and receptiveness to a premium offering, setting the price at ₹60 per month—a first for any Tata Play regional service.<br/>Meticulous research, extensive planning and seamless collaboration across teams to sell the service to the right target group. The results were immediate, with Tata Play Deiveegam setting a new benchmark in the regional devotional space in its launch week. <br/>Key milestones:<br/>Deiveegam was launched at 33% higher price still achieved similar gross adds (14-15k) as Tamil classics and Telugu classics in the first 7 days.<br/>Revenue generated by Deiveegam was significantly higher than other regional services by 16-20%<br/>This launch has set a best practice to be replicated for pricing interventions in other regional services and drive revenue | G10: Q3-FY 25
A11: The team streamlined the planning & execution for implementing SEO on Binge, it was the first of its kind project with no in house expertise and required every team member to go above and beyond to get it LIVE . Right from identifying keywords to website design ,technical and programming aspects of the website, the team ensured that the Binge website was made SEO friendly for organic ranking on Google search and will give long term benefits of organic marketing. | B11: Q4 FY24
A12: Inbound team had taken an arduous task of achieving NPS of 70 this year compared to 57 last year. This required a lot of brainstorming, project mapping, cross functional stake holder management, process changes, introducing new monitoring mechanism etc. Every individual had taken a specific region and PI\u2019s to improve upon from April to December. The overall project was divided into Six Sigma and 360-degree feedback learning to be incorporated into practice. NPS has moved from 57 last to 71 in December with YTD NPS being at 70 which is best ever for us and across industries. The entire team and every individual have demonstrated a rare passion to achieve the goals with excellent call to action. Not only the scores were improved drastically but also NPS is almost insular now to process changes and exhibiting a process level stability. A great foot to achieve with astounding teamwork. Keep it up team!\u00A0 | B12: Q4 FY24
A13: This Award Goes to each ASM of Team Marathwada for all their hard work in Delivering Result in Q4 & Hitting Hat Trick of West Region Award too with Highest TSK Active Dealer Achievement in the month of March 2024. Congratulations Team & Keep it up! | B13: Q4 FY24
A14: Good Job Done Team! you guys have adopted the change and action on task and delivered 100% result within timeline.Task was TSK active Target 2150 by Dec 2023. & Achievement was 2154 & given Growth over July is 65%. which the highest in Pune district.your contribution is more than 100% ASM Name\u00A0 Q3 Tgt Q3 Ach\u00A0 Ach%\u00A0 Sachin Gaikwad 1237 1477 119% Vikas Desai 1168 1286 110% Mohsin Tamboli 1244 1536 123% | B14: Q4 FY24
A15: Monish and Sahil have contributed very well in success of Sales and Revenue Performance for CO OB function. with 9% reduction in cost, we have 10% growth in Conversions and Gross Revenue. We will be doing 5X ROI with 180 CR revenue from OB CO Team. Their contribution is highly commendable with keeping Compliance intact. Commercial team has shared accolades for their contribution. Congratulations to both of them for their good work for FY 23-24. | B15: Q4 FY24
A16: Excellent job for achieving more than 80% ISP Installer contribution for BMP contribution with in 21 days of the month. Across ASMs has contributed and strong activity to the field level & sense of urgency has been showing.The similar trend showing in Recharge as well , every ASM now contributing to over all circle numbers and as a Circle we are now contributing highest numbers for both BMP and Recharges on many days to region..This is the step stone for big success for coming days, with this engagement level we as a team can achieve more such success.. | B16: Q4 FY24
A17: As A Team All managed MDU migration load efficiently within timelines. They prepared well in advance manpower and started following up daily plan vs Achievement. They coordinated well with ODU teams in handling all institutional subscribers along with VIP subscriber with least escalation and minimum break down time with MDU migration hand in hand West having Highest MDU base of 23803 buildings, still we able to Migrate all subs as per given timelines. | B17: Q4 FY24
A18: We took a bold target of doing 100,000 Gross adds of Tata Play Services through TPMA at the start of the year. The number then was 30K. The team took this as a challenge. Collaboratively, they devised strategies on how to achieve it and achieved the targets in March. A true example of collaboration, strategic thinking and execution excellence. | B18: Q4 FY24
A19: The BE Team worked very hard for CD 6.0 of Binge. The exercise was first project and was highly appreciated by Samba Sir and Harit Sir too. Based on the same actions are being taken. What is important to note that the Final presentation that had to be done ib December 2023 was preponed to 22nd November 2023 based on a decision in Factbook which was held around 17th Nov 2023. The BE Team gathered together and turned it around to deliver the Final presentation on 22nd November 2023 which was on the basis of 500 Calls of Customers analysed for the outcome of Pain Points to be addressed. Samba Sir also send an email to the Finance Team appreciating this effort and also stating that such process of fast Turn around should be noted and imbibed by each individual. | B19: Q3 FY24
A20: Almost all content viewing apps have hero banners as a norm. The radical thought of not having a hero banner for TPMA warranted a A/B testing. As it could potentially have impact on business KPI and customer experience. A/B testing as a solution was not available and hence had to get developed. For doing the test it was also critical that we had the baseline of KPI’s available across content viewing and upselling and their CTR’s. The launch of AB testing required it to be prioritized in the road map along with business rules being put in place. It also required a new UI to be created along with localization. The period for this testing was also critical as we wanted to test this with and without a sporting event. Last but not the least it required a mindshift change to go against the norm. A/B testing was launched in November and we monitored the performance over 14 days. The results were interesting. It showed that not having a hero banner did not have any adverse impact on business. | B20: Q3 FY25
A21: With over 20 new releases on Tata Play Binge every week, across partner apps, there was an opportunity to ride on the popularity and buzz of the titles and leverage that to drive higher subscriptions and engagement for Binge. The team identified the high-decibel content releases to create a seamless end-to-end strategy: procuring trailers and promos, crafting compelling assets, and deploying them across multiple touchpoints including Ch 100, set-top boxes, Binge App, TPMA, emailers, notifications, digital platforms, social and field communication. What sets this initiative apart is the agility - despite tight timelines with partners delivering assets just days or even hours before launch, the team has executed flawless go-to-market plans, ensuring maximum impact. | B21: Q3 FY25
A22: Would like to extend appreciation to the team for their dedication and collaboration for the successful launch of the Quality Framework- 'NEF' for SR desk.<br/>Team created comprehensive Quality framework, stringent guidelines, ensured training sessions, calibrations, simplifying the guidelines, system enhancements for higher efficiencies and collaborated with partners to ensure seamless integration and adoption of the new framework. The new framework has resulted in higher accuracies and quicker resolution <br/> | B22: Q3 FY25
... A24: RO Antennas old Feed system replacement with Krato’s feed got Carried out by In-house team members: Required to replace old Feed system of RO-Antennas and need to install new feed along with New LNB changeover system with Acrylic Protection Assembly for entire feed system, Tech Services team members taken ownership for this critical installations and completed the same on required Antennas.<br/><br/>Installation and Replacement Rack power MDU’s EATON STS-16 units with EATON-ATS-16, To prevent equipment power failures in Compression system AVP racks old EATON STS-16 units which are having switching issues required to be replaced with New EATON ATS units, Tech Services team taken ownership and worked responsibly during Scheduled Activity timings and completed the critical MDU units replacement activity successfully. | B24: Q3 FY25

Sheet CEO of the Qtr
A1: Sl No. | B1: Emp ID | C1: Name | D1: Citation | E1: Grade | F1: Designation | G1: Department | H1: Region | I1: Quarter | J1: Award Name | K1: Award Name Quarter
A2: 1 | B2: 7347 | C2: Anilkumar N | D2: Amitabh Das - I really appreciate the effort put in by you in configuring the UNICA campaign for Binge Mobile Flexi 99 OB campaign Launch. You took end to end responsibility from raising the CR, to coordinating closely with IT and UAT teams to ensure the solution is created, tested, and deployed seamlessly within a very stiff timeline. A big thanks for your support and ownership. | E2: M5 | F2: Assistant Manager - Systems Solutions & Design - COSSG | G2: Customer Operations | H2: South | I2: Q4-FY24 | J2: CEO of the Quarter | K2: =_xlfn.CONCAT(J2," ",I2) -> CEO of the Quarter Q4-FY24
A3: 2 | B3: 4149 | C3: Joby George | D3: Lolakshi Ashok Moolya - The Department of Telecommunications (DOT) issued an Office Order on October 1, 2022, eliminating NOCC charges for using the Space segment. TATA Play had already made advance payments to DOT for the entire year. Upon the order taking effect, efforts were made, particularly by Joby, who played a crucial role in meeting with officials to initiate the refund process. This involved extensive sharing of reconciliation and data to demonstrate timely payment of old dues. Finally, in September 2023, the refund was successfully received. Additionally, following the activation of GSAT 24, Joby diligently pursued the refund of WPC License fees paid in advance. After persistent follow-ups, a senior official agreed to offset these fees against the next year's Spectrum fees. The commendable efforts of Joby in navigating the complexities of government authorities to secure these refunds are truly appreciated. | E3: M3 | F3: Assistant General Manager - Regulatory Affairs | G3: Legal | H3: North | I3: Q4-FY24 | J3: CEO of the Quarter | K3: =_xlfn.CONCAT(J3," ",I3) -> CEO of the Quarter Q4-FY24
A4: 3 | B4: 6805 | C4: Kumar Shubham | D4: Shubham has played a pivotal role in assisting in setting up processes and spearheading the signage project Ravi and Versova. He brings to the table the ability to understand trade, the potential challenges on a project and managing key stakeholders through his relationships. Shubham has been relentless and reliable team member to ensure that the signage project keeps rolling on-time and in-full. He has also contributed to ensuring timely deliveries and execution of the long- term visibility elements including innovative elements such as sturdy standees in 2023 that has benefited the trade/business to a large extent. | E4: M4 | F4: Senior Manager - Brand Marketing | G4: Communications | H4: Corporate | I4: Q4-FY24 | J4: CEO of the Quarter | K4: =_xlfn.CONCAT(J4," ",I4) -> CEO of the Quarter Q4-FY24
A5: 4 | B5: 6375 | C5: P Yogapriya . | D5: Ritesh Jain ( Commercial )-Yoga has extremely well managed 'Next Best Action' project. Right from creating Business Requirement Document to coordinating with various teams (Analytics, IT, Customer Operations..) and making sure that project is on track, Yoga has been instrumental in making this project successful. Intelligent product rules have been designed which made sure that subscribers are recommended right product there by maximizing the revenue opportunity. She made sure that at every step all the teams are aligned on the objective of the project leading to timely closure of the project. Post go live reporting has been also taken care of, daily reporting is helping teams to drive business better. Overall, an excellent work done on NBA. Keep up the good work Yoga. | E5: M4 | F5: Senior Manager - Subscriber Marketing | G5: Commercial | H5: Corporate | I5: Q4-FY24 | J5: CEO of the Quarter | K5: =_xlfn.CONCAT(J5," ",I5) -> CEO of the Quarter Q4-FY24
A6: 5 | B6: 7644 | C6: Sachin Ravasab Janaj | D6: Anitha Joy ( Commercial )-Sachin has helped the content ops team in automating the daily schedule process for Tata Play Fun Learn , being new in the organisation, Sachin has been able to quickly understand content teams schedule requirement and has developed a tool to generated the various output schedules like Playout, EPG , AMS , Application schedule etc . Team used to take good amount of time to generate these schedules manually are now able to generate them with ease and manual errors are minimized through system generated schedules. Thank you Sachin. | E6: M5 | F6: Executive - New Product Development | G6: Commercial | H6: South | I6: Q4-FY24 | J6: CEO of the Quarter | K6: =_xlfn.CONCAT(J6," ",I6) -> CEO of the Quarter Q4-FY24
A7: 6 | B7: 6356 | C7: Sushant Awasthi | D7: Naveen Rawal ( Technology )-For a potential customer on white label product, the requirement was to provide them with detailed performance review of their existing STB and accessory items and hence offer our expertise. Sushant took ownership and successfully completed the hardware reliability testing activity on the received sample units within short span of time with critical improvement findings in the product. Sushant's contribution and commitment in completing this activity is valued and appreciated. Keep it up. | E7: M5 | F7: Assistant Manager - Consumer Technology | G7: Technology | H7: North | I7: Q4-FY24 | J7: CEO of the Quarter | K7: =_xlfn.CONCAT(J7," ",I7) -> CEO of the Quarter Q4-FY24
A8: 7 | B8: 7658 | C8: Kaushal Kumar Jha | D8: Meghana Nagaraj - Kaushal, I would like to express my appreciation for your outstanding contribution to taking Notifications live on Binge+. You took ownership of the project end to end and collaborated with Business & Technology teams, playing a crucial role in prioritization, negotiating timelines, technical discussions & managing stakeholder expectations to ensure the feature was taken live with a significant impact on the engagement KPIs. Your dedication is truly commendable and deeply appreciated! Your enthusiasm and determination always reflect in your outputs. Keep up the good work! | E8: M4 | F8: Senior Manager - New Product Development | G8: Commercial | H8: South | I8: Q4-FY24 | J8: CEO of the Quarter | K8: =_xlfn.CONCAT(J8," ",I8) -> CEO of the Quarter Q4-FY24
A9: 8 | B9: 7640 | C9: Cheril Mehta | D9: Cheril, the effort that you have put into making Notifications on Binge+ live is remarkable. All the CLM and promotional campaigns planned and executed by you to every last detail to win back Binge customers on Binge+ & to improve engagement of existing customers have been having a significant impact on the KPIs & this will only improve further. Your collaborative spirit and willingness to support others have helped in making this possible. Not to mention, your attention to detail that makes you more unique. Your dedication is truly commendable and deeply appreciated! Keep up the good work! | E9: M4 | F9: Manager - Subscriber Marketing | G9: Commercial | H9: Corporate | I9: Q4-FY24 | J9: CEO of the Quarter | K9: =_xlfn.CONCAT(J9," ",I9) -> CEO of the Quarter Q4-FY24
A10: 9 | B10: 6745 | C10: Shriram Mahajan | D10: Shriram Congratulations on your ever Highest Achievement of TSK Active for the month of March 2024 ! Keep it up | E10: M4 | F10: Manager - Trade Sales | G10: Sales | H10: West | I10: Q4-FY24 | J10: CEO of the Quarter | K10: =_xlfn.CONCAT(J10," ",I10) -> CEO of the Quarter Q4-FY24
A11: 10 | B11: 5129 | C11: Aditya Sharma | D11: Sandeep Mann ( Technology )-Aditya has been crucial in helping us getting the RECD work completed for DG Sets which was supposed to be completed by 31st Dec 23, he helped us to get the PO released for this work at a very brisk rate coordinating with all the stake holders, we deeply appreciate his dedication and competence which demonstrated Collaboration, ownership, speed for the closure of subjected issue which helped us to comply with the govt guidelines well before the deadlines. | E11: M3 | F11: General Manager - Supply Chain Services | G11: Finance | H11: North | I11: Q4-FY24 | J11: CEO of the Quarter | K11: =_xlfn.CONCAT(J11," ",I11) -> CEO of the Quarter Q4-FY24
A12: 11 | B12: 7667 | C12: Janarthanan Thangavelu | D12: Truly appreciate Jana for optimizing BI operations stream. Since 3 last months there are no issues in month end processing, everything went smooth. Thanks for building BI Operation Dashboard which is extremely helpful to business owners to track their RR status directly from MS teams channel seamlessly.Superb work demonstrated. Keep it up. | E12: M4 | F12: Senior Manager - IT Delivery | G12: IT | H12: South | I12: Q4-FY24 | J12: CEO of the Quarter | K12: =_xlfn.CONCAT(J12," ",I12) -> CEO of the Quarter Q4-FY24
A13: 12 | B13: 7157 | C13: Suraj Pandey | D13: Prasanna Kumar Singh ( Sales )-I appreciate your effectiveness and precision in managing MDU installation in and around Lucknow. We are acquiring hotels and other commercial establishments on a good speed and your support in installing MDU set up at these places is recognised. You not only help us in giving installations with a good speed and deliver always on time, but also you own your commitment. Keep up this good work. | E13: M5 | F13: Assistant Manager - Field Service Delivery | G13: Field Service Delivery | H13: North | I13: Q4-FY24 | J13: CEO of the Quarter | K13: =_xlfn.CONCAT(J13," ",I13) -> CEO of the Quarter Q4-FY24
... A105: 104 | B105: 7250 | C105: Prachodaya Das | D105: Anitha Joy (Commercial) -Need to appreciate Prachodaya for quick collaboration and speed to go live of ten floaters along with the 1 alias services, in terms of required information like EPG No., genre and the schedules for the same with which has helped revenue teams to monetize the additional bandwidth of GSAT-24. Thank you. | E105: M4 | F105: Manager - Subscriber Marketing | G105: Commercial | H105: Corporate | I105: Q3-FY24 | J105: CEO of the Quarter | K105: =_xlfn.CONCAT(J105," ",I105) -> CEO of the Quarter Q3-FY24
A106: 105 | B106: 7237 | C106: Lakshya Lohumi | D106: YashasviGupta (Commercial) -Lakshya has been driving daily content led campaigns for Binge mobile app on Clevertap with rigour and ownership. This entails sending notifications basis content go-live and even on weekends. She has played pivotal role in go-live of new payment gateway (PayU) for Binge mobile and has good grip and understanding of transaction journeys and dashboards which has been of great help in improving transaction success rates for the new PG. Kudos to the efforts and wishing her good luck to keep up the good work. | E106: #N/A | F106: Manager - Subscriber Marketing | G106: Commercial | H106: Corporate | I106: Q3-FY24 | J106: CEO of the Quarter | K106: =_xlfn.CONCAT(J106," ",I106) -> CEO of the Quarter Q3-FY24
A107: 106 | B107: 7123 | C107: Kumar Gaurav | D107: Vijay Chandel (Technology) -Gaurav took Ownership and modified Service Count report during Satellite Migration activity carried on GSAT24 and GSAT 1O services including addition of 15 Transponders. Which help us to keep track of services within Tata Play Platform. | E107: M5 | F107: Assistant Manager - Broadcast operations | G107: Technology | H107: North | I107: Q3-FY24 | J107: CEO of the Quarter | K107: =_xlfn.CONCAT(J107," ",I107) -> CEO of the Quarter Q3-FY24
A108: 107 | B108: 2038 | C108: Kishore V. Reddy | D108: Komal Sahu (Commercial) -GSAT-24 migration was a critical project from Customer retention PoV. We had many ODU & MDU customers holding PVR,DS34T(SD on 96-97 series) and on SUPERLNB 1, that were affected due this migration and our objective was complete base retention. We immediately started working on building mService solution with Kishore. Within 1 week, we had mService solution ready, built BULKWOs and successive days FS team was at subscriber's door for box or LnB replacement. We started with 6k BulkWO with multiple teething issues at mService but Kishore was resolving with speed and agility to ensure FS team is duly supported and WO are closed with utmost customers satisfaction. We kept on adding more steps into this solution like giving credit for subs charged for service visits; again Kishore built a makeshift solution using the existing solution to maintain the execution pace. We would like to thank Kishore by giving this spot and supporting us in tight timelines. | E108: M3 | F108: Assistant General Manager - IT Delivery | G108: IT | H108: South | I108: Q3-FY24 | J108: CEO of the Quarter | K108: =_xlfn.CONCAT(J108," ",I108) -> CEO of the Quarter Q3-FY24
A109: 108 | B109: 7722 | C109: Aryan Raj | D109: Pradeep Maurya (Sales) -Well Done Aryan!!!This is the Great Start by Champ.Being a ET,Aryan learn the Rural Trade Very fast and the speed of Execution is amazing.He able to make impact by his people Management skills. He able to understand the needs and wants very well which help him to get the things going in a WIN WIN way.Being just 3 days old in current territory he able to achieve more than 11o% on most of the KPIs with highest Ever Act and TSK Active in Nov Month..KUDOS to you Aryan and Keep up the Good Work. | E109: M5 | F109: Assistant Manager - Trade Sales | G109: Sales | H109: West | I109: Q3-FY24 | J109: CEO of the Quarter | K109: =_xlfn.CONCAT(J109," ",I109) -> CEO of the Quarter Q3-FY24
A110: 109 | B110: 4171 | C110: Mohd Irfan | D110: C. Sheik Mehaboob Basha (Field Service Delivery) -Hi Irfan, Thanks for coordinating with TAJ properties SPOC person & fixed appointments, arranged manpower & visited site with Trainer & Auditor for successful completion of LH services migration in TAJ properties in Delhi. LH services migration on TAJ properties completed within Time so that no channel issues in these premium sites post GSAT 24 migration. | E110: M4 | F110: Senior Manager - Field Service Delivery | G110: Field Service Delivery | H110: North | I110: Q3-FY24 | J110: CEO of the Quarter | K110: =_xlfn.CONCAT(J110," ",I110) -> CEO of the Quarter Q3-FY24
A111: 110 | B111: 1404 | C111: Robin Thomas | D111: Shayor Das (Field Service Delivery) -MDU related concepts are very technical. The knowledge of Backbone Design, different types of equipment and proper troubleshooting steps is very critical for Field Team. Apart from Theoretical knowledge, proper hands on practical training is also very important. But organizing classroom training is challenging because of logistics issue and involve cost also. Robin understood this challenge and designed an MDU Training Kit which is an actual working replica of MDU Backbone which has all the components and equipment and it can be connected with Tata Play live signal. Since this MDU Training Kit is a mobile unit so Trainer can carry it along with himself and can organize trainings @ ISP locations also. This Kit has both Single Trunk and 4 Trunk design and all type of real life simulations can be practiced on this kit. MDU Training Kit is the innovation done by Robin Thomas and now we have replicated this best practice in rest of the circles too. | E111: M4 | F111: Senior Manager - Field Service Delivery Support | G111: Field Service Delivery | H111: North | I111: Q3-FY24 | J111: CEO of the Quarter | K111: =_xlfn.CONCAT(J111," ",I111) -> CEO of the Quarter Q3-FY24
A112: 111 | B112: 2651 | C112: Vineet Malik | D112: Nandini . (Technology) -Appreciate taking ownership & collaborating with internal & external teams & plan the upgrade effectively for new software in Binge+, enhancing the MDU robustness, required for GSAT24 migration. Thank you! | E112: M3 | F112: Assistant General Manager - Consumer Technology | G112: Technology | H112: North | I112: Q3-FY24 | J112: CEO of the Quarter | K112: =_xlfn.CONCAT(J112," ",I112) -> CEO of the Quarter Q3-FY24
A113: 112 | B113: 1585 | C113: Vasumathy S. | D113: YashasviGupta (Customer Operations) -Vasu has been working on Delinking UAT end to end. It is a super complex project with lot of scenarios and confusions and vasu has been bravely facing it all and doing the UAT. Kudos to her. | E113: M4 | F113: Manager - Systems Solutions & Design - COSSG | G113: Customer Operations | H113: South | I113: Q3-FY24 | J113: CEO of the Quarter | K113: =_xlfn.CONCAT(J113," ",I113) -> CEO of the Quarter Q3-FY24
A114: 113 | B114: 1377 | C114: B.P. Tharamani | D114: Shrinidhi DC (Customer Operations) -Thara have taken the ownership in closing the Airtel MSA. She has coordinated with multiple teams like - IT, SSD, Legal, SCM and Vendor teams in diligently following up, tracking the clauses under discussion and bringing the stakeholders on several calls for closure. | E114: M5 | F114: Assistant Manager - Vendor Management & Outbound Billing Operations | G114: Customer Operations | H114: South | I114: Q3-FY24 | J114: CEO of the Quarter | K114: =_xlfn.CONCAT(J114," ",I114) -> CEO of the Quarter Q3-FY24
A115: 114 | B115: 2990 | C115: Anwar Ali | D115: Nandini . (Technology) -Appreciate your good work in collaborating with internal & external teams and Middleware partners for the new software upgrade for enhancing the MDU robustness, required for GSAT24 migration. The excel template you created to monitor the software upgrade was helpful, thank you & keep it up! | E115: M4 | F115: Senior Manager - Consumer Technology | G115: Technology | H115: North | I115: Q3-FY24 | J115: CEO of the Quarter | K115: =_xlfn.CONCAT(J115," ",I115) -> CEO of the Quarter Q3-FY24
A116: 115 | B116: 5897 | C116: Anil Kumar N | D116: Kishore V. Reddy (IT) -Thank you Anil for all your support in sorting the LDP Renewal flow on What's app which was delaying the project go live. Your commitment helped me fix the PDF issue & support on UAT helped close it in a days time. Great to have you in IT team. | E116: M3 | F116: General Manager - IT Architecture | G116: IT | H116: South | I116: Q3-FY24 | J116: CEO of the Quarter | K116: =_xlfn.CONCAT(J116," ",I116) -> CEO of the Quarter Q3-FY24
A117: 116 | B117: 3653 | C117: Geetesh Fulari | D117: Pradeep Maurya (Sales) -Once a Champion Always a Champion and always stands for Team. Geetesh done 545 bulk in Dec and ensuring that no account go to competition.This is Commendable Ach and help in getting higher Market share.He also helps in getting more revenue by selling higher end packs to bulks and Ensure Annual Subscription...Kudos to You. | E117: M4 | F117: Senior Manager - Direct Sales | G117: Sales | H117: West | I117: Q3-FY24 | J117: CEO of the Quarter | K117: =_xlfn.CONCAT(J117," ",I117) -> CEO of the Quarter Q3-FY24
A118: 117 | B118: 4036 | C118: Gautam Sah | D118: Nitish Singhal (Technology) -Supported in network connectivity provision by laying the cable in critical area with complete safety and precautions. Work done is exemplary and very quick. Thanks. | E118: M5 | F118: Senior Executive - Facilities | G118: Technology | H118: North | I118: Q3-FY24 | J118: CEO of the Quarter | K118: =_xlfn.CONCAT(J118," ",I118) -> CEO of the Quarter Q3-FY24
... A214: 213 | B214: 5782 | C214: Somisetty Srinivas | D214: Sirmad Hasan - Srinivas is one of the most dedicated and helpful individual I have collaborated with at Tata Play. He takes things up responsibly and always delivers results on time. He is ever ready to support business and provides different angles through data. He represents Tata Play in the true sense by taking by ownership and delivering tasks with speed. | E214: M4 | F214: Manager - MIS & Business Information | G214: Field Service Delivery | H214: South | I214: Q1-FY26 | J214: CEO of the Quarter | K214: =_xlfn.CONCAT(J214," ",I214) -> CEO of the Quarter Q1-FY26

Sheet Spot & Spot of the Month
A1: Receiver Employee Id | B1: Receiver Name | C1: Nominator Employee Id | D1: Nominator Name | E1: Citation | F1: Reward Name | G1: Nomination Date | H1: Department | I1: Region | J1: Points | K1: Month- Year | L1: FY
A2: 3964 | B2: S Waseem Ulla | C2: 7400 | D2: Vikas Soni | E2: Waseem has been very helpful with CRM related requirements and with BE<>SSD weekly connects.\nHis swift action in terms of processing the call log creation requests is very helpful for last min project changes.\nBE<>SSD cadence tracker maintained by him is very useful for us and it is helping us in driving many projects. Siebel release related connects are another example where his coordination is well appreciated by the entire BE team.\n\nThanks a lot, Waseem | F2: Spot of the Month | G2: 45603 | H2: Customer Operations | I2: South | J2: INR 500.0 | K2: =TEXT(G2,"mm-yyyy") -> 11-2024 | L2: FY24-25
A3: 7661 | B3: Wilson Dsouza | C3: 4889 | D3: Dilip Kumar Singh | E3: Good effort in securing business of new client "ABG- Indriya" with a decent deal volume by combo deal structure of landing channel100 + S&S for the month of Oct-Nov'24. Hence our overall new client revenue contribution weightage has also increased in Q3. | F3: Spot | G3: 45603 | H3: B2B | I3: Corporate | J3: INR 0.0 | K3: =TEXT(G3,"mm-yyyy") -> 11-2024 | L3: FY24-25
A4: 6707 | B4: Avishek Bose | C4: 7418 | D4: Rabindra Agarwal | E4: Avishek has delivered well in the key input parameters like new dealer appointment and highway town coverage in his territory and has also become the Winner of Trail Blazer Contest in the month of Oct 24. This is not done in a month alone, but this is a result of hard work done for new outlet opening and dealer engagement over a period of time which has given him the result in incremental stocking dealers and TSK. Good job Avishek and keep up the good work in coming months too.\n | F4: Spot | G4: 45602 | H4: Sales | I4: East | J4: INR 0.0 | K4: =TEXT(G4,"mm-yyyy") -> 11-2024 | L4: FY24-25
A5: 4009 | B5: Sharath K S | C5: big.stage@tataplay.com | D5: Big Stage | E5: Meghna Tiwari - Sharath has been exceptional support and has helped consistently to keep track with our work on Binge.\\nWith his help and his efforts for seamless coordination within his team, he has contributed immensely to the smooth functioning of our OTT aggregator platform. His dedication and collaborative spirit make him an indispensable part of our success.\\nThanks Sharath! | F5: Spot of the Month | G5: 45602 | H5: Commercial | I5: South | J5: INR 500.0 | K5: =TEXT(G5,"mm-yyyy") -> 11-2024 | L5: FY24-25
A6: 4013 | B6: Sheeja P.A. | C6: big.stage@tataplay.com | D6: Big Stage | E6: Rishikesh Patil - Sheeja played a crucial role in the month of September by collaborating and helping Content team with a high number of de-packaging and re-packaging requests which helped us recover 50% of the outstanding amounts from the partners. Her quick support played a very important role to help us set context with the partners to avoid late payments. Thank you Sheeja for all the support!\\n | F6: Spot of the Month | G6: 45602 | H6: Commercial | I6: South | J6: INR 500.0 | K6: =TEXT(G6,"mm-yyyy") -> 11-2024 | L6: FY24-25
A7: 3964 | B7: S Waseem Ulla | C7: big.stage@tataplay.com | D7: Big Stage | E7: Anshul Nuwal - Regarding redesign of framework of sending out the communication for Service Request's status updates, there was a requirement of converting a master table of more than 80k unique records to another table which will have only 3 to 4 k unique records as per new architecture. Waseem understood the new framework and requirement very quickly and returned with updated master table within a day with almost 0 discrepancies. Kudos to Waseem for showing this support which helped IT to finish the task quickly in timely manner. | F7: Spot of the Month | G7: 45602 | H7: Customer Operations | I7: South | J7: INR 500.0 | K7: =TEXT(G7,"mm-yyyy") -> 11-2024 | L7: FY24-25
A8: 4068 | B8: Nagesh Y Bhonsle | C8: big.stage@tataplay.com | D8: Big Stage | E8: Anirudh Das - Shout-out to Nagesh for taking ownership of marketing campaign deployments on TPMA properties - Be it a late-night request for midnight release or a last-minute ad-hoc email, Nagesh consistently delivers the ask with speed and accuracy. Thank you for your support Nagesh! | F8: Spot of the Month | G8: 45602 | H8: Commercial | I8: South | J8: INR 500.0 | K8: =TEXT(G8,"mm-yyyy") -> 11-2024 | L8: FY24-25
A9: 7756 | B9: Mayur Wadulkar | C9: big.stage@tataplay.com | D9: Big Stage | E9: Rishikesh Patil - Mayur played an important role in the month of September by collaborating and helping Content team with a high number of de-packaging and re-packaging requests which helped us recover 50% of the outstanding amounts from the partners. His quick support played a very important role to help us set context with the partners to avoid late payments. Thank you Mayur for all the support!\\n | F9: Spot of the Month | G9: 45602 | H9: Commercial | I9: South | J9: INR 500.0 | K9: =TEXT(G9,"mm-yyyy") -> 11-2024 | L9: FY24-25
A10: 6586 | B10: Losang Yolmo | C10: big.stage@tataplay.com | D10: Big Stage | E10: Rishikesh Patil - Losang played an important role in the month of September by collaborating and helping Content team with a high number of de-packaging and re-packaging requests which helped us recover 50% of the outstanding amounts from the partners. His quick support played a very important role to help us set context with the partners to avoid late payments. Thank you Losang for all the support!\\n | F10: Spot of the Month | G10: 45602 | H10: Commercial | I10: Corporate | J10: INR 500.0 | K10: =TEXT(G10,"mm-yyyy") -> 11-2024 | L10: FY24-25
A11: 2444 | B11: Harsh Aggarwal | C11: big.stage@tataplay.com | D11: Big Stage | E11: Parth Shah - Harsh is the go-to person for Tech issues related to my Binge partners. He is good at coordinating & prioritizing across his team, specifically for urgent issues related to content ingestion failure, playback issues and metadata problems. His ownership and prompt action are much appreciated. | F11: Spot of the Month | G11: 45602 | H11: Technology | I11: North | J11: INR 500.0 | K11: =TEXT(G11,"mm-yyyy") -> 11-2024 | L11: FY24-25
A12: 7469 | B12: Chien Sharma | C12: big.stage@tataplay.com | D12: Big Stage | E12: Parth Shah - Chien has been very helpful in project managing across Binge partners and helping co-ordinate & align team members to resolve issues. Her collaboration and ownership on closing items like Shorts TV ingestion, PTC Play DRM issues, Hallmark API etc. is much appreciated. | F12: Spot of the Month | G12: 45602 | H12: Technology | I12: North | J12: INR 500.0 | K12: =TEXT(G12,"mm-yyyy") -> 11-2024 | L12: FY24-25
A13: 4010 | B13: Abhishek K R | C13: big.stage@tataplay.com | D13: Big Stage | E13: Meghna Tiwari & Rabiya Sidiqa - Abhishek is a brilliant self-starter, he ensures the seamless functioning of our Binge app, consistently solving issues with initiative and precision.\\nHis excellent people management skills foster collaboration across teams, contributing significantly to our success. \\nHis dedication, leadership, and positive influence make him a true inspiration and an invaluable team member.\nAbhishek provided valuable assistance during the CMS/TA deployment process. I commend his efforts during the TA modifications, where he exhibited strong ownership skills. He played a crucial role in loading the updated schedules and banks into the system. I sincerely appreciate the time and energy he has devoted to this task and the successful completion of it. Thank you for your dedication and ongoing support. | F13: Spot of the Month | G13: 45602 | H13: Commercial | I13: South | J13: INR 500.0 | K13: =TEXT(G13,"mm-yyyy") -> 11-2024 | L13: FY24-25
A14: 3323 | B14: Amit Singh | C14: 4724 | D14: Atul Pawar | E14: Dear Amit I appreciate your collaboration at Partner end to take desire project wos completion vai motivation at ISP Staff level In Sep Month you were 1.9% and Oct you finish to double 7 % with own positive new ideas implementations \n\nKeep such new ideas implementation to get new results | F14: Spot | G14: 45601 | H14: Field Service Delivery | I14: West | J14: INR 0.0 | K14: =TEXT(G14,"mm-yyyy") -> 11-2024 | L14: FY24-25
A15: 3328 | B15: Rakesh Tiwary | C15: 4724 | D15: Atul Pawar | E15: Dear Rakesh I appreciate your collaboration at Partner end to take desire project wos completion vai motivation at ISP Staff level In Sep Month you were 4% and Oct you finish to double 8.7% with own positive new ideas implementations \n\nKeep such momentum to take new and positive results | F15: Spot | G15: 45601 | H15: Field Service Delivery | I15: West | J15: INR 0.0 | K15: =TEXT(G15,"mm-yyyy") -> 11-2024 | L15: FY24-25
A16: 1680 | B16: P. Gopal Rao | C16: 4724 | D16: Atul Pawar | E16: Dear Gopal\n\nI appreciate you taken as challenge yourself to take your Name in West region TOP ASM in BMP\n\nIn Sep Month you were 10% and Oct you finish 15 % get you in West Region TOP ASM \n\nYou show very good SPEED to reach to desire % so keep it up such to get new activity\n | F16: Spot | G16: 45601 | H16: Field Service Delivery | I16: West | J16: INR 0.0 | K16: =TEXT(G16,"mm-yyyy") -> 11-2024 | L16: FY24-25
A17: 7895 | B17: Pankaj Satpudke | C17: 4724 | D17: Atul Pawar | E17: Dear Pankaj I appreciate your collaboration at Partner end to take desire project wos completion vai motivation at ISP Staff level In Sep Month you were 5% and Oct you finish to double 9.6% with own positive new ideas implementations \n\nKeep positive momentum at Partner level to get positive result | F17: Spot | G17: 45601 | H17: Field Service Delivery | I17: West | J17: INR 0.0 | K17: =TEXT(G17,"mm-yyyy") -> 11-2024 | L17: FY24-25
A18: 7877 | B18: Manik Mittal | C18: 4724 | D18: Atul Pawar | E18: Dear Manik\n\nI appreciate your Dedication and partner end motivation activity wherein In Oct Month you taken Binge mobile conversion as Challenge to get you as West Region Top ASM.\n\nIn Oct Month you were 8% and Nov you finish to double 16% to remain West Region Top 5 ASM\n\nYou taken Challenge as Ownership and made Delivery and keep same momentum | F18: Spot of the Month | G18: 45601 | H18: Sales | I18: West | J18: INR 500.0 | K18: =TEXT(G18,"mm-yyyy") -> 11-2024 | L18: FY24-25
A19: 7877 | B19: Manik Mittal | C19: 4724 | D19: Atul Pawar | E19: Dear Manik\n\nI appreciate your Dedication and partner end motivation activity wherein In Oct Month you taken Binge mobile conversion as Challenge to get you as West Region Top ASM.\n\nIn Oct Month you were 8% and Nov you finish to double 16% to remain West Region Top 5 ASM\n\nYou taken Challenge as Ownership and made Delivery and keep same momentum | F19: Spot | G19: 45601 | H19: Sales | I19: West | J19: INR 0.0 | K19: =TEXT(G19,"mm-yyyy") -> 11-2024 | L19: FY24-25
A20: 6500 | B20: Gopal Dey | C20: 7418 | D20: Rabindra Agarwal | E20: Gopal has taken ownership of the business and delivered well in the key input parameters in the month of October. This is not done in a month alone, but this is a result of inputs like new outlet opening, CEISP engagement and KRO engagement over a period of time which has given him the outcome during this season time. Good job Gopal and keep up the good work in coming months too | F20: Spot | G20: 45600 | H20: Sales | I20: East | J20: INR 0.0 | K20: =TEXT(G20,"mm-yyyy") -> 11-2024 | L20: FY24-25
A21: 7287 | B21: Deepti Yadav | C21: 1763 | D21: Nirmal Kumar | E21: Thanks for the prompt support & collaboration in getting the invoices cleared in Zycus portal which has helped in running the critical operations smoothly | F21: Spot | G21: 45600 | H21: Technology | I21: North | J21: INR 0.0 | K21: =TEXT(G21,"mm-yyyy") -> 11-2024 | L21: FY24-25
A22: 7056 | B22: Ajay Harwani | C22: 7225 | D22: Divya Shenoy | E22: Ajay helped resolve the issue on Sony Liv on the Diwali evening despite prior personal commitments. He exhibited ownership and collaborated with the Liv team to arrive at a solution and fixed the issue along with the help of the backend team from TTN. A big shoutout to Ajay. :)\n | F22: Spot | G22: 45600 | H22: Technology | I22: West | J22: INR 0.0 | K22: =TEXT(G22,"mm-yyyy") -> 11-2024 | L22: FY24-25
A23: 7418 | B23: Rabindra Agarwal | C23: 3624 | D23: Chitiz Rai | E23: Rabindra has taken ownership of the Business and came out as top performer in the month of October. This was not done in a month, the result is due to months of inputs like new outlet opening, CEISP appointment and KRO engagement which has given him the edge during festive times. Good job and keep it up Rabindra | F23: Spot | G23: 45600 | H23: Sales | I23: East | J23: INR 0.0 | K23: =TEXT(G23,"mm-yyyy") -> 11-2024 | L23: FY24-25
A24: 1192 | B24: Jaipal Singh Bhandari | C24: 7444 | D24: Parikshit Marwah | E24: Self-initiative support given for Store old assets and accessories scrap | F24: Spot | G24: 45593 | H24: Technology | I24: North | J24: INR 0.0 | K24: =TEXT(G24,"mm-yyyy") -> 10-2024 | L24: FY24-25
A25: 2056 | B25: Kamal Kishore Sharma | C25: 7444 | D25: Parikshit Marwah | E25: Excellent work in Store STBs reconciliation & scrap management. | F25: Spot | G25: 45593 | H25: Technology | I25: North | J25: INR 0.0 | K25: =TEXT(G25,"mm-yyyy") -> 10-2024 | L25: FY24-25
A26: 6519 | B26: Rinkesh Pulekar | C26: big.stage@tataplay.com | D26: Big Stage | E26: Lakshya Lohumi - Rinkesh has been a key driver in programming of the largest acquisition channel for Binge. All the key titles were promoted swiftly and with speed on Ch100, even on weekends!!! He has always been understanding and ready to lend his support during crucial times for binge business. Onwards and upwards!!! | F26: Spot of the Month | G26: 45589 | H26: B2B | I26: Corporate | J26: INR 500.0 | K26: =TEXT(G26,"mm-yyyy") -> 10-2024 | L26: FY24-25
A27: 7827 | B27: Vinodkumar Jakkala | C27: big.stage@tataplay.com | D27: Big Stage | E27: Lakshya Lohumi - Vinod has recently join the binge team and has been able to adjust to the binge ecosystem so well. His understanding and clarity coupled with his go-getter attitude has helped us in the launch and programming of CH100 with ease on weekdays and weekends as well!! Really grateful for all the support received during critical launches :) | F27: Spot of the Month | G27: 45589 | H27: B2B | I27: Corporate | J27: INR 500.0 | K27: =TEXT(G27,"mm-yyyy") -> 10-2024 | L27: FY24-25
A28: 4004 | B28: Velu C | C28: big.stage@tataplay.com | D28: Big Stage | E28: Rohit Mishra - Velu has been a great support in execution of multiple packaging changes in a quick succession. These are namely RIO rollback with simultaneous pricing revision to protect revenues, launch of new acquisition, renewal and winback LDP packs post-RIO (with higher price and higher content) and increase in HD box prices of 2 major states to improve acquisition quality. Thank you and keep up the good work, Velu! | F28: Spot of the Month | G28: 45589 | H28: Commercial | I28: South | J28: INR 500.0 | K28: =TEXT(G28,"mm-yyyy") -> 10-2024 | L28: FY24-25
A29: 2298 | B29: Thanuja M.M. | C29: big.stage@tataplay.com | D29: Big Stage | E29: Gurpreet Singh - HI Thanu \\nThank you for your effort and time on the NEF guidelines and SR Types and Tagging | F29: Spot of the Month | G29: 45589 | H29: Customer Operations | I29: South | J29: INR 500.0 | K29: =TEXT(G29,"mm-yyyy") -> 10-2024 | L29: FY24-25
A30: 1313 | B30: Lenin Suresh Raj | C30: big.stage@tataplay.com | D30: Big Stage | E30: Amitabh Das - Thanks a lot Lenin for the continuous support you have provided by sharing your expertise and knowledge with us. \\nWe count on you, and you have always delivered more than what we expected.\\nThank you for being such a team player. We wouldn\\u2019t be the same without you! | F30: Spot of the Month | G30: 45589 | H30: Customer Operations | I30: South | J30: INR 500.0 | K30: =TEXT(G30,"mm-yyyy") -> 10-2024 | L30: FY24-25
A31: 5976 | B31: Rohit Jaggi | C31: big.stage@tataplay.com | D31: Big Stage | E31: Piyush Gupta - Your positive attitude , Collaboration and dedication make all the difference, and for that, I am genuinely grateful. With this coordination we can achieve milestones in Sales & Service...Keep this coordination always on. Thanks | F31: Spot of the Month | G31: 45589 | H31: Field Service Delivery | I31: North | J31: INR 500.0 | K31: =TEXT(G31,"mm-yyyy") -> 10-2024 | L31: FY24-25
A32: 17 | B32: Kavita Rohan | C32: big.stage@tataplay.com | D32: Big Stage | E32: Pankaj Joshi - I really appreciate your continuous efforts for implementation of CLM tools for Onboarding Channel Partners.\\n\\u00A0\\nIn last 6 months, you have co-ordinated very well with all Regional MIS, Finance, Legal & CLM teams for timely implementation of CLM tools.\\n\\u00A0\\nReally appreciate your commitment & dedication towards work! Keep up the good work! | F32: Spot of the Month | G32: 45589 | H32: Sales | I32: Corporate | J32: INR 500.0 | K32: =TEXT(G32,"mm-yyyy") -> 10-2024 | L32: FY24-25
A33: 7247 | B33: Pracheer Pranay | C33: big.stage@tataplay.com | D33: Big Stage | E33: Pratiksha Mainkar - Pracheer was able to quickly turn around the logistics for an important review in Delhi. He managed multiple stakeholders and constraints to make the review a success. There were no gaps in the planning process and the execution was smooth with all things going as per plan. He had meagre four days to make this happen, well done Pracheer! Keep up the good work. | F33: Spot of the Month | G33: 45589 | H33: Human Resources | I33: Corporate | J33: INR 500.0 | K33: =TEXT(G33,"mm-yyyy") -> 10-2024 | L33: FY24-25
A34: 4935 | B34: Satish Kumar K P | C34: big.stage@tataplay.com | D34: Big Stage | E34: Sandeep Sharma - Thanks Satish,\\nFor Solving all critical issues and clearing all the pending work. | F34: Spot of the Month | G34: 45589 | H34: Technology | I34: South | J34: INR 500.0 | K34: =TEXT(G34,"mm-yyyy") -> 10-2024 | L34: FY24-25
A35: 7123 | B35: Kumar Gaurav | C35: big.stage@tataplay.com | D35: Big Stage | E35: Asheesh Kumar - Organized the audio details of all the channels which have multiple language tracks. Demonstrate the technical certainty of the audio configuration of Broadcaster as well as on our platform in order to avoid any mismatch audio language issue. It will help us to provide the configuration data record as and when required. | F35: Spot of the Month | G35: 45589 | H35: Technology | I35: North | J35: INR 500.0 | K35: =TEXT(G35,"mm-yyyy") -> 10-2024 | L35: FY24-25
A36: 7576 | B36: Radha Krishna Jha | C36: big.stage@tataplay.com | D36: Big Stage | E36: Shivam Gaur, Masroor Jafar Siddiqui & Sumit Bhatia - Radha, You are always very supportive for productivity of Circle and you are always available to help which shows your dedication towards the business.\\nVery Well Done ..... \nRadha Have done good work and takes ownership of the work given to him beside his own domain also. He work on the things which are not in his KPI but supportive for Circle business. He calls top dealer for quality promoter for productivity. He helps promoter having difficulty in attandance and onboarding. He shares individual report like New dealer creation report with data whose billing or latlong capture is pending. He provides any help which we need if we are in market like detail of DSR wise activating ols et. Over all he is dedicated to circle business productivity.\\n Radha has always supporting in Data Points, Boosting My DSR to Achieve Bandhan Programme & Bandhan Booster, he is just one call away for any help required me for Business Success. | F36: Spot of the Month | G36: 45589 | H36: Sales | I36: North | J36: INR 500.0 | K36: =TEXT(G36,"mm-yyyy") -> 10-2024 | L36: FY24-25
A37: 6461 | B37: Veerendra Pathak | C37: big.stage@tataplay.com | D37: Big Stage | E37: Prasanna Kumar Singh - Veerendra, Your consistency and approach is appreciated. Maintaining performance on top level and above that consistent contribution to new dealer appointment is a key achievement. You also won new dealer contest and that shows your high level of ownership. | F37: Spot of the Month | G37: 45589 | H37: Sales | I37: North | J37: INR 500.0 | K37: =TEXT(G37,"mm-yyyy") -> 10-2024 | L37: FY24-25
... A54: 6541 | B54: Akash Nag M B | C54: big.stage@tataplay.com | D54: Big Stage | E54: Rahul Bhalla - Akash, you truly make a difference with your unlimited support. You're quick and on time help in terms of providing the reports and required data for different analysis has been fantastic. Your suggestions / ideas in order to improvise on reports also helps us in terms of watching the output / conversions with different perspectives. We appreciate all your efforts and your quick turn around on requirements. | F54: Spot of the Month | G54: 45589 | H54: Customer Operations | I54: South | J54: INR 500.0 | K54: =TEXT(G54,"mm-yyyy") -> 10-2024 | L54: FY24-25
A55: 4889 | B55: Dilip Kumar Singh | C55: 66 | D55: Shalmali Desai | E55: Fantastic job on securing Phillips Airfryer bulk ad booking for Ch 100, delivering over 35% of October revenue in one go! This is exactly the kind of ad sales deal that sets the tone for successful festive season. Your ability to drive the results is remarkable. Keep up the excellent work! | F55: Spot of the Month | G55: 45587 | H55: B2B | I55: North | J55: INR 500.0 | K55: =TEXT(G55,"mm-yyyy") -> 10-2024 | L55: FY24-25
A56: 7287 | B56: Deepti Yadav | C56: 3973 | D56: Sandeep Mann | E56: Deepti has been instrumental in handling Zycus related invoices handling, she has been very helpful for guiding us to process the invoice and to raise query in case any invoice has been wrongly uploaded by vendors.\nHer proactive approach for handling finance issues have been exceptional.\nShe collaborates well and demonstrates speed in the helping our tasks resolved. | F56: Spot | G56: 45587 | H56: Technology | I56: North | J56: INR 0.0 | K56: =TEXT(G56,"mm-yyyy") -> 10-2024 | L56: FY24-25
A57: 2444 | B57: Harsh Aggarwal | C57: 7162 | D57: Parth Shah | E57: Harsh is the go-to person for Tech issues related to my Binge partners. He is good at coordinating & prioritizing across his team, specifically for urgent issues related to content ingestion failure, playback issues and metadata problems. His ownership and prompt action are much appreciated. | F57: Spot | G57: 45586 | H57: Technology | I57: North | J57: INR 0.0 | K57: =TEXT(G57,"mm-yyyy") -> 10-2024 | L57: FY24-25
A58: 7469 | B58: Chien Sharma | C58: 7162 | D58: Parth Shah | E58: Chien has been very helpful in project managing across Binge partners and helping co-ordinate & align team members to resolve issues. Her collaboration and ownership on closing items like Shorts TV ingestion, PTC Play DRM issues, Hallmark API etc. is much appreciated. | F58: Spot | G58: 45586 | H58: Technology | I58: North | J58: INR 0.0 | K58: =TEXT(G58,"mm-yyyy") -> 10-2024 | L58: FY24-25
A59: 887 | B59: S. Nithyanand Murthy | C59: 4222 | D59: Mohan Raj K.K. | E59: Nithyanand took ownership whenever we are in trouble with some mistakes done by partners in wrong recharge or wrong package selections. He always helped frontline team even after office hours or in holidays. Thank you very much for all your supports. | F59: Spot | G59: 45584 | H59: Customer Operations | I59: South | J59: INR 0.0 | K59: =TEXT(G59,"mm-yyyy") -> 10-2024 | L59: FY24-25
A60: 2733 | B60: Sangram Singh Poonia | C60: 4416 | D60: Vivek Kumar Shukla | E60: Thanks for taking ownership and setting up the Venus room ready for Online training. | F60: Spot | G60: 45581 | H60: Technology | I60: North | J60: INR 0.0 | K60: =TEXT(G60,"mm-yyyy") -> 10-2024 | L60: FY24-25
A61: 3902 | B61: Yogesh Sharma | C61: 5744 | D61: Rohan Mehra | E61: Yogesh has been very supportive in resolving RA cases & had worked as a strong median for us to move many cases to no debit where partner satisfaction got enhanced | F61: Spot of the Month | G61: 45580 | H61: Field Service Delivery | I61: North | J61: INR 500.0 | K61: =TEXT(G61,"mm-yyyy") -> 10-2024 | L61: FY24-25
A62: 7543 | B62: Eram . | C62: 4927 | D62: Rahul Puri | E62: Eram has done an exceptional behind the scenes job in collaborating with the Infosec team for the change of Thread Intelligence tools. This tool identifies any misuse / misinformation regarding Tata Play on the internet. The previous tool had various limitations, however she worked closely with the vendors, did a detailed PoC, created the Technology evaluation document along with Infosec team. Now she is closely involved in the migration and handholding implementation of the new tool. \nEram is single handedly handling all the alerts coming from the system and ensuring action by the respective stakeholders, till closure. Each month she apply her expertise in the field, identifies the genuine alerts and actions. Her experience in this field and the last one year learning has helped us procure a better tool. She also ensure due priority and speed of action for closure. Keep up the bar and all success will be yours, Thank you Eram | F62: Spot | G62: 45580 | H62: Finance | I62: South | J62: INR 0.0 | K62: =TEXT(G62,"mm-yyyy") -> 10-2024 | L62: FY24-25
A63: 2980 | B63: Sachin Joshi | C63: 1624 | D63: K. Kiran Kumar | E63: For compression equipment stability we required to replace AVP racks MDU units, Sachin Joshi provided his support for tracing out EATON ATS new MDU units and provided on time which is very helpful. | F63: Spot | G63: 45579 | H63: Technology | I63: North | J63: INR 0.0 | K63: =TEXT(G63,"mm-yyyy") -> 10-2024 | L63: FY24-25
A64: 7287 | B64: Deepti Yadav | C64: 1624 | D64: K. Kiran Kumar | E64: Deepti supported in a quick way for PR, PO related Query\u2019s and supported during verification of Invoices and processing, which is very helpful. | F64: Spot | G64: 45579 | H64: Technology | I64: North | J64: INR 0.0 | K64: =TEXT(G64,"mm-yyyy") -> 10-2024 | L64: FY24-25
A65: 7287 | B65: Deepti Yadav | C65: 2353 | D65: Arun Sapra | E65: I would like to express my gratitude to Ms. Deepti Yadav for her timely assistance in clarifying the Zycus Portal for invoicing processing, addressing the challenges encountered, and ensuring the resolution of outstanding issues. | F65: Spot | G65: 45579 | H65: Technology | I65: North | J65: INR 0.0 | K65: =TEXT(G65,"mm-yyyy") -> 10-2024 | L65: FY24-25
A66: 7287 | B66: Deepti Yadav | C66: 2220 | D66: Anshul Kapoor | E66: Thanks to Ms. Deepti Yadav for promptly supporting and making understand the Zycus Portal for Invoicing processing, resolving the issues faced & follow up closures. | F66: Spot | G66: 45579 | H66: Technology | I66: North | J66: INR 0.0 | K66: =TEXT(G66,"mm-yyyy") -> 10-2024 | L66: FY24-25
... A104: 7576 | B104: Radha Krishna Jha | C104: 7577 | D104: Sumit Bhatia | E104: Radha has always supporting in Data Points, Boosting My DSR to Achieve Bandhan Programme & Bandhan Booster, he is just one call away for any help required me for Business Success | F104: Spot | G104: 45561 | H104: Sales | I104: North | J104: INR 0.0 | K104: =TEXT(G104,"mm-yyyy") -> 09-2024 | L104: FY24-25
A105: 7886 | B105: Pawan Chandra | C105: big.stage@tataplay.com | D105: Big Stage | E105: Pavan Kumar Garg - Pawan, you have taken ownership and collaborated with your peers and delivered single digit critical WO and out of Top 15 Circle.\\nKeep the momentum up!!! | F105: Spot of the Month | G105: 45560 | H105: Field Service Delivery | I105: West | J105: INR 500.0 | K105: =TEXT(G105,"mm-yyyy") -> 09-2024 | L105: FY24-25
A106: 6551 | B106: Yasar Ali Khan | C106: big.stage@tataplay.com | D106: Big Stage | E106: K R Champa - Yasar Ali Khan we are proud to have you as a part of the TATA PLAY family as you have contributed to our success in making the customers smile. You have helped us achieve the level of customer experience we would like to provide on each interaction\\nThis is a token of appreciation for the good job done for the contest "Making Customer Smile".\\nLooking forward to having many more such smiles on our way towards every milestone. | F106: Spot of the Month | G106: 45560 | H106: Customer Operations | I106: South | J106: INR 500.0 | K106: =TEXT(G106,"mm-yyyy") -> 09-2024 | L106: FY24-25
A107: 3964 | B107: S Waseem Ulla | C107: big.stage@tataplay.com | D107: Big Stage | E107: Vikas Soni - Waseem has been very supportive when it comes to capturing and working on new requirements.\\nUnder R57, he has worked on more than 10 requirements including a few critical ones - SR scheduler, SR closeloop SMS, Core group desk creation, Open order auto cancellation, Account reactivation RPA.\\nThese initiatives are certainly going to reduce the cost to serve.\\nThanks, Waseem. | F107: Spot of the Month | G107: 45560 | H107: Customer Operations | I107: South | J107: INR 500.0 | K107: =TEXT(G107,"mm-yyyy") -> 09-2024 | L107: FY24-25
A108: 7413 | B108: Vikrant Singh | C108: big.stage@tataplay.com | D108: Big Stage | E108: Bhupendra Kumar - I would like to take this opportunity to thank you and appreciate your commitment to clean up the market Defective inventory, which has resulted in achieving the KPI (DSO) at 12 days in Bihar after a year time. The joint effort was instrumental in achieving this objective. | F108: Spot of the Month | G108: 45560 | H108: Field Service Delivery | I108: East | J108: INR 500.0 | K108: =TEXT(G108,"mm-yyyy") -> 09-2024 | L108: FY24-25
A109: 5805 | B109: Vidya . | C109: big.stage@tataplay.com | D109: Big Stage | E109: K R Champa - Vidya we are proud to have you as a part of the TATAPLAY family as you have contributed to our success in making the customers smile. You have helped us achieve the level of customer experience we would like to provide on each interaction.\\nThis is a token of appreciation for the good job done for the contest "Making Customer Smile".\\nLooking forward to having many more such smiles on our way towards every milestone. | F109: Spot of the Month | G109: 45560 | H109: Customer Operations | I109: South | J109: INR 500.0 | K109: =TEXT(G109,"mm-yyyy") -> 09-2024 | L109: FY24-25
A110: 1585 | B110: Vasumathy S. | C110: big.stage@tataplay.com | D110: Big Stage | E110: Velu C - I wanted to extend my heartfelt thanks to each of you for your diligent work in testing all the PCF parts of the Sony RIO activities, Binge and all BAU PCF's and CR's . Your attention to detail and commitment to ensuring everything functions perfectly have been crucial to the success of this project.\\nYour efforts have helped us move forward with confidence, knowing that we\\u2019ve thoroughly tested every aspect. I truly appreciate the time and energy you\\u2019ve dedicated to this task.\\nThank you for your hard work and continued support. | F110: Spot of the Month | G110: 45560 | H110: Customer Operations | I110: South | J110: INR 500.0 | K110: =TEXT(G110,"mm-yyyy") -> 09-2024 | L110: FY24-25
A111: 5714 | B111: Usha Rani K | C111: big.stage@tataplay.com | D111: Big Stage | E111: Divya Shenoy - Usha went out of her way to help overcome the issues with regard to KBC live event on Sony Liv. The solution was discussed, tried and tested over two days before the event went Live. Usha worked odd hours ensure that the content is pulled in and made available for seamless subscriber experience. | F111: Spot of the Month | G111: 45560 | H111: Commercial | I111: South | J111: INR 500.0 | K111: =TEXT(G111,"mm-yyyy") -> 09-2024 | L111: FY24-25
A112: 2315 | B112: Vasantha Kumar G. | C112: big.stage@tataplay.com | D112: Big Stage | E112: Velu C - I wanted extend my sincere appreciation for your dedicated work on the validations involved in our finance Go-ahead process for the price hike and RIO data.\\nYour contribution has been instrumental, and I am truly grateful for your unwavering commitment to excellence.\\u00A0\\nThank you for your continued hard work and for always delivering top-quality results. | F112: Spot of the Month | G112: 45560 | H112: Finance | I112: South | J112: INR 500.0 | K112: =TEXT(G112,"mm-yyyy") -> 09-2024 | L112: FY24-25
A113: 3955 | B113: Umashree C N | C113: big.stage@tataplay.com | D113: Big Stage | E113: K R Champa - Umashree we are proud to have you as a part of the TATAPLAY family as you have contributed to our success in making the customers smile. You have helped us achieve the level of customer experience we would like to provide on each call.\\nThis is a token of appreciation for the good job done for the contest "Making Customer Smile".\\nLooking forward to having many more such smiles on our way towards every milestone. | F113: Spot of the Month | G113: 45560 | H113: Customer Operations | I113: South | J113: INR 500.0 | K113: =TEXT(G113,"mm-yyyy") -> 09-2024 | L113: FY24-25
A114: 6434 | B114: Srinivasan Thiagarajan | C114: big.stage@tataplay.com | D114: Big Stage | E114: Nitin Gupta - Appreciate the efforts done and taking ownership to complete the technology office at fast pace and build a wonderful office as per the expectations of the company. | F114: Spot of the Month | G114: 45560 | H114: Finance | I114: Corporate | J114: INR 500.0 | K114: =TEXT(G114,"mm-yyyy") -> 09-2024 | L114: FY24-25
A115: 4009 | B115: Sharath K S | C115: big.stage@tataplay.com | D115: Big Stage | E115: Divya Shenoy - Sharath went out of her way to help overcome the issues with regard to KBC live event on Sony Liv. The solution was discussed, tried and tested over two days before the event went Live. Usha worked odd hours ensure that the content is pulled in and made available for seamless subscriber experience. | F115: Spot of the Month | G115: 45560 | H115: Commercial | I115: South | J115: INR 500.0 | K115: =TEXT(G115,"mm-yyyy") -> 09-2024 | L115: FY24-25
A116: 4935 | B116: Satish Kumar K P | C116: big.stage@tataplay.com | D116: Big Stage | E116: Sandeep Sharma - Hi Satish,\\n\\nThanks For Updating and solving the issues.\\nAlways you are in supporting and positive attitude.\\nThanks \\n\\n | F116: Spot of the Month | G116: 45560 | H116: Technology | I116: South | J116: INR 500.0 | K116: =TEXT(G116,"mm-yyyy") -> 09-2024 | L116: FY24-25
... A154: 2214 | B154: Aftab Khan | C154: big.stage@tataplay.com | D154: Big Stage | E154: Mayur Wadulkar - I would like to extend my heartfelt appreciation to Aftab for his outstanding work in closing the highly critical and significant Sony RIO-related campaign & What's App CRs within the allotted timeline. His dedication is evident in his willingness to stretch his working hours to ensure the CRs were signed off promptly. This commitment to excellence is truly commendable. | F154: Spot of the Month | G154: 45560 | H154: Customer Operations | I154: South | J154: INR 500.0 | K154: =TEXT(G154,"mm-yyyy") -> 09-2024 | L154: FY24-25
A155: 2056 | B155: Kamal Kishore Sharma | C155: 1938 | D155: Sandeep Sharma | E155: Thanks Kamal,\n\nFor your support and Guidance to do the work properly and time frame.\n | F155: Spot | G155: 45559 | H155: Technology | I155: North | J155: INR 0.0 | K155: =TEXT(G155,"mm-yyyy") -> 09-2024 | L155: FY24-25
A156: 4935 | B156: Satish Kumar K P | C156: 1938 | D156: Sandeep Sharma | E156: Thanks Satish,\nFor Solving all critical issues and clearing all the pending work. | F156: Spot | G156: 45559 | H156: Technology | I156: South | J156: INR 0.0 | K156: =TEXT(G156,"mm-yyyy") -> 09-2024 | L156: FY24-25
A157: 7247 | B157: Pracheer Pranay | C157: 7687 | D157: Pratiksha Mainkar | E157: Pracheer was able to quickly turn around the logistics for an important review in Delhi. He managed multiple stakeholders and constraints to make the review a success. There were no gaps in the planning process and the execution was smooth with all things going as per plan. He had meagre four days to make this happen, well done Pracheer! Keep up the good work. | F157: Spot | G157: 45557 | H157: Human Resources | I157: Corporate | J157: INR 0.0 | K157: =TEXT(G157,"mm-yyyy") -> 09-2024 | L157: FY24-25
A158: 17 | B158: Kavita Rohan | C158: 3883 | D158: Pankaj Joshi | E158: I really appreciate your continuous efforts for implementation of CLM tools for Onboarding Channel Partners.\n\u00A0\nIn last 6 months, you have co-ordinated very well with all Regional MIS, Finance, Legal & CLM teams for timely implementation of CLM tools.\n\u00A0\nReally appreciate your commitment & dedication towards work! Keep up the good work! | F158: Spot | G158: 45554 | H158: Sales | I158: Corporate | J158: INR 0.0 | K158: =TEXT(G158,"mm-yyyy") -> 09-2024 | L158: FY24-25
A159: 6541 | B159: Akash Nag M B | C159: 5271 | D159: Rahul Bhalla | E159: Akash, you truly make a difference with your unlimited support. You're quick and on time help in terms of providing the reports and required data for different analysis has been fantastic. Your suggestions / ideas in order to improvise on reports also helps us in terms of watching the output / conversions with different perspectives. We appreciate all your efforts and your quick turn around on requirements. | F159: Spot | G159: 45547 | H159: Customer Operations | I159: South | J159: INR 0.0 | K159: =TEXT(G159,"mm-yyyy") -> 09-2024 | L159: FY24-25
A160: 7080 | B160: Alok Kumar | C160: 7460 | D160: Abhaya Kumar Mishra | E160: I appreciate your patience and support as I navigated through unfamiliar territories. \nThanks a lot for your support in TPL ISD planning. \nThanks, \nAbhay Mishra\n | F160: Spot | G160: 45547 | H160: IT | I160: South | J160: INR 0.0 | K160: =TEXT(G160,"mm-yyyy") -> 09-2024 | L160: FY24-25
A161: 5679 | B161: Bhavyashree SN | C161: 5378 | D161: Piyush Gupta | E161: Thanks for all your support, prompt response, speed , execution and collaboration....You always helps me out when i got stuck somewhere..\n | F161: Spot | G161: 45546 | H161: Customer Operations | I161: South | J161: INR 0.0 | K161: =TEXT(G161,"mm-yyyy") -> 09-2024 | L161: FY24-25
A162: 7609 | B162: Gaurav Batra | C162: 5378 | D162: Piyush Gupta | E162: Your positive attitude , Collaboration and dedication make all the difference, happy for your coordination and execution speed.\nThanks | F162: Spot | G162: 45546 | H162: Field Service Delivery | I162: North | J162: INR 0.0 | K162: =TEXT(G162,"mm-yyyy") -> 09-2024 | L162: FY24-25
A163: 5976 | B163: Rohit Jaggi | C163: 5378 | D163: Piyush Gupta | E163: Your positive attitude , Collaboration and dedication make all the difference, and for that, I am genuinely grateful. With this coordination we can achieve milestones in Sales & Service...Keep this coordination always on. Thanks | F163: Spot | G163: 45546 | H163: Field Service Delivery | I163: North | J163: INR 0.0 | K163: =TEXT(G163,"mm-yyyy") -> 09-2024 | L163: FY24-25
A164: 6516 | B164: Azam Naseem | C164: 5378 | D164: Piyush Gupta | E164: Your positive attitude , Collaboration and dedication make all the difference, and for that, I am genuinely grateful. With this coordination we can achieve milestones in Sales & Service...Keep this coordination always on. Thanks | F164: Spot | G164: 45546 | H164: Field Service Delivery | I164: North | J164: INR 0.0 | K164: =TEXT(G164,"mm-yyyy") -> 09-2024 | L164: FY24-25
A165: 5387 | B165: Ashutosh Kumar | C165: 4004 | D165: Velu C | E165: Thank you Ashutosh for your contributions New packs testing on Msales and the box price changes for UP and Bihar \nYour support has been crucial, appreciate all your efforts and Support and I\u2019m looking forward to our continued success together | F165: Spot | G165: 45546 | H165: Sales | I165: South | J165: INR 0.0 | K165: =TEXT(G165,"mm-yyyy") -> 09-2024 | L165: FY24-25
A166: 7470 | B166: Suraj Prakash | C166: 7254 | D166: Ratan Kumar Vishwakarma | E166: Suraj has done a commendable job of doing end-to-end testing of new CIP journey of Apple TV on Binge Plus platform. He was new for UAT environment testing but still took full ownership of UAT readiness and tested end to end subscription journey of Apple TV App on all Binge+ packs. He has played a pivotal role in pre-prod testing as well and during go live of new Apple TV CIP journey in production environment. He has exhibited anchor competencies like ownership and grow partnership which helped in meeting business timelines.\nKeep progressing and keep up the great work Suraj! | F166: Spot | G166: 45546 | H166: Technology | I166: North | J166: INR 0.0 | K166: =TEXT(G166,"mm-yyyy") -> 09-2024 | L166: FY24-25
... A208: 5714 | B208: Usha Rani K | C208: 7225 | D208: Divya Shenoy | E208: Usha went out of her way to help overcome the issues with regard to KBC live event on Sony Liv. The solution was discussed, tried and tested over two days before the event went Live. Usha worked odd hours ensure that the content is pulled in and made available for seamless subscriber experience. | F208: Spot | G208: 45526 | H208: Commercial | I208: South | J208: INR 0.0 | K208: =TEXT(G208,"mm-yyyy") -> 08-2024 | L208: FY24-25
A209: 6593 | B209: S Prakash . | C209: big.stage@tataplay.com | D209: Big Stage | E209: Pradeepkumar Velayudhan - Thanks Prakash for partnering with Ashish and for the support extended in creating a 4year story line on the overall financials and cost. This presentation outlined the specific actionable to be taken this year towards ensuring better EBITDA. The slides were self explanatory with details for each of the cost lines. Your expertise in creating an understanding of financial trend and requesting further data points to cross check the same was quite helpful. Well done! | F209: Spot of the Month | G209: 45526 | H209: Finance | I209: South | J209: INR 500.0 | K209: =TEXT(G209,"mm-yyyy") -> 08-2024 | L209: FY24-25
A210: 7243 | B210: Gaurav Yadav | C210: big.stage@tataplay.com | D210: Big Stage | E210: Pradeepkumar Velayudhan - Thanks Gaurav for partnering with Ashish and for the support extended in creating a 4year story line on the overall financials and cost and drawing insights into specific actionable to be taken this year towards ensuring better EBITDA. The slides were self explanatory with details for each of the cost lines .Well done. The pace with which you could plot the expectations on the presentation was quite appreciative. We could complete this activity due to your POWER BI skill along with deep understanding of financial trends. | F210: Spot of the Month | G210: 45526 | H210: Finance | I210: Corporate | J210: INR 500.0 | K210: =TEXT(G210,"mm-yyyy") -> 08-2024 | L210: FY24-25
A211: 7804 | B211: Ashish Vig | C211: big.stage@tataplay.com | D211: Big Stage | E211: Pradeepkumar Velayudhan - Thanks Ashish for creating a 4year story line on the overall financials and cost and drawing insights into specific actionable to be taken this year towards ensuring better EBITDA. The slides were self explanatory with details for each of the cost lines thereby reducing the effort involvedin explaining each comment / figs on the presentation. Well done. | F211: Spot of the Month | G211: 45526 | H211: Finance | I211: Corporate | J211: INR 500.0 | K211: =TEXT(G211,"mm-yyyy") -> 08-2024 | L211: FY24-25
A212: 4068 | B212: Nagesh Y Bhonsle | C212: big.stage@tataplay.com | D212: Big Stage | E212: Rochelle R Rajguru - Thank you Nagesh. During Elections, you helped in showcasing the banners to proper segments. You find out the areas of scope and work out on the misses. One late evening we also needed Bigg Boss (All languages) Creatives and promos urgently, without wasting any time you were upfront and shared the assets and supported us. I would like to thank you once again Nagesh for your continuous efforts. | F212: Spot of the Month | G212: 45526 | H212: Commercial | I212: South | J212: INR 500.0 | K212: =TEXT(G212,"mm-yyyy") -> 08-2024 | L212: FY24-25
A213: 6388 | B213: Akshaya Sahu | C213: big.stage@tataplay.com | D213: Big Stage | E213: Rochelle R Rajguru - I would like to thank and appreciate Akshaya for supporting us quickly in Partner Collaboration during Mother's Day. Within 3 days Akshaya managed to get the posts ready by the agency. Thank you once again Akshaya for overcoming all the roadblocks and making this happen. | F213: Spot of the Month | G213: 45526 | H213: Digital Marketing | I213: Corporate | J213: INR 500.0 | K213: =TEXT(G213,"mm-yyyy") -> 08-2024 | L213: FY24-25
A214: 7495 | B214: Manender Singh Negi | C214: big.stage@tataplay.com | D214: Big Stage | E214: Pradeep Kumar - Appreciating Manender for deployment of Nysa HD Formal build on Live platform as this is new MediaTek chipset 5711 & low-cost STB for us and faced lot of challenges to validate E2E functionality of Nysa STB. You focused on identifying the basic types of test requirement. As resulted, identified many critical bugs (approx. 80 blocker bugs) like satellite migration issue, loader voltage issues, SWDL issues etc. timely same have been fixed before launched the product in market. As we are Committed in bringing a Valuable and error free product to the Tata play portfolio. Good Manender keep it up.\\u00A0 | F214: Spot of the Month | G214: 45526 | H214: Technology | I214: North | J214: INR 500.0 | K214: =TEXT(G214,"mm-yyyy") -> 08-2024 | L214: FY24-25
A215: 4416 | B215: Vivek Kumar Shukla | C215: big.stage@tataplay.com | D215: Big Stage | E215: Vinod K.S. - HI Vivek we are so happy with you always, because you handled our Repair centers RF Signal network new set up installation /Other repair centers old\\u00A0RF Singal network maintenance both activity related challenges and assisted to us very effective way of collaborations and resolving the issue at hand was commendable. Without you, we couldn't complete or run our centers effectively Signal network on time. Our team is always grateful for your support. all the best and congratulation for great job. | F215: Spot of the Month | G215: 45526 | H215: Technology | I215: North | J215: INR 500.0 | K215: =TEXT(G215,"mm-yyyy") -> 08-2024 | L215: FY24-25
A216: 7816 | B216: Neha Veling | C216: big.stage@tataplay.com | D216: Big Stage | E216: Rochelle R Rajguru - I wish to extend my sincere appreciation to Neha for her remarkable efficiency in providing the Terms and Conditions (TnCs) on our website amidst the World Cup Binge contest on Hotstar. Despite her unwellness, she managed to ensure their completion within the designated timeframe. Within a mere half-hour, the TnCs were successfully displayed on our website, allowing us to proceed with the contest. Thank you, Neha, for your prompt response and dedication to this task. | F216: Spot of the Month | G216: 45526 | H216: Digital Marketing | I216: Corporate | J216: INR 500.0 | K216: =TEXT(G216,"mm-yyyy") -> 08-2024 | L216: FY24-25
A217: 7748 | B217: Pranshul Gupta | C217: big.stage@tataplay.com | D217: Big Stage | E217: Apurva Panwar - Pranshul has recently assumed the responsibility of driving Binge on TPMA. Wanted to take a moment to recognize and appreciate his efforts and commitment towards driving Binge via TPMA channel through various interventions like slotting for Binge assets on TPMA along with other LOBs, ensuring that there is a balance maintained with other teams, scheduling push and in app campaigns with full rigor. With all these efforts and dedication, we were able to achieve ever highest gross adds from TPMA on Binge in June'24. Wishing him all the very best for a great run on driving OTT via TPMA | F217: Spot of the Month | G217: 45526 | H217: Commercial | I217: Corporate | J217: INR 500.0 | K217: =TEXT(G217,"mm-yyyy") -> 08-2024 | L217: FY24-25
A218: 4013 | B218: Sheeja P.A. | C218: big.stage@tataplay.com | D218: Big Stage | E218: Rohit Mishra - As part of Project Profitability, a major initiative to improve profitability of customers being acquired, we were required to replace or close all LDP acquisition packs with payback > 7 years. Sheeja, along with Mayur, from GTM team led the configuration of the 23 new packs (with higher price) and closure of the older packs (with lower price), took complete ownership of the process and helped launch these products within a week of the request being raised. Thanks for your quick support, Sheeja! | F218: Spot of the Month | G218: 45526 | H218: Commercial | I218: South | J218: INR 500.0 | K218: =TEXT(G218,"mm-yyyy") -> 08-2024 | L218: FY24-25
A219: 7742 | B219: Kaustubh Pant | C219: big.stage@tataplay.com | D219: Big Stage | E219: Bharti Samant - We wanted to express sincere appreciation for Kaustubh's invaluable contribution for the successful launch of Tata Play Anime Local. \\nHis knowledge, dedication, hard work and quick TAT played a key role in successful launch of this new service.\\n | F219: Spot of the Month | G219: 45526 | H219: Digital Marketing | I219: Corporate | J219: INR 500.0 | K219: =TEXT(G219,"mm-yyyy") -> 08-2024 | L219: FY24-25
A220: 7394 | B220: Chandan Kumar Sharma | C220: big.stage@tataplay.com | D220: Big Stage | E220: Manoj Jadhav - Chandan is having very good knowledge regarding competition data. Always give speedy and accurate information regarding the competitor updates. Thanks for your support to trade Marketing team. | F220: Spot of the Month | G220: 45526 | H220: Sales | I220: West | J220: INR 500.0 | K220: =TEXT(G220,"mm-yyyy") -> 08-2024 | L220: FY24-25
... A242: 7197 | B242: Harsh Gaur | C242: big.stage@tataplay.com | D242: Big Stage | E242: Rohit Mishra - As part of a major packaging change activity, scheduled to go live on 1st Aug'24, subscriber marketing team configured 64 new LDP packs (acquisition, winback and renewal). Harsh is the SPOC from RA for checking if all the inputs (whether for pack itself, or of the broadcaster packs/channels being used in it) are correct. Harsh has been vigilant and collaborative to seek out clarifications on any discrepancy and has got some corrections made where required, before the packs move into IT configurations. Thank you for your support, Harsh! | F242: Spot of the Month | G242: 45526 | H242: Finance | I242: Corporate | J242: INR 500.0 | K242: =TEXT(G242,"mm-yyyy") -> 08-2024 | L242: FY24-25
A243: 6434 | B243: Srinivasan Thiagarajan | C243: 1760 | D243: Rajaneesh Chaubey | E243: Srini has done a wonderful job in closing the LRP conflict and get released the valuable material from there promptly. | F243: Spot of the Month | G243: 45526 | H243: Finance | I243: Corporate | J243: INR 500.0 | K243: =TEXT(G243,"mm-yyyy") -> 08-2024 | L243: FY24-25
A244: 7656 | B244: Sneha Mohan | C244: big.stage@tataplay.com | D244: Big Stage | E244: Pranshul Gupta - This SPOT is to recognize the incredible work done by Sneha during the recent eventful months for TPMA. Her exceptional speed of execution ensured we had the most content viewing engagement. Sneha drove significant content viewing engagement with timely and relevant notifications, actively participating in strategic decisions on what to promote. Her efficiency in managing asset consumption costs, especially by minimizing rework for GEC promotions, has been invaluable. Thank you, and let's keep this momentum going for even greater success ahead. \\uD83C\\uDF89 | F244: Spot of the Month | G244: 45526 | H244: Digital Marketing | I244: Corporate | J244: INR 500.0 | K244: =TEXT(G244,"mm-yyyy") -> 08-2024 | L244: FY24-25
A245: 2292 | B245: Bhagavaldas P.K. | C245: big.stage@tataplay.com | D245: Big Stage | E245: Vikas Soni - Hi Bhagaval Das, thanks for your extended efforts and ownership while driving the Making customer smile contest for the IB partners. You have coordinated with all partners end to end and ensured continuous improvement in our ranking, and also coverage% of the contest.\nWith your help, we were able to successfully close the contest at 3rd rank out of 50+ Tata group companies with 10K+ stories this year.\nOur next target is to have a winning story in the next contest duration; let's gear up for the same!\nAgain, appreciation all the hard work you have put in. Thank you. | F245: Spot of the Month | G245: 45526 | H245: Customer Operations | I245: South | J245: INR 500.0 | K245: =TEXT(G245,"mm-yyyy") -> 08-2024 | L245: FY24-25
A246: 1697 | B246: Shashikala K. | C246: big.stage@tataplay.com | D246: Big Stage | E246: Vikas Soni - Hi Shashi, thanks for your extended efforts and ownership while driving the Making customer smile contest for the IB partners. You have coordinated with all partners end to end and ensured continuous improvement in our ranking, and also coverage% of the contest.\nWith your help, we were able to successfully close the contest at 3rd rank out of 50+ Tata group companies with 10K+ stories this year.\nOur next target is to have a winning story in the next contest duration; let's gear up for the same!\nAgain, appreciation all the hard work you have put in. Thank you. | F246: Spot of the Month | G246: 45526 | H246: Customer Operations | I246: South | J246: INR 500.0 | K246: =TEXT(G246,"mm-yyyy") -> 08-2024 | L246: FY24-25
A247: 4366 | B247: Deepjyoti Mohapatro | C247: big.stage@tataplay.com | D247: Big Stage | E247: Vikas Soni - Hi Deepjyoti, thanks for your extended efforts and ownership while driving the Making customer smile contest for the IB partners. You have coordinated with all partners end to end and ensured continuous improvement in our ranking, and also coverage% of the contest. \nWith your help, we were able to successfully close the contest at 3rd rank out of 50+ Tata group companies with 10K+ stories this year.\nOur next target is to have a winning story in the next contest duration; let's gear up for the same!\nAgain, appreciation all the hard work you have put in. Thank you. | F247: Spot of the Month | G247: 45526 | H247: Customer Operations | I247: South | J247: INR 500.0 | K247: =TEXT(G247,"mm-yyyy") -> 08-2024 | L247: FY24-25
A248: 4935 | B248: Satish Kumar K P | C248: big.stage@tataplay.com | D248: Big Stage | E248: Vivek Kumar Shukla - My SSO id was locked. Satish reactivated it in 1 day. Thank you ! | F248: Spot of the Month | G248: 45526 | H248: Technology | I248: South | J248: INR 500.0 | K248: =TEXT(G248,"mm-yyyy") -> 08-2024 | L248: FY24-25
A249: 2826 | B249: Rabiya Sidiqa | C249: big.stage@tataplay.com | D249: Big Stage | E249: Bhuvaneshwaran S & Apurva Panwar-Rabiya has been instrumental in helping us leverage segmentation capabilities for TPMA. As a result, segmented CTR% on app has drastically improved. Almost all assets on app are segmented. She was instrumental in helping execute around 30 segments for APV launch. She helped us identify sharper segments for linear upselling which has contributed to pack add revenue increment.\nI am glad to take a moment and appreciate Rabiya's efforts in driving Binge via TPMA. In the month of May and June, around Prime launch we have done several experiments to drive Binge via TPMA channel. Many new segments were created across assets, and it meant a lot more complexity at ops and scheduling end. Rabiya's commitment towards her work and end to end ownership is commendable. We saw really good growth in Binge gross adds from TPMA in May and June and with all such efforts, rigor and experimentation, we did ever highest gross adds on Binge from TPMA channel in June'24. | F249: Spot of the Month | G249: 45526 | H249: Commercial | I249: South | J249: INR 500.0 | K249: =TEXT(G249,"mm-yyyy") -> 08-2024 | L249: FY24-25
A250: 4517 | B250: Md Ahmed | C250: big.stage@tataplay.com | D250: Big Stage | E250: Vikas Soni - Hi Ahmed, thanks for your extended efforts and ownership while driving the Making customer smile contest for the IB partners. You have coordinated with all partners end to end and ensured continuous improvement in our ranking, and also coverage% of the contest.\nWith your help, we were able to successfully close the contest at 3rd rank out of 50+ Tata group companies with 10K+ stories this year.\nOur next target is to have a winning story in the next contest duration; let's gear up for the same!\nAgain, appreciation all the hard work you have put in. Thank you. | F250: Spot of the Month | G250: 45526 | H250: Customer Operations | I250: South | J250: INR 500.0 | K250: =TEXT(G250,"mm-yyyy") -> 08-2024 | L250: FY24-25
A251: 7569 | B251: Manoj Jadhav | C251: big.stage@tataplay.com | D251: Big Stage | E251: Abhijeet Bandgar - Manoj, I Appreciate your Prompt Reply about every work requirement for us & also your Innovative creatives helps US for driving the business. \nThanks for Support | F251: Spot of the Month | G251: 45526 | H251: Sales | I251: West | J251: INR 500.0 | K251: =TEXT(G251,"mm-yyyy") -> 08-2024 | L251: FY24-25
A252: 7576 | B252: Radha Krishna Jha | C252: big.stage@tataplay.com | D252: Big Stage | E252: Chirag Gauba - Radha Krishna Jha has been always a great support. He always helped me in various trade marketing stuff throughout my time at Tata Play. | F252: Spot of the Month | G252: 45526 | H252: Sales | I252: North | J252: INR 500.0 | K252: =TEXT(G252,"mm-yyyy") -> 08-2024 | L252: FY24-25
...

Sheet Debutant of the Qtr
A1: Receiver Employee Id | B1: Receiver Name | C1: Nominator Employee Id | D1: Nominator Name | E1: Citation | F1: Quarter | G1: Reward Name | H1: Nomination Date | I1: Department | J1: Region
A2: 7742 | B2: Kaustubh Pant | C2: 7690 | D2: Sharath Nair | E2: Kaustubh quickly demonstrated his ability to deliver results in his first stint with the Subscriber Communications team .\nHe worked on AI solutions for communications, crafting hardworking regional comms, and contributing to the successful launch of Anime Local. His proactive approach and fast learning were an asset to the team, even before transitioning to social media.\nSince taking up the social media role, Kaustubh has demonstrated exceptional creativity & commitment to enhance the Tata Play social media presence and engagement. He has introduced engaging content formats which has not only increased engagement but also helped build community. | F2: Q2-FY25 | G2: Debutant | H2: 45572 | I2: Digital Marketing | J2: Corporate
A3: 7868 | B3: Karan Mehta | C3: 7224 | D3: Nishant Bangar | E3: In his first few months here, Karan has led the charge towards streamlining communications for Binge performance marketing, ensuring that we catch all the big releases of the week, on the weekend of release. His good collaboration with content, digital & agency teams has significantly reduced turnaround time for performance statics to just 1.5 days for creation, approval, adapts, and delivery. In September, Karan led the creation of the Crow film for Tata Play Binge - a new digital and Ch 100 value proposition campaign, using 3D animated characters as protagonists. | F3: Q2-FY25 | G3: Debutant | H3: 45572 | I3: Digital Marketing | J3: Corporate
A4: 7750 | B4: Thameema T M | C4: 7035 | D4: Anand Prakash | E4: In the very short timeframe Thameema has spent so far with the Technology group, she has got good understanding of the Binge ecosystem and started to manage multiple projects like Binge Large Screen platforms (Samsung, LG, Android SmartTV, Fire TV OS), Whitelabel In-house Recommendation Engine, Video QC/QOE, Metadata Enrichment etc. Keep up the good work, Thameema. | F4: Q2-FY25 | G4: Debutant | H4: 45569 | I4: Technology | J4: North
A5: 7748 | B5: Pranshul Gupta | C5: 7024 | D5: Abhishek Jindal | E5: Pranshul joined the Tata Play Mobile App Marketing team in Q2. In a short while he has added value to the business through his inputs as well as results generated out of the same!\nHe has been able to bring fresh ideas to the table and make them see the light of day through constant collaboration and execution.\nThis includes results across various different verticals within the debut quarter:\nBinge acquisitions through TPMA\nMissed Call productivity on TPMA\nContent viewing on TPMA through election results and regional targeting through news\nMultiple innovations across notifications on Tata Play Mobile App | F5: Q2-FY25 | G5: Debutant | H5: 45569 | I5: Commercial | J5: Corporate
A6: 7751 | B6: Dwitiya Chandekar | C6: 5517 | D6: Bindi Thakkar | E6: Dwitiya from day-1 of the joining started working towards the launch of Tata Play Anime Local. She demonstrated great ownership and was on top of things despite having no know-how of launching a product. She quickly grasped entire process, managed relevant stakeholders, resolved lot of issues by herself. It is commendable to put together a launch within few months of joining amid the chaos and tight timelines.\u00A0 | F6: Q2-FY25 | G6: Debutant | H6: 45569 | I6: Commercial | J6: Corporate
A7: 7739 | B7: Akshat Singh | C7: 4926 | D7: Hitesh Shetty | E7: Akshat has been an outstanding addition to our team. As a recent member, he has quickly proven himself to be a valuable asset. His contributions to the OTT Destination on TPMA have been particularly impressive.\nAkshat's enthusiasm and eagerness to learn have been evident from the start. He has demonstrated a strong grasp of the project's objectives and has consistently exceeded expectations. His ability to collaborate effectively with colleagues and his willingness to take on new challenges have been instrumental to his success.\n\nI am delighted to nominate Akshat for the Debutant of the Quarter award. His exceptional performance and positive attitude make him a deserving candidate.\n\n | F7: Q2-FY25 | G7: Debutant | H7: 45568 | I7: Commercial | J7: Corporate
A8: 7841 | B8: Kunal Soni | C8: 4735 | D8: Sandesh Patel | E8: Kunal\u00A0is quick learner, adaptive and team player. He learned the System / processes with the help of his peers quickly and took the independent charge of his area in the short span of time. He Understood the company focused drive and prioritized the initiatives like BMP / recharge along with all his other KPIS. He passionately started daily meetings with the CCOs and installers to understand their awareness and challenges. Accordingly, he motivated his team and executed daily drive with focused CCOS / Installers who are good in selling. He Incentives them and started celebrating it with winners on daily basis. He was awarded Nationally NO 1 ASM in MAY 24 \u2013 BMP ( 10.2% ) All India contest BMP contest in his category slab\u00A0and Also in RECHRAGE \u2013 Project wo he delivered 35% in the month of June 2023 which was highest in the central region. He Keep sharing his idea/ inputs with others too which gives him best results. He quickly adapted the situations and started delivering ! Kudos ! | F8: Q1-FY25 | G8: Debutant | H8: 45514 | I8: Field Service Delivery | J8: West
A9: 7747 | B9: Rishikesh Patil | C9: 7580 | D9: Resya Ramachandran | E9: Rishikesh joined the Content team after a year-long stint with Tata Play. Post joining us in Mar'24, he took over the entire carriage charter & ran collections, renewals with rigor. This Q1, was also the strongest first quarter collections as compared to the last 3 years for Tata Play. He also created an AOP of carriage, which helps us track all renewals & benchmarking & helps us deliver against the target. Rishikesh also quickly ramped up & overtook operations for Hotstar and has been solving for all operational roadblocks which have since reduced.\u00A0 | F9: Q1-FY25 | G9: Debutant | H9: 45513 | I9: Content | J9: Corporate
A10: 7834 | B10: Sujana V S Jogi | C10: 2477 | D10: Kishore Kumar B. | E10: Sujana V S Jogi has rapidly developed the skills and knowledge required to excel in their role. Their impressive adaptability, strong work ethic, and quick learning curve have made a significant impact on our team's success. Rapid Mastery of Game Testing, Box Builds and New services. Despite being new to the industry, Sujana quickly mastered the complexities of game testing. Successfully tested 2 new FST games and identified 2 critical blocker issues, contributing to the overall quality of the products. Demonstrated an impressive ability to testing 40+interative services as per the testing protocol on 7 different box builds of Synamedia and Irdeto. Took on the challenge of testing 2 interactive applications which are come up with new CR\u2019s in the same duration. Sujana V S Jogi ability to rapidly adapt and excel in a challenging environment is commendable. Their dedication and quick learning have not only benefited our projects but also set a strong example for others in the team. | F10: Q1-FY25 | G10: Debutant | H10: 45513 | I10: Commercial | J10: South
A11: 7737 | B11: Mansi Meena | C11: 7224 | D11: Nishant Bangar | E11: Mansi joined the Binge Subs-Comms team in April this year. In her first quarter with us she led one of the biggest partner launches for Binge - Amazon Prime. This entailed a multi-channel acquisition and engagement campaign on owned media - Ch 100, TPMA, Binge App, Emailers - and also paid channels - digital & Addressable ads with Star network. There were also two Binge roadblocks on Ch 100 in the month of May for this launch. \nMansi displayed great dedication and commitment and as she built the comms strategy that included 2 campaign films - Amazon Prime On Tata Play Binge and Binge 199 for 6 - and over 15 other promos in Hindi, Tamil, Telugu & Kannada to sell the proposition of content aggregation and OTT partner aggregation. This was supplemented with 100+ statics. She collaborated skillfully and tactfully with agencies, internal teams, and also Amazon team. | F11: Q1-FY25 | G11: Debutant | H11: 45513 | I11: Digital Marketing | J11: Corporate
A12: 7837 | B12: Aditya Shrivastava | C12: 1908 | D12: Rajesh R. Dayal | E12: Aditya has done exceptionally well in picking up test automation. The efforts he put in learning Witbe test automation is highly commendable. Aditya took ownership of the quality analysis and contributed in scripting couple of new test cases. He has collaborated well with the team to understand the requirement & challenges and deliveries within agreed timelines ensuring all STB performance KPIs validation and quality in reports. | F12: Q1-FY25 | G12: Debutant | H12: 45512 | I12: Technology | J12: North
A13: 7827 | B13: Vinodkumar Jakkala | C13: 4763 | D13: Govinda Sane | E13: Vinod has learned and took over the Ad operations & scheduling of 8 Channels. He has maintained error free implementation of internal and external campaigns on all Ch100s and floaters. He has also taken over inventory management and coordination of teleshopping campaigns. He is a team player, always ready to help, takes additional responsibility and put extra effort to accommodate last minute changes in the schedule to save the revenue. Keep up the momentum. | F13: Q1-FY25 | G13: Debutant | H13: 45511 | I13: B2B | J13: Corporate
... A32: 7996 | B32: Sanjay Dubey | C32: 7884 | D32: Krupa Shah | E32: Sanjay joined the data science team and within a short span has taken up multiple responsibilities across initiating Gen AI capabilities within the team, building Binge personas, developing VOC text analytics for Communications team. Sanjay is a good collaborator, team player and takes feedback very positively. I wish Sanjay the very best to help drive some key initiatives for the organization!<br/><br/>#Innovator | F32: Q1-FY26 | G32: Debutant | H32: 45835 | I32: Commercial | J32: Corporate

Sheet Job Well Done
A1: Receiver Employee Id | B1: Receiver Name | C1: Nominator Employee Id | D1: Nominator Name | E1: Citation | F1: Quarter | G1: Reward Name | H1: Nomination Date | I1: Department | J1: Region
A2: 6803 | B2: Arinjaya Khare | C2: 7955 | D2: Dinesh Patwari | E2: He is a valuable member of our team, for his exceptional contributions to package profitability and SAC. Arinjaya's dedication, expertise, and passion for excellence make him an invaluable asset to our team. His contributions have not only enhanced our analytics strength but also inspired colleagues to strive for similar excellence. a)Significant Impact on Profitability : Arinjaya’ s diligent efforts have resulted in change of business strategy to improve the package profitability, directly benefiting our organization's bottom line for future . b)Innovative Solutions: He has consistently demonstrated creative problem-solving skills, developing effective strategies to optimize the ROI. c)Collaboration and Teamwork: Arinjaya has worked harmoniously with cross-functional teams, ensuring seamless outcome of analysis , and driving collective success. | F2: Q2-FY25 | G2: Job Well Done | H2: 45583 | I2: Finance | J2: Corporate
A3: 798 | B3: Swaminathan Konar | C3: 2508 | D3: Pranav Deshpande | E3: (A) Several high stakes litigation came up during the quarter. Full Stay and ZERO pre-deposit was ensured in these matters. 1.TN GST matter of 45 crores – Got full stay 2.Service tax matter of 2016-17 – levy of ST on LF – 26 crores – Got full stay 3.UP matters for 6 years – 11/12 to 17/18 – 25.87 crores – got them quashed and remanded back 4.Rajasthan entry tax litigation – 25 crores – matter successfully remanded back after 10 year litigation 5.West Bengal Tribunal matter – 19.66 crores – got full stay 6.Maharashtra GST demands – 27 crore SCN reduced to 12 crores 7.Telangana GST demand of 3.26 crores – dropped (B) Handled the entertainment tax final hearing related issues very well, with multiple documentation, meetings with Counsel, attending in SC (C) With the amendment in GST, bringing into effect the Invoice Management System, he had the foresight to visualise adverse cash flow impact in monthly GST compliance and we changed the current sale model documentation with a new one, which would mitigate this issue. | F3: Q2-FY25 | G3: Job Well Done | H3: 45583 | I3: Finance | J3: Corporate
A4: 6737 | B4: Sushant Sawant | C4: 4329 | D4: Hemant Bhatkhande | E4: Sushant has contributed to all key focus areas of BE deliverables in an outstanding manner in the last quarter. He has been self-driven and motivated to achieve the following :- 1) Cadences for CD 6.0 that has led to 19/20 projects being completed, that addresses customer pain points 2) Execution of CD 7.0 from working with Cust Ops, to obtain the samples to its distribution to participants and synthesizing of the observation to arrive at 32 pain points to be worked upon in the second half of the year for customer pain point alleviation’ 3) For CD NPS 4.0 he has worked with the core teams to formulate NPS targets for 2024-25, drive cadences with Top Management (4 in total to date) that has led to 13 of the 23 actionable being completed 4) He has collaboratively worked with various project team members of CEO projects to provide traction for 18 projects being pursued 5) During the Cyber Excellence engagement, he was a core team member that facilitated the assessment. Over and above this he has worked in a focussed manner in enabling publication of the Promising Practices. All of this has contributed to the organisational objectives and therefore the nomination. | F4: Q2-FY25 | G4: Job Well Done | H4: 45583 | I4: Finance | J4: Corporate
A5: 7693 | B5: Vivekananda Mishra | C5: 5744 | D5: Rohan Mehra | E5: "Vivek had been able to maintain NPS scores of 92 plus in both Completed & cancelled NPS scores and had been able to perform at it\u2019s best with 13% conversion on project recharge in Qtr 2\u201924. And had been able to maintain good service deliveries even in hilly terrain \u201C\n\u00A0 | F5: Q2-FY25 | G5: Job Well Done | H5: 45573 | I5: Field Service Delivery | J5: North
A6: 7426 | B6: Pooja Sharma | C6: 7807 | D6: Zenaida Pereira | E6: Poojas strategic thinking and agility in conceptualising an endearing comm campaign for superhit serials helped evoke a sense of nostalgia and excitement for the return of TVs superhit serials.\nAn integrated campaign across TV & Digital mediums was meticulously planned with tailored messages.\u00A0The campaign resonated with our target audience, resulting in 44k gross adds with highest contribution from miss calls, 44% and TPMA,12%\u00A0 | F6: Q2-FY25 | G6: Job Well Done | H6: 45573 | I6: Digital Marketing | J6: Corporate
A7: 7162 | B7: Parth Shah | C7: 3469 | D7: Neelam Mane | E7: Parth has demonstrated exemplary efforts in bringing both internal(Product, tech) and external stakeholders to successfully launch of Hard bundle Apple CIP integration on Binge. His efforts in collaborating ensured timely execution, while his partner management skills adeptly navigated challenging situations. Parth effectively worked with customer-facing teams to swiftly resolve Apple-related user issues and collaborated with the sub-marketing and communications teams to drive adoption of Apple TV+ for both existing and new users. His initiatives led to a smoother user journey and significantly improved activation rates. Congratulations on your exceptional contribution. Well done. | F7: Q2-FY25 | G7: Job Well Done | H7: 45573 | I7: Content | J7: Corporate
A8: 7156 | B8: Vivek Kumar | C8: 7282 | D8: Amanjeet Singh Suri | E8: Vivek has done Superb Job in Dealer expansion in JAS month and appointed highest 394 New Dealers in circle & Stocking Dealers 109%, | F8: Q2-FY25 | G8: Job Well Done | H8: 45572 | I8: Sales | J8: North
A9: 7655 | B9: Gundeep Singh | C9: 5495 | D9: Shekh Aashif | E9: Maximum Number of Government Bulks Month on Month by Gundeep Singh in Central Delhi\n TSK & Activation Tgt over Achieved\n Quality maintained 100+ Tgt, M2, M7 Below 20%\n Stocking Achieved 100%, 6 out of 7 DSRs qualified for Bandhan Incentive\n Government Accounts in Last Quarter - CBI HQ- 31, Dak Bhawan - 60, Maharashtra Bhavan - 150, Ministry of Railway - 48 ,20 Done (28 pending for Installation) \n | F9: Q2-FY25 | G9: Job Well Done | H9: 45572 | I9: Sales | J9: North
A10: 5074 | B10: Ranjeet Chauhan | C10: 5495 | D10: Shekh Aashif | E10: Highest Numbers of Bulks in the Region by Ranjeet Chauhan\n New Ceisp Tgt Achechive\n No. of 5 + new ceisp Activation ever Highet in region\n 550 no. don through Bulk in this quarter\n \n | F10: Q2-FY25 | G10: Job Well Done | H10: 45572 | I10: Sales | J10: North
A11: 4370 | B11: Sandeep Singh | C11: 7619 | D11: Deepak Singh | E11: Sandeep, You Have done extremally great work in opening new dealer in most challenging areas (mountains) and in toughest of time (Seasonal Effect & extreme weather) . From Day one you have taken charge and deliver results which also help me in motivating other team members. \nYour dedication to our organization growth and expansion is truly commendable. | F11: Q2-FY25 | G11: Job Well Done | H11: 45572 | I11: Sales | J11: North
A12: 7551 | B12: Pushpendra Singh | C12: 3634 | D12: Prasanna Kumar Singh | E12: Pushpendra is working in a territory having only rural markets and all the three districts being handled by him are similar in nature. In spite of being present in rural territory, he matched sales volume of cities which have population manifolds higher. His contribution to overall circle volume is higher than even few DAS-2 ASMs. His effort in sustaining excellent output from territory is appreciated. He has also topped in the last quarter contest in region and that shows his involvement and ability to extract business. | F12: Q2-FY25 | G12: Job Well Done | H12: 45572 | I12: Sales | J12: North
A13: 7672 | B13: Ashish Sharma | C13: 6658 | D13: Sarabjit Rupaal | E13: Well-done Ashish, keep up the good work and continue to own & lead from the front.\nYou have very meticulously owned and executed multiple Partner Integrations for both AkashGo & Cignal at the same time. You have exhibited an outstanding technical expertise & grasp for all the partner tracks. You have always stayed one step ahead and very meticulously maintained an upper edge in driving the Integration to closure in a timely manner. This was very instrumental for Release and building Customer confidence. | F13: Q2-FY25 | G13: Job Well Done | H13: 45572 | I13: Technology | J13: North
... A158: 7799 | B158: Aparna Choraria | C158: 4135 | D158: Himavat Chaudhuri | E158: Aparna worked on project Aqua from the Contracts Team end. She was able to Deliver Results from her end by Collaborating with other stakeholders within the legal department and across other departments thereby Growing Partnerships to close out key deliverables to meet stringent timelines set by Tata Group. Aparna's ownership of tasks on hand was a great benefit to everyone in the team. | F158: Q1-FY26 | G158: Job Well Done | H158: 45833 | I158: Legal | J158: Corporate

Sheet Intrafunctional 
A1: Receiver Employee Id | B1: Receiver Name | C1: Nominator Employee Id | D1: Nominator Name | E1: Citation | F1: Quarter | G1: Reward Name | H1: Nomination Date | I1: Department | J1: Region | K1: Points
A2: 5342 | B2: Kanchan Kumari | C2: 6623 | D2: Amitanshu Shankar | E2: Sony RIO was a very complex and a unique project which involved various teams within commercial function. The project helped rationalise subscribers content and also impact monthly charges. It was a complex project which involved making changes packaging and meeting regulatory compliances within timelines. Post execution the task was to roll it back as well with speed and efficiency as business objectives were achieved. This team worked very closely and their collective efforts demonstrated successful collaboration, ownership, speed and innovation with a focus on not just business KPIs but also on customer experience | F2: Q2-FY 25 | G2: Intra Functional Team Award | H2: 45583 | I2: Content | J2: Corporate | K2: 555
A3: 7244 | B3: Pragya Shekhar | C3: 6623 | D3: Amitanshu Shankar | E3: Sony RIO was a very complex and a unique project which involved various teams within commercial function. The project helped rationalise subscribers content and also impact monthly charges. It was a complex project which involved making changes packaging and meeting regulatory compliances within timelines. Post execution the task was to roll it back as well with speed and efficiency as business objectives were achieved. This team worked very closely and their collective efforts demonstrated successful collaboration, ownership, speed and innovation with a focus on not just business KPIs but also on customer experience | F3: Q2-FY 25 | G3: Intra Functional Team Award | H3: 45583 | I3: Content | J3: Corporate | K3: 555
A4: 5252 | B4: Rohit Mishra | C4: 6623 | D4: Amitanshu Shankar | E4: Sony RIO was a very complex and a unique project which involved various teams within commercial function. The project helped rationalise subscribers content and also impact monthly charges. It was a complex project which involved making changes packaging and meeting regulatory compliances within timelines. Post execution the task was to roll it back as well with speed and efficiency as business objectives were achieved. This team worked very closely and their collective efforts demonstrated successful collaboration, ownership, speed and innovation with a focus on not just business KPIs but also on customer experience | F4: Q2-FY 25 | G4: Intra Functional Team Award | H4: 45583 | I4: Commercial | J4: Corporate | K4: 555
A5: 6586 | B5: Losang Yolmo | C5: 6623 | D5: Amitanshu Shankar | E5: Sony RIO was a very complex and a unique project which involved various teams within commercial function. The project helped rationalise subscribers content and also impact monthly charges. It was a complex project which involved making changes packaging and meeting regulatory compliances within timelines. Post execution the task was to roll it back as well with speed and efficiency as business objectives were achieved. This team worked very closely and their collective efforts demonstrated successful collaboration, ownership, speed and innovation with a focus on not just business KPIs but also on customer experience | F5: Q2-FY 25 | G5: Intra Functional Team Award | H5: 45583 | I5: Commercial | J5: Corporate | K5: 555
A6: 7024 | B6: Abhishek Jindal | C6: 6623 | D6: Amitanshu Shankar | E6: Sony RIO was a very complex and a unique project which involved various teams within commercial function. The project helped rationalise subscribers content and also impact monthly charges. It was a complex project which involved making changes packaging and meeting regulatory compliances within timelines. Post execution the task was to roll it back as well with speed and efficiency as business objectives were achieved. This team worked very closely and their collective efforts demonstrated successful collaboration, ownership, speed and innovation with a focus on not just business KPIs but also on customer experience | F6: Q2-FY 25 | G6: Intra Functional Team Award | H6: 45583 | I6: Commercial | J6: Corporate | K6: 555
A7: 7748 | B7: Pranshul Gupta | C7: 6623 | D7: Amitanshu Shankar | E7: Sony RIO was a very complex and a unique project which involved various teams within commercial function. The project helped rationalise subscribers content and also impact monthly charges. It was a complex project which involved making changes packaging and meeting regulatory compliances within timelines. Post execution the task was to roll it back as well with speed and efficiency as business objectives were achieved. This team worked very closely and their collective efforts demonstrated successful collaboration, ownership, speed and innovation with a focus on not just business KPIs but also on customer experience | F7: Q2-FY 25 | G7: Intra Functional Team Award | H7: 45583 | I7: Commercial | J7: Corporate | K7: 555
A8: 7517 | B8: Pradeep Tambade | C8: 6623 | D8: Amitanshu Shankar | E8: Sony RIO was a very complex and a unique project which involved various teams within commercial function. The project helped rationalise subscribers content and also impact monthly charges. It was a complex project which involved making changes packaging and meeting regulatory compliances within timelines. Post execution the task was to roll it back as well with speed and efficiency as business objectives were achieved. This team worked very closely and their collective efforts demonstrated successful collaboration, ownership, speed and innovation with a focus on not just business KPIs but also on customer experience | F8: Q2-FY 25 | G8: Intra Functional Team Award | H8: 45583 | I8: Commercial | J8: Corporate | K8: 555
A9: 7291 | B9: Kaniz Sayed | C9: 6623 | D9: Amitanshu Shankar | E9: Sony RIO was a very complex and a unique project which involved various teams within commercial function. The project helped rationalise subscribers content and also impact monthly charges. It was a complex project which involved making changes packaging and meeting regulatory compliances within timelines. Post execution the task was to roll it back as well with speed and efficiency as business objectives were achieved. This team worked very closely and their collective efforts demonstrated successful collaboration, ownership, speed and innovation with a focus on not just business KPIs but also on customer experience | F9: Q2-FY 25 | G9: Intra Functional Team Award | H9: 45583 | I9: Commercial | J9: Corporate | K9: 555
A10: 5325 | B10: Amit Maurya | C10: 6623 | D10: Amitanshu Shankar | E10: Sony RIO was a very complex and a unique project which involved various teams within commercial function. The project helped rationalise subscribers content and also impact monthly charges. It was a complex project which involved making changes packaging and meeting regulatory compliances within timelines. Post execution the task was to roll it back as well with speed and efficiency as business objectives were achieved. This team worked very closely and their collective efforts demonstrated successful collaboration, ownership, speed and innovation with a focus on not just business KPIs but also on customer experience | F10: Q2-FY 25 | G10: Intra Functional Team Award | H10: 45583 | I10: Commercial | J10: Corporate | K10: 555
A11: 885 | B11: Anitha Joy | C11: 6623 | D11: Amitanshu Shankar | E11: Sony RIO was a very complex and a unique project which involved various teams within commercial function. The project helped rationalise subscribers content and also impact monthly charges. It was a complex project which involved making changes packaging and meeting regulatory compliances within timelines. Post execution the task was to roll it back as well with speed and efficiency as business objectives were achieved. This team worked very closely and their collective efforts demonstrated successful collaboration, ownership, speed and innovation with a focus on not just business KPIs but also on customer experience | F11: Q2-FY 25 | G11: Intra Functional Team Award | H11: 45583 | I11: Commercial | J11: South | K11: 555
A12: 4013 | B12: Sheeja P.A. | C12: 6623 | D12: Amitanshu Shankar | E12: Sony RIO was a very complex and a unique project which involved various teams within commercial function. The project helped rationalise subscribers content and also impact monthly charges. It was a complex project which involved making changes packaging and meeting regulatory compliances within timelines. Post execution the task was to roll it back as well with speed and efficiency as business objectives were achieved. This team worked very closely and their collective efforts demonstrated successful collaboration, ownership, speed and innovation with a focus on not just business KPIs but also on customer experience | F12: Q2-FY 25 | G12: Intra Functional Team Award | H12: 45583 | I12: Commercial | J12: South | K12: 555
A13: 5201 | B13: Mohan A | C13: 6623 | D13: Amitanshu Shankar | E13: Sony RIO was a very complex and a unique project which involved various teams within commercial function. The project helped rationalise subscribers content and also impact monthly charges. It was a complex project which involved making changes packaging and meeting regulatory compliances within timelines. Post execution the task was to roll it back as well with speed and efficiency as business objectives were achieved. This team worked very closely and their collective efforts demonstrated successful collaboration, ownership, speed and innovation with a focus on not just business KPIs but also on customer experience | F13: Q2-FY 25 | G13: Intra Functional Team Award | H13: 45583 | I13: Commercial | J13: South | K13: 555
... A191: 7836 | B191: Purshottam Bairagi | C191: 3472 | D191: A. Manjunath | E191: RO Antennas old Feed system replacement with Krato’s feed got Carried out by In-house team members: Required to replace old Feed system of RO-Antennas and need to install new feed along with New LNB changeover system with Acrylic Protection Assembly for entire feed system, Tech Services team members taken ownership for this critical installations and completed the same on required Antennas.<br/><br/>Installation and Replacement Rack power MDU’s EATON STS-16 units with EATON-ATS-16, To prevent equipment power failures in Compression system AVP racks old EATON STS-16 units which are having switching issues required to be replaced with New EATON ATS units, Tech Services team taken ownership and worked responsibly during Scheduled Activity timings and completed the critical MDU units replacement activity successfully. | F191: Q3 FY25 | G191: Intra Functional Team Award | H191: 45649 | I191: Technology | J191: North | K191: 2000
A192: 5428 | B192: Rochelle R Rajguru | C192: 6623 | D192: Amitanshu Shankar | E192: At the beginning of FY25 we set ourselves a BIG HAIRY GOAL, to achieve 1 Million Services Gross Adds from TPMA. In FY 24 we grew by about 50%+ and team had aspired to get about 50% growth this year as well, that too with a lower base. Happy & proud to share that teams across functions took this as a challenge and got down to what we do best - collaborate, innovate & execute. The goal was achieved well in advance with 10 days to spare and Q4 averaging almost 1 Lakh per month, through a combination of relentless experimentation and planning. What is even more heartening is that by the end of the year, Tata Play Mobile App started to emerge as one of the largest channels for Tata Play Services and helping the shift towards digital journey. | F192: Q4-FY 25 | G192: Intra Functional Team Award | H192: 45756 | I192: Content | J192: Corporate | K192: =10000/23 -> 434.78261
A193: 7969 | B193: Aarushi Baghel | C193: 6623 | D193: Amitanshu Shankar | E193: At the beginning of FY25 we set ourselves a BIG HAIRY GOAL, to achieve 1 Million Services Gross Adds from TPMA. In FY 24 we grew by about 50%+ and team had aspired to get about 50% growth this year as well, that too with a lower base. Happy & proud to share that teams across functions took this as a challenge and got down to what we do best - collaborate, innovate & execute. The goal was achieved well in advance with 10 days to spare and Q4 averaging almost 1 Lakh per month, through a combination of relentless experimentation and planning. What is even more heartening is that by the end of the year, Tata Play Mobile App started to emerge as one of the largest channels for Tata Play Services and helping the shift towards digital journey. | F193: Q4-FY 25 | G193: Intra Functional Team Award | H193: 45756 | I193: Commercial | J193: Corporate | K193: =10000/23 -> 434.78261
A194: 7751 | B194: Dwitiya Chandekar | C194: 6623 | D194: Amitanshu Shankar | E194: At the beginning of FY25 we set ourselves a BIG HAIRY GOAL, to achieve 1 Million Services Gross Adds from TPMA. In FY 24 we grew by about 50%+ and team had aspired to get about 50% growth this year as well, that too with a lower base. Happy & proud to share that teams across functions took this as a challenge and got down to what we do best - collaborate, innovate & execute. The goal was achieved well in advance with 10 days to spare and Q4 averaging almost 1 Lakh per month, through a combination of relentless experimentation and planning. What is even more heartening is that by the end of the year, Tata Play Mobile App started to emerge as one of the largest channels for Tata Play Services and helping the shift towards digital journey. | F194: Q4-FY 25 | G194: Intra Functional Team Award | H194: 45756 | I194: Commercial | J194: Corporate | K194: =10000/23 -> 434.78261
A195: 7250 | B195: Prachodaya Das | C195: 6623 | D195: Amitanshu Shankar | E195: At the beginning of FY25 we set ourselves a BIG HAIRY GOAL, to achieve 1 Million Services Gross Adds from TPMA. In FY 24 we grew by about 50%+ and team had aspired to get about 50% growth this year as well, that too with a lower base. Happy & proud to share that teams across functions took this as a challenge and got down to what we do best - collaborate, innovate & execute. The goal was achieved well in advance with 10 days to spare and Q4 averaging almost 1 Lakh per month, through a combination of relentless experimentation and planning. What is even more heartening is that by the end of the year, Tata Play Mobile App started to emerge as one of the largest channels for Tata Play Services and helping the shift towards digital journey. | F195: Q4-FY 25 | G195: Intra Functional Team Award | H195: 45756 | I195: Commercial | J195: Corporate | K195: =10000/23 -> 434.78261
A196: 3447 | B196: Narayanan P. | C196: 6623 | D196: Amitanshu Shankar | E196: At the beginning of FY25 we set ourselves a BIG HAIRY GOAL, to achieve 1 Million Services Gross Adds from TPMA. In FY 24 we grew by about 50%+ and team had aspired to get about 50% growth this year as well, that too with a lower base. Happy & proud to share that teams across functions took this as a challenge and got down to what we do best - collaborate, innovate & execute. The goal was achieved well in advance with 10 days to spare and Q4 averaging almost 1 Lakh per month, through a combination of relentless experimentation and planning. What is even more heartening is that by the end of the year, Tata Play Mobile App started to emerge as one of the largest channels for Tata Play Services and helping the shift towards digital journey. | F196: Q4-FY 25 | G196: Intra Functional Team Award | H196: 45756 | I196: Commercial | J196: South | K196: =10000/23 -> 434.78261
A197: 7584 | B197: Ankita Pawar | C197: 6623 | D197: Amitanshu Shankar | E197: At the beginning of FY25 we set ourselves a BIG HAIRY GOAL, to achieve 1 Million Services Gross Adds from TPMA. In FY 24 we grew by about 50%+ and team had aspired to get about 50% growth this year as well, that too with a lower base. Happy & proud to share that teams across functions took this as a challenge and got down to what we do best - collaborate, innovate & execute. The goal was achieved well in advance with 10 days to spare and Q4 averaging almost 1 Lakh per month, through a combination of relentless experimentation and planning. What is even more heartening is that by the end of the year, Tata Play Mobile App started to emerge as one of the largest channels for Tata Play Services and helping the shift towards digital journey. | F197: Q4-FY 25 | G197: Intra Functional Team Award | H197: 45756 | I197: Commercial | J197: Corporate | K197: =10000/23 -> 434.78261
A198: 4013 | B198: Sheeja P.A. | C198: 6623 | D198: Amitanshu Shankar | E198: At the beginning of FY25 we set ourselves a BIG HAIRY GOAL, to achieve 1 Million Services Gross Adds from TPMA. In FY 24 we grew by about 50%+ and team had aspired to get about 50% growth this year as well, that too with a lower base. Happy & proud to share that teams across functions took this as a challenge and got down to what we do best - collaborate, innovate & execute. The goal was achieved well in advance with 10 days to spare and Q4 averaging almost 1 Lakh per month, through a combination of relentless experimentation and planning. What is even more heartening is that by the end of the year, Tata Play Mobile App started to emerge as one of the largest channels for Tata Play Services and helping the shift towards digital journey. | F198: Q4-FY 25 | G198: Intra Functional Team Award | H198: 45756 | I198: Commercial | J198: South | K198: =10000/23 -> 434.78261
A199: 6808 | B199: Gurpreet Kaur | C199: 6623 | D199: Amitanshu Shankar | E199: At the beginning of FY25 we set ourselves a BIG HAIRY GOAL, to achieve 1 Million Services Gross Adds from TPMA. In FY 24 we grew by about 50%+ and team had aspired to get about 50% growth this year as well, that too with a lower base. Happy & proud to share that teams across functions took this as a challenge and got down to what we do best - collaborate, innovate & execute. The goal was achieved well in advance with 10 days to spare and Q4 averaging almost 1 Lakh per month, through a combination of relentless experimentation and planning. What is even more heartening is that by the end of the year, Tata Play Mobile App started to emerge as one of the largest channels for Tata Play Services and helping the shift towards digital journey. | F199: Q4-FY 25 | G199: Intra Functional Team Award | H199: 45756 | I199: Commercial | J199: Corporate | K199: =10000/23 -> 434.78261
A200: 7398 | B200: Abhinav Aggarwal | C200: 6623 | D200: Amitanshu Shankar | E200: At the beginning of FY25 we set ourselves a BIG HAIRY GOAL, to achieve 1 Million Services Gross Adds from TPMA. In FY 24 we grew by about 50%+ and team had aspired to get about 50% growth this year as well, that too with a lower base. Happy & proud to share that teams across functions took this as a challenge and got down to what we do best - collaborate, innovate & execute. The goal was achieved well in advance with 10 days to spare and Q4 averaging almost 1 Lakh per month, through a combination of relentless experimentation and planning. What is even more heartening is that by the end of the year, Tata Play Mobile App started to emerge as one of the largest channels for Tata Play Services and helping the shift towards digital journey. | F200: Q4-FY 25 | G200: Intra Functional Team Award | H200: 45756 | I200: Commercial | J200: Corporate | K200: =10000/23 -> 434.78261
A201: 7567 | B201: Harsh Gill | C201: 6623 | D201: Amitanshu Shankar | E201: At the beginning of FY25 we set ourselves a BIG HAIRY GOAL, to achieve 1 Million Services Gross Adds from TPMA. In FY 24 we grew by about 50%+ and team had aspired to get about 50% growth this year as well, that too with a lower base. Happy & proud to share that teams across functions took this as a challenge and got down to what we do best - collaborate, innovate & execute. The goal was achieved well in advance with 10 days to spare and Q4 averaging almost 1 Lakh per month, through a combination of relentless experimentation and planning. What is even more heartening is that by the end of the year, Tata Play Mobile App started to emerge as one of the largest channels for Tata Play Services and helping the shift towards digital journey. | F201: Q4-FY 25 | G201: Intra Functional Team Award | H201: 45756 | I201: Commercial | J201: Corporate | K201: =10000/23 -> 434.78261
A202: 7807 | B202: Zenaida Pereira | C202: 6623 | D202: Amitanshu Shankar | E202: At the beginning of FY25 we set ourselves a BIG HAIRY GOAL, to achieve 1 Million Services Gross Adds from TPMA. In FY 24 we grew by about 50%+ and team had aspired to get about 50% growth this year as well, that too with a lower base. Happy & proud to share that teams across functions took this as a challenge and got down to what we do best - collaborate, innovate & execute. The goal was achieved well in advance with 10 days to spare and Q4 averaging almost 1 Lakh per month, through a combination of relentless experimentation and planning. What is even more heartening is that by the end of the year, Tata Play Mobile App started to emerge as one of the largest channels for Tata Play Services and helping the shift towards digital journey. | F202: Q4-FY 25 | G202: Intra Functional Team Award | H202: 45756 | I202: Digital Marketing | J202: Corporate | K202: =10000/23 -> 434.78261
A203: 7943 | B203: Manjiri Mazgaonkar | C203: 6623 | D203: Amitanshu Shankar | E203: At the beginning of FY25 we set ourselves a BIG HAIRY GOAL, to achieve 1 Million Services Gross Adds from TPMA. In FY 24 we grew by about 50%+ and team had aspired to get about 50% growth this year as well, that too with a lower base. Happy & proud to share that teams across functions took this as a challenge and got down to what we do best - collaborate, innovate & execute. The goal was achieved well in advance with 10 days to spare and Q4 averaging almost 1 Lakh per month, through a combination of relentless experimentation and planning. What is even more heartening is that by the end of the year, Tata Play Mobile App started to emerge as one of the largest channels for Tata Play Services and helping the shift towards digital journey. | F203: Q4-FY 25 | G203: Intra Functional Team Award | H203: 45756 | I203: Commercial | J203: Corporate | K203: =10000/23 -> 434.78261
... A214: 2826 | B214: Rabiya Sidiqa | C214: 6623 | D214: Amitanshu Shankar | E214: At the beginning of FY25 we set ourselves a BIG HAIRY GOAL, to achieve 1 Million Services Gross Adds from TPMA. In FY 24 we grew by about 50%+ and team had aspired to get about 50% growth this year as well, that too with a lower base. Happy & proud to share that teams across functions took this as a challenge and got down to what we do best - collaborate, innovate & execute. The goal was achieved well in advance with 10 days to spare and Q4 averaging almost 1 Lakh per month, through a combination of relentless experimentation and planning. What is even more heartening is that by the end of the year, Tata Play Mobile App started to emerge as one of the largest channels for Tata Play Services and helping the shift towards digital journey. | F214: Q4-FY 25 | G214: Intra Functional Team Award | H214: 45756 | I214: Commercial | J214: South | K214: =10000/23 -> 434.78261
A215: 4010 | B215: Abhishek K R | C215: 5780 | D215: Yashasvi Gupta | E215: Binge engagement has been an awesome story in FY 25 - with monthly active viewers on the paid binge base moving from 34% at the beginning of the year to almost 60% by year exit. Engagement on Binge app is extremely critical - as it helps on base retention - thereby leading to higher revenues. All teams came together to drive engagement up - right from envisaging, creating and executing the right campaigns to title / content marketing to programming to product functionalities to scheduling to creating the right communication - the various team members worked hand in hand with a single agenda - driving the engagement numbers up. Collaboration across various teams was key to drive this in the right direction. Kudos to all the team members and wish you all good luck to drive this up even higher going forward! | F215: Q4-FY 25 | G215: Intra Functional Team Award | H215: 45755 | I215: Commercial | J215: South | K215: 625
A216: 6822 | B216: Kapil Laddha | C216: 5780 | D216: Yashasvi Gupta | E216: Binge engagement has been an awesome story in FY 25 - with monthly active viewers on the paid binge base moving from 34% at the beginning of the year to almost 60% by year exit. Engagement on Binge app is extremely critical - as it helps on base retention - thereby leading to higher revenues. All teams came together to drive engagement up - right from envisaging, creating and executing the right campaigns to title / content marketing to programming to product functionalities to scheduling to creating the right communication - the various team members worked hand in hand with a single agenda - driving the engagement numbers up. Collaboration across various teams was key to drive this in the right direction. Kudos to all the team members and wish you all good luck to drive this up even higher going forward! | F216: Q4-FY 25 | G216: Intra Functional Team Award | H216: 45755 | I216: Content | J216: Corporate | K216: 625
A217: 7640 | B217: Cheril Mehta | C217: 5780 | D217: Yashasvi Gupta | E217: Binge engagement has been an awesome story in FY 25 - with monthly active viewers on the paid binge base moving from 34% at the beginning of the year to almost 60% by year exit. Engagement on Binge app is extremely critical - as it helps on base retention - thereby leading to higher revenues. All teams came together to drive engagement up - right from envisaging, creating and executing the right campaigns to title / content marketing to programming to product functionalities to scheduling to creating the right communication - the various team members worked hand in hand with a single agenda - driving the engagement numbers up. Collaboration across various teams was key to drive this in the right direction. Kudos to all the team members and wish you all good luck to drive this up even higher going forward! | F217: Q4-FY 25 | G217: Intra Functional Team Award | H217: 45755 | I217: Commercial | J217: Corporate | K217: 625
A218: 7431 | B218: Rohan Swarnkar | C218: 5780 | D218: Yashasvi Gupta | E218: Binge engagement has been an awesome story in FY 25 - with monthly active viewers on the paid binge base moving from 34% at the beginning of the year to almost 60% by year exit. Engagement on Binge app is extremely critical - as it helps on base retention - thereby leading to higher revenues. All teams came together to drive engagement up - right from envisaging, creating and executing the right campaigns to title / content marketing to programming to product functionalities to scheduling to creating the right communication - the various team members worked hand in hand with a single agenda - driving the engagement numbers up. Collaboration across various teams was key to drive this in the right direction. Kudos to all the team members and wish you all good luck to drive this up even higher going forward! | F218: Q4-FY 25 | G218: Intra Functional Team Award | H218: 45755 | I218: Commercial | J218: South | K218: 625
A219: 7083 | B219: Pratik Wadkar | C219: 5780 | D219: Yashasvi Gupta | E219: Binge engagement has been an awesome story in FY 25 - with monthly active viewers on the paid binge base moving from 34% at the beginning of the year to almost 60% by year exit. Engagement on Binge app is extremely critical - as it helps on base retention - thereby leading to higher revenues. All teams came together to drive engagement up - right from envisaging, creating and executing the right campaigns to title / content marketing to programming to product functionalities to scheduling to creating the right communication - the various team members worked hand in hand with a single agenda - driving the engagement numbers up. Collaboration across various teams was key to drive this in the right direction. Kudos to all the team members and wish you all good luck to drive this up even higher going forward! | F219: Q4-FY 25 | G219: Intra Functional Team Award | H219: 45755 | I219: Commercial | J219: Corporate | K219: 625
A220: 6368 | B220: Anirudh Vishal Yadav | C220: 5780 | D220: Yashasvi Gupta | E220: Binge engagement has been an awesome story in FY 25 - with monthly active viewers on the paid binge base moving from 34% at the beginning of the year to almost 60% by year exit. Engagement on Binge app is extremely critical - as it helps on base retention - thereby leading to higher revenues. All teams came together to drive engagement up - right from envisaging, creating and executing the right campaigns to title / content marketing to programming to product functionalities to scheduling to creating the right communication - the various team members worked hand in hand with a single agenda - driving the engagement numbers up. Collaboration across various teams was key to drive this in the right direction. Kudos to all the team members and wish you all good luck to drive this up even higher going forward! | F220: Q4-FY 25 | G220: Intra Functional Team Award | H220: 45755 | I220: Commercial | J220: South | K220: 625
A221: 6975 | B221: Meghna Tiwari | C221: 5780 | D221: Yashasvi Gupta | E221: Binge engagement has been an awesome story in FY 25 - with monthly active viewers on the paid binge base moving from 34% at the beginning of the year to almost 60% by year exit. Engagement on Binge app is extremely critical - as it helps on base retention - thereby leading to higher revenues. All teams came together to drive engagement up - right from envisaging, creating and executing the right campaigns to title / content marketing to programming to product functionalities to scheduling to creating the right communication - the various team members worked hand in hand with a single agenda - driving the engagement numbers up. Collaboration across various teams was key to drive this in the right direction. Kudos to all the team members and wish you all good luck to drive this up even higher going forward! | F221: Q4-FY 25 | G221: Intra Functional Team Award | H221: 45755 | I221: Content | J221: Corporate | K221: 625
A222: 7452 | B222: Ajay Pathak | C222: 5780 | D222: Yashasvi Gupta | E222: Binge engagement has been an awesome story in FY 25 - with monthly active viewers on the paid binge base moving from 34% at the beginning of the year to almost 60% by year exit. Engagement on Binge app is extremely critical - as it helps on base retention - thereby leading to higher revenues. All teams came together to drive engagement up - right from envisaging, creating and executing the right campaigns to title / content marketing to programming to product functionalities to scheduling to creating the right communication - the various team members worked hand in hand with a single agenda - driving the engagement numbers up. Collaboration across various teams was key to drive this in the right direction. Kudos to all the team members and wish you all good luck to drive this up even higher going forward! | F222: Q4-FY 25 | G222: Intra Functional Team Award | H222: 45755 | I222: Content | J222: Corporate | K222: 625
A223: 7823 | B223: Sehar Qureshi | C223: 5780 | D223: Yashasvi Gupta | E223: Binge engagement has been an awesome story in FY 25 - with monthly active viewers on the paid binge base moving from 34% at the beginning of the year to almost 60% by year exit. Engagement on Binge app is extremely critical - as it helps on base retention - thereby leading to higher revenues. All teams came together to drive engagement up - right from envisaging, creating and executing the right campaigns to title / content marketing to programming to product functionalities to scheduling to creating the right communication - the various team members worked hand in hand with a single agenda - driving the engagement numbers up. Collaboration across various teams was key to drive this in the right direction. Kudos to all the team members and wish you all good luck to drive this up even higher going forward! | F223: Q4-FY 25 | G223: Intra Functional Team Award | H223: 45755 | I223: Digital Marketing | J223: Corporate | K223: 625
A224: 5714 | B224: Usha Rani K | C224: 5780 | D224: Yashasvi Gupta | E224: Binge engagement has been an awesome story in FY 25 - with monthly active viewers on the paid binge base moving from 34% at the beginning of the year to almost 60% by year exit. Engagement on Binge app is extremely critical - as it helps on base retention - thereby leading to higher revenues. All teams came together to drive engagement up - right from envisaging, creating and executing the right campaigns to title / content marketing to programming to product functionalities to scheduling to creating the right communication - the various team members worked hand in hand with a single agenda - driving the engagement numbers up. Collaboration across various teams was key to drive this in the right direction. Kudos to all the team members and wish you all good luck to drive this up even higher going forward! | F224: Q4-FY 25 | G224: Intra Functional Team Award | H224: 45755 | I224: Commercial | J224: South | K224: 625
A225: 7658 | B225: Kaushal Kumar Jha | C225: 5780 | D225: Yashasvi Gupta | E225: Binge engagement has been an awesome story in FY 25 - with monthly active viewers on the paid binge base moving from 34% at the beginning of the year to almost 60% by year exit. Engagement on Binge app is extremely critical - as it helps on base retention - thereby leading to higher revenues. All teams came together to drive engagement up - right from envisaging, creating and executing the right campaigns to title / content marketing to programming to product functionalities to scheduling to creating the right communication - the various team members worked hand in hand with a single agenda - driving the engagement numbers up. Collaboration across various teams was key to drive this in the right direction. Kudos to all the team members and wish you all good luck to drive this up even higher going forward! | F225: Q4-FY 25 | G225: Intra Functional Team Award | H225: 45755 | I225: Commercial | J225: South | K225: 625
A226: 7809 | B226: Nupur Patel | C226: 5780 | D226: Yashasvi Gupta | E226: Binge engagement has been an awesome story in FY 25 - with monthly active viewers on the paid binge base moving from 34% at the beginning of the year to almost 60% by year exit. Engagement on Binge app is extremely critical - as it helps on base retention - thereby leading to higher revenues. All teams came together to drive engagement up - right from envisaging, creating and executing the right campaigns to title / content marketing to programming to product functionalities to scheduling to creating the right communication - the various team members worked hand in hand with a single agenda - driving the engagement numbers up. Collaboration across various teams was key to drive this in the right direction. Kudos to all the team members and wish you all good luck to drive this up even higher going forward! | F226: Q4-FY 25 | G226: Intra Functional Team Award | H226: 45755 | I226: Digital Marketing | J226: Corporate | K226: 625
... A247: 2736 | B247: Esther J. | C247: 7227 | D247: Vinodkumar Anandan | E247: I am delighted to present the Intra Function Award to the outstanding team (Lenin, Akash, Surya, Prasath and Esther) behind the Automation of Outbound Reports in the Tableau Digital Dashboard (13 Digital Dashboard Launches). Your collaborative efforts, technical ingenuity, and unwavering commitment have redefined how we drive data visibility and efficiency. Through your automation initiative, what was once a time-intensive reporting process has now become a streamlined, intelligent workflow—empowering stakeholders with trend insights, enhanced accuracy, and significantly improved turnaround times. The results are smarter decisions, faster actions, and a dashboard that speaks the language of innovation. Your achievement stands as a brilliant example of Intra-functional teamwork, problem-solving excellence, and a shared drive to push boundaries. Congratulations to each one of you for setting high standards and wishing you All the best for future endeavors in report Automation. | F247: Q1-FY26 | G247: Intra Functional Team Award | H247: 45856 | I247: Customer Operations | J247: South | K247: 2000

Sheet People Champion
A1: Receiver Employee Id | B1: Receiver Name | C1: Nominator Employee Id | D1: Nominator Name | E1: Citation | F1: Quarter | G1: Reward Name | H1: Nomination Date | I1: Department | J1: Region | K1: Points
A2: 4379 | B2: Inderpreet Singh | C2: 5803 | D2: SAYANTANI GUPTA | E2: Inder is known for being a customer champion. He has always been known for understanding the business KPI's from the customer lens by understanding data trends and voice of the customer. As a leader and leading the Retention team, he has instilled the same in his team. Every team member has been mentored and trained to analyse business trends in the daily data and present their understanding. This is coupled with regular connect with the customers through regular VOC's, home visit and discussions with customer facing teams like sales, FS and CO. Inder has ensured that this mantra of being abreast of daily data trends and VOC is imbibed and exhibited by all his team members. | F2: Q3 FY 25 | G2: People Champion | H2: 45652 | I2: Commercial | J2: Corporate | K2: 0
A3: 5517 | B3: Bindi Thakkar | C3: 454 | D3: Vinati Malik | E3: Bindi has taken over the New Product Development for Services team approximately a year and a half back and has proven herself to be a capable and motivating manager. She saw some early exits from the team but managed to consolidate, regroup and motivate her team to continue to innovate, drive and deliver albeit with a smaller team. Along the way she realised that there were some team members who had aspirations to acquire cross-functional experience and she helped them achieve their aspirations, once again ensuring that this did not hamper the morale or productivity of the team. She worked quickly and smartly to find replacements and hired well for a challenging multi-faceted product role and ensured that she was able to replace gaps in the team quickly. She is a confidant for her team and yet encourages them to lead visibly from the front on their own projects. She is a mature manager and has built a strong team and an environment that has helped them to grow and kept them engaged | F3: Q3 FY 25 | G3: People Champion | H3: 45652 | I3: Commercial | J3: Corporate | K3: 0
A4: 2826 | B4: Rabiya Sidiqa | C4: 647 | D4: Vinitha Kompella | E4: Rabiya is a very high energy team leader and a good team player. She has made sure the team manages the daily operations independently by giving them the opportunity to build their confidence and understand the operations better. She helps the team organize and plan all operational activities and ensures diligent planning and co-ordination with all stakeholders. She finds a solve for any operational problem and steps in to provide the support. She has excellent rapport with cross-functional teams and proactively provides support to ensure business deliverables. Rabiya took on the addl. responsibility of Binge Ops and has worked with the team and other stakeholders scaling up both herself and the team to manage the high volume of publishing operations. Whether through providing mentorship, advocating equitable opportunities or creating an approachable environment Rabiya has supported both her team and the stakeholders. | F4: Q3 FY 25 | G4: People Champion | H4: 45652 | I4: Commercial | J4: South | K4: 0
A5: 6481 | B5: Paurav S Choubal | C5: 4496 | D5: Aditya Shah | E5: Paurav has led managed multiple complex projects - key one being Driving Digital NPS with stakeholders across functions and was able to bring them all together to drive the initiatives which resulted in the NPS score growth by almost 10 points. Beyond this he has also been working with his own team as well as cross functional teams in suggesting in house design interventions for business/ experience opportunities for both Binge and TPMA App and has truly been a People's Champion. | F5: Q3 FY 25 | G5: People Champion | H5: 45652 | I5: Digital Marketing | J5: Corporate | K5: 0
A6: 5780 | B6: Yashasvi Gupta | C6: 5803 | D6: SAYANTANI GUPTA | E6: FY25 has been a table shift year for Binge. We launched tick tick and Prime Video joined the Binge family. The focus on getting the number growth was high. Yash led this from the front. He has championed all the acquisition initiatives and along with it also got a lot of changes done on engagement and renewal. He instituted the drive for Binge base growth in his team which led to lot of proactive experiments being carried out and reports and analysis being shared. His team has been in the fore front of Fiber integration. Yash as a People Champion has ensured that his team members are strong in analytics, are customer focused, experimentation is at the centre of actions and results are achieved, thereby showcasing various competencies as a leader. Well done Yash! | F6: Q3 FY 25 | G6: People Champion | H6: 45652 | I6: Commercial | J6: Corporate | K6: 0

Sheet Cross Functional
A1: Receiver Employee Id | B1: Receiver Name | C1: Nominator Employee Id | D1: Nominator Name | E1: Citation | F1: Quarter | G1: Reward Name | H1: Nomination Date | I1: Department | J1: Region | K1: Points
A2: 1591 | B2: Nirmal Abraham | C2: 647 | D2: Vinitha Kompella | E2: Launch of Tata Play Superhit Serials At all levels, this was a project launched well and doing well despite very many challenges. It has been, at idea level, well thought out and well researched product after much debate between extension of classic TV vs standalone product. Example of good partner negotiation wherein for the first time, star agreed to create launch promos and create conceptual promos every month. Star also created special 1 hours edits of all shows despite the large cost. Overall, product idea, partner negotiations, new experiments in GTM, new formats of slate promos, appreciation by subscribers for bringing this product and great numbers makes this a superhit product of the year. All teams involved has put in wholehearted efforts to make this happen. | F2: Q2-FY 25 | G2: Cross Functional Team Award | H2: 45582 | I2: Commercial | J2: South | K2: INR 585.0
A3: 7756 | B3: Mayur Wadulkar | C3: 647 | D3: Vinitha Kompella | E3: Launch of Tata Play Superhit Serials At all levels, this was a project launched well and doing well despite very many challenges. It has been, at idea level, well thought out and well researched product after much debate between extension of classic TV vs standalone product. Example of good partner negotiation wherein for the first time, star agreed to create launch promos and create conceptual promos every month. Star also created special 1 hours edits of all shows despite the large cost. Overall, product idea, partner negotiations, new experiments in GTM, new formats of slate promos, appreciation by subscribers for bringing this product and great numbers makes this a superhit product of the year. All teams involved has put in wholehearted efforts to make this happen. | F3: Q2-FY 25 | G3: Cross Functional Team Award | H3: 45582 | I3: Commercial | J3: South | K3: INR 585.0
A4: 5517 | B4: Bindi Thakkar | C4: 647 | D4: Vinitha Kompella | E4: Launch of Tata Play Superhit Serials At all levels, this was a project launched well and doing well despite very many challenges. It has been, at idea level, well thought out and well researched product after much debate between extension of classic TV vs standalone product. Example of good partner negotiation wherein for the first time, star agreed to create launch promos and create conceptual promos every month. Star also created special 1 hours edits of all shows despite the large cost. Overall, product idea, partner negotiations, new experiments in GTM, new formats of slate promos, appreciation by subscribers for bringing this product and great numbers makes this a superhit product of the year. All teams involved has put in wholehearted efforts to make this happen. | F4: Q2-FY 25 | G4: Cross Functional Team Award | H4: 45582 | I4: Commercial | J4: Corporate | K4: INR 585.0
A5: 2451 | B5: Rajeev Singh | C5: 647 | D5: Vinitha Kompella | E5: Launch of Tata Play Superhit Serials At all levels, this was a project launched well and doing well despite very many challenges. It has been, at idea level, well thought out and well researched product after much debate between extension of classic TV vs standalone product. Example of good partner negotiation wherein for the first time, star agreed to create launch promos and create conceptual promos every month. Star also created special 1 hours edits of all shows despite the large cost. Overall, product idea, partner negotiations, new experiments in GTM, new formats of slate promos, appreciation by subscribers for bringing this product and great numbers makes this a superhit product of the year. All teams involved has put in wholehearted efforts to make this happen. | F5: Q2-FY 25 | G5: Cross Functional Team Award | H5: 45582 | I5: Technology | J5: North | K5: INR 585.0
A6: 6409 | B6: Arpit Mutha | C6: 647 | D6: Vinitha Kompella | E6: Launch of Tata Play Superhit Serials At all levels, this was a project launched well and doing well despite very many challenges. It has been, at idea level, well thought out and well researched product after much debate between extension of classic TV vs standalone product. Example of good partner negotiation wherein for the first time, star agreed to create launch promos and create conceptual promos every month. Star also created special 1 hours edits of all shows despite the large cost. Overall, product idea, partner negotiations, new experiments in GTM, new formats of slate promos, appreciation by subscribers for bringing this product and great numbers makes this a superhit product of the year. All teams involved has put in wholehearted efforts to make this happen. | F6: Q2-FY 25 | G6: Cross Functional Team Award | H6: 45582 | I6: Commercial | J6: Corporate | K6: INR 585.0
A7: 2904 | B7: Ajay Singh | C7: 647 | D7: Vinitha Kompella | E7: Launch of Tata Play Superhit Serials At all levels, this was a project launched well and doing well despite very many challenges. It has been, at idea level, well thought out and well researched product after much debate between extension of classic TV vs standalone product. Example of good partner negotiation wherein for the first time, star agreed to create launch promos and create conceptual promos every month. Star also created special 1 hours edits of all shows despite the large cost. Overall, product idea, partner negotiations, new experiments in GTM, new formats of slate promos, appreciation by subscribers for bringing this product and great numbers makes this a superhit product of the year. All teams involved has put in wholehearted efforts to make this happen. | F7: Q2-FY 25 | G7: Cross Functional Team Award | H7: 45582 | I7: Technology | J7: North | K7: INR 585.0
A8: 5201 | B8: Mohan A | C8: 647 | D8: Vinitha Kompella | E8: Launch of Tata Play Superhit Serials At all levels, this was a project launched well and doing well despite very many challenges. It has been, at idea level, well thought out and well researched product after much debate between extension of classic TV vs standalone product. Example of good partner negotiation wherein for the first time, star agreed to create launch promos and create conceptual promos every month. Star also created special 1 hours edits of all shows despite the large cost. Overall, product idea, partner negotiations, new experiments in GTM, new formats of slate promos, appreciation by subscribers for bringing this product and great numbers makes this a superhit product of the year. All teams involved has put in wholehearted efforts to make this happen. | F8: Q2-FY 25 | G8: Cross Functional Team Award | H8: 45582 | I8: Commercial | J8: South | K8: INR 585.0
A9: 7807 | B9: Zenaida Pereira | C9: 647 | D9: Vinitha Kompella | E9: Launch of Tata Play Superhit Serials At all levels, this was a project launched well and doing well despite very many challenges. It has been, at idea level, well thought out and well researched product after much debate between extension of classic TV vs standalone product. Example of good partner negotiation wherein for the first time, star agreed to create launch promos and create conceptual promos every month. Star also created special 1 hours edits of all shows despite the large cost. Overall, product idea, partner negotiations, new experiments in GTM, new formats of slate promos, appreciation by subscribers for bringing this product and great numbers makes this a superhit product of the year. All teams involved has put in wholehearted efforts to make this happen. | F9: Q2-FY 25 | G9: Cross Functional Team Award | H9: 45582 | I9: Digital Marketing | J9: Corporate | K9: INR 585.0
A10: 6808 | B10: Gurpreet Kaur | C10: 647 | D10: Vinitha Kompella | E10: Launch of Tata Play Superhit Serials At all levels, this was a project launched well and doing well despite very many challenges. It has been, at idea level, well thought out and well researched product after much debate between extension of classic TV vs standalone product. Example of good partner negotiation wherein for the first time, star agreed to create launch promos and create conceptual promos every month. Star also created special 1 hours edits of all shows despite the large cost. Overall, product idea, partner negotiations, new experiments in GTM, new formats of slate promos, appreciation by subscribers for bringing this product and great numbers makes this a superhit product of the year. All teams involved has put in wholehearted efforts to make this happen. | F10: Q2-FY 25 | G10: Cross Functional Team Award | H10: 45582 | I10: Commercial | J10: Corporate | K10: INR 585.0
A11: 7426 | B11: Pooja Sharma | C11: 647 | D11: Vinitha Kompella | E11: Launch of Tata Play Superhit Serials At all levels, this was a project launched well and doing well despite very many challenges. It has been, at idea level, well thought out and well researched product after much debate between extension of classic TV vs standalone product. Example of good partner negotiation wherein for the first time, star agreed to create launch promos and create conceptual promos every month. Star also created special 1 hours edits of all shows despite the large cost. Overall, product idea, partner negotiations, new experiments in GTM, new formats of slate promos, appreciation by subscribers for bringing this product and great numbers makes this a superhit product of the year. All teams involved has put in wholehearted efforts to make this happen. | F11: Q2-FY 25 | G11: Cross Functional Team Award | H11: 45582 | I11: Digital Marketing | J11: Corporate | K11: INR 585.0
A12: 7225 | B12: Divya Shenoy | C12: 647 | D12: Vinitha Kompella | E12: Launch of Tata Play Superhit Serials At all levels, this was a project launched well and doing well despite very many challenges. It has been, at idea level, well thought out and well researched product after much debate between extension of classic TV vs standalone product. Example of good partner negotiation wherein for the first time, star agreed to create launch promos and create conceptual promos every month. Star also created special 1 hours edits of all shows despite the large cost. Overall, product idea, partner negotiations, new experiments in GTM, new formats of slate promos, appreciation by subscribers for bringing this product and great numbers makes this a superhit product of the year. All teams involved has put in wholehearted efforts to make this happen. | F12: Q2-FY 25 | G12: Cross Functional Team Award | H12: 45582 | I12: Content | J12: Corporate | K12: INR 585.0
A13: 7584 | B13: Ankita Pawar | C13: 647 | D13: Vinitha Kompella | E13: Launch of Tata Play Superhit Serials At all levels, this was a project launched well and doing well despite very many challenges. It has been, at idea level, well thought out and well researched product after much debate between extension of classic TV vs standalone product. Example of good partner negotiation wherein for the first time, star agreed to create launch promos and create conceptual promos every month. Star also created special 1 hours edits of all shows despite the large cost. Overall, product idea, partner negotiations, new experiments in GTM, new formats of slate promos, appreciation by subscribers for bringing this product and great numbers makes this a superhit product of the year. All teams involved has put in wholehearted efforts to make this happen. | F13: Q2-FY 25 | G13: Cross Functional Team Award | H13: 45582 | I13: Commercial | J13: Corporate | K13: INR 585.0
... A121: 7457 | B121: Reena Khakre | C121: 6409 | D121: Arpit Mutha | E121: Launch of Tata Play Deiveegam<br/> The launch of Tata Play Deiveegam marked a significant milestone as our first regional devotional service after Aradhana. Recognizing the importance of the South Indian market, we chose Tamil for its enthusiasm and receptiveness to a premium offering, setting the price at ₹60 per month—a first for any Tata Play regional service.<br/>Meticulous research, extensive planning and seamless collaboration across teams to sell the service to the right target group. The results were immediate, with Tata Play Deiveegam setting a new benchmark in the regional devotional space in its launch week. <br/>Key milestones:<br/>Deiveegam was launched at 33% higher price still achieved similar gross adds (14-15k) as Tamil classics and Telugu classics in the first 7 days.<br/>Revenue generated by Deiveegam was significantly higher than other regional services by 16-20%<br/>This launch has set a best practice to be replicated for pricing interventions in other regional services and drive revenue | F121: Q3-FY 25 | G121: Cross Functional Team Award | H121: 45672 | I121: Commercial | J121: South | K121: INR 665
A122: 4013 | B122: Sheeja P.A. | C122: 3469 | D122: Neelam Mane | E122: Fastest to launch & market - Tata Play FanCode Sports marked a landmark launch—the first live sports service in the Specials bouquet and on DTH, bringing F1 back to TV screens after 3+ years. The launch showcased exceptional cross-functional collaboration, effort, and agility across Content, Commercial, Comms, Legal, Technology functions. | F122: Q4-FY 25 | G122: Cross Functional Team Award | H122: 45792 | I122: Commercial | J122: South | K122: 500
A123: 5517 | B123: Bindi Thakkar | C123: 3469 | D123: Neelam Mane | E123: Fastest to launch & market - Tata Play FanCode Sports marked a landmark launch—the first live sports service in the Specials bouquet and on DTH, bringing F1 back to TV screens after 3+ years. The launch showcased exceptional cross-functional collaboration, effort, and agility across Content, Commercial, Comms, Legal, Technology functions. | F123: Q4-FY 25 | G123: Cross Functional Team Award | H123: 45792 | I123: Commercial | J123: Corporate | K123: 500
